Workbook
Name _Hlk139903454: '<35K'!$I$22
Name _Hlk139903454: Master!$I$25

Sheet Master
A1: BSD Technologies - Master | E1: 43951 | H1: HIDE | J1: Forex | K1: 276 | Q1: HIDE | R1: HIDE | S1: HIDE | T1: HIDE | AG1: 2000
A2: Payroll
A3: Wkg Days (Local) | G3: 19 | AJ3: 1.1666667
A4: Wkg Days (Hardware UK) | G4: 20 | Q4: =COLUMN()-2 -> 15 | R4: =COLUMN()-2 -> 16 | S4: =COLUMN()-2 -> 17 | T4: =COLUMN()-2 -> 18 | AJ4: =COLUMN()-2 -> 34 | AK4: =COLUMN()-2 -> 35 | AL4: =COLUMN()-2 -> 36 | BF4: =COLUMN()-2 -> 56
A5: Wkg Days (Design US) | G5: 21 | AW5: DISBURSEMENT DETAIL
A6: Wkg Days (Hardware US) | G6: 21 | J6: =COLUMN()-5 -> 5 | K6: =COLUMN()-5 -> 6 | M6: =COLUMN()-5 -> 8 | N6: =COLUMN()-5 -> 9 | O6: =COLUMN()-5 -> 10 | P6: =COLUMN()-5 -> 11 | Q6: =COLUMN()-5 -> 12 | R6: =COLUMN()-5 -> 13 | S6: =COLUMN()-5 -> 14 | T6: =COLUMN()-5 -> 15 | ... AL6: =COLUMN()-5 -> 33 | AW6: =+AW56 -> 106789 | AX6: =+AX56 -> 44461 | BC6: =SUM(AW6:BB6) -> 151250
B7: Sr.No | C7: date of last increment | D7: last incremnet | E7: # Months Since Last Increment | F7: Emp Code | G7: DOJ (DD/MM/Y) | H7: CURRENT STATUS | I7: Employee Name (CNIC) | J7: Department | K7: Designation | L7: Reporting Manager | M7: MCS | N7: BRAND | O7: Status | P7: Gross Salary | Q7: Basic Salary | R7: H.Rent All | S7: Ut. All | T7: Conv. All | U7: Gross salary with Conveyance | V7: Bonus/Incentive/ Reimbursemet | W7: No.Extra Days | X7: Amount Ex. Days | Y7: DISAPPROVED Absent Days | Z7: Deduction absent Days | AA7: Hourly Rate | AB7: No. of Ded Hours | AC7: Ded Amt Hrs | AD7: Net Gross | AE7: Tax | AF7: EOBI | AG7: Advance | AH7: Loan | AI7: Net Pay | AJ7: Bank Name | AK7: AC Number | AL7: CNIC | AM7: Account Title | AN7: HBL | AO7: Samba | AP7: Cheque | AQ7: IBFT | AR7: Cash | AS7: Payments | AT7: Hold | AU7: Total | AV7: Payment Status | AW7: 1st Batch HBL to HBL 08 May 2024 | AX7: 2nd Batch IBFT 08 May 2024 | AY7: 3rd Batch Cash 08 May 2024 | AZ7: 4th Batch HBL to HBL 10 May 2022 | BA7: 5th Batch IBFT 10 May 2022 | BB7: Column4 | BC7: On Hold | BD7: Total3 | BE7: Difference | BF7: Region | BG7: EOBI Employers' Contribution
B8: 49 | F8: 701 | G8: 43684 | H8: CT | I8: Usman Amin | J8: Sales | K8: International Sales Executive | L8: Umer Shahjahan | M8: HW | N8: BNS | O8: NP | P8: =85000*0 -> 0 | Q8: =P8/160% -> 0 | R8: =40/100*Q8 -> 0 | S8: =10/100*Q8 -> 0 | T8: =10/100*Q8 -> 0 | U8: =Q8+R8+S8+T8 -> 0 | X8: =P8/$G$6*W8 -> 0 | Y8: 0 | Z8: =P8/$G$6*Y8 -> 0 | AA8: =P8/$G$6/9 -> 0 | AC8: =AA8*AB8 -> 0 | AD8: =U8+V8+X8-Z8-AC8 -> 0 | AE8: 0 | AF8: 0 | AG8: 0 | AH8: 0 | AI8: =AD8-AE8-AG8-AH8-AF8 -> 0 | AJ8: Habib Bank Limited | AK8: 0445-79012790-99 | AL8: 35202-7785641-9 | AM8: Muhammad ADA | AN8: =AI8 -> 0 | AS8: =SUM(AN8:AR8) -> 0 | AU8: =+AS8+AT8 -> 0 | AV8: =+AI8-AU8 -> 0 | AZ8: 0 | BA8: 0 | BD8: =SUM(AW8:BC8) -> 0 | BE8: =BD8-AU8 -> 0 | BF8: US | BG8: =AF8/1*5 -> 0
B9: 15 | F9: 191 | G9: 43788 | H9: NJ | I9: Usman | J9: Data Analysis | K9: Trainee | L9: Azmeer | M9: HW | N9: ALL | O9: NP | P9: 15000 | Q9: =P9/160% -> 9375 | R9: =40/100*Q9 -> 3750 | S9: =10/100*Q9 -> 937.5 | T9: =10/100*Q9 -> 937.5 | U9: =Q9+R9+S9+T9 -> 15000 | X9: =P9/$G$3*W9 -> 0 | Y9: 14 | Z9: =P9/$G$3*Y9 -> 11052.632 | AA9: =P9/$G$3/9 -> 87.719298 | AC9: =AA9*AB9 -> 0 | AD9: =U9+V9+X9-Z9-AC9 -> 3947.3684 | AE9: 0 | AF9: 0 | AG9: 0 | AH9: 0 | AI9: =AD9-AE9-AG9-AH9-AF9 -> 3947.3684 | AM9: Muhammad Khawar | AR9: =Master[[#This Row],[Net Pay]] -> 3947.3684 | AS9: =SUM(AN9:AR9) -> 3947.3684 | AU9: =+AS9+AT9 -> 3947.3684 | AV9: Paid | AY9: 3947 | AZ9: 0 | BA9: 0 | BD9: =SUM(AW9:BC9) -> 3947 | BE9: =BD9-AU9 -> -0.36842105 | BF9: Local | BG9: =AF9/1*5 -> 0
F10: 230 | G10: 43945 | I10: Muhammad Yousha | J10: Sales | K10: International Sales Executive | M10: HW | N10: BD | O10: NP | P10: 35000 | Q10: =P10/160% -> 21875 | R10: =40/100*Q10 -> 8750 | S10: =10/100*Q10 -> 2187.5 | T10: =10/100*Q10 -> 2187.5 | U10: =Q10+R10+S10+T10 -> 35000 | X10: =P10/$G$4*W10 -> 0 | Y10: 17 | Z10: =P10/$G$4*Y10 -> 29750 | AA10: =P10/$G$4/9 -> 194.44444 | AC10: =AA10*AB10 -> 0 | AD10: =U10+V10+X10-Z10-AC10 -> 5250 | AE10: 0 | AG10: 0 | AH10: 0 | AI10: =AD10-AE10-AG10-AH10-AF10 -> 5250 | AJ10: Meezan Bank Limited | AK10: PK08MEZN0001130105931538 | AL10: 42301-6418406-5 | AM10: Muhammad Yousha | AQ10: =Master[[#This Row],[Net Pay]] -> 5250 | AS10: =SUM(AN10:AR10) -> 5250 | AU10: =+AS10+AT10 -> 5250 | AV10: Paid | AX10: 5250 | AZ10: 0 | BD10: =SUM(AW10:BC10) -> 5250 | BE10: =BD10-AU10 -> 0 | BF10: UK | BG10: =AF10/1*5 -> 0
F11: 229 | G11: 43942 | I11: Maham Khan | J11: Sales | K11: International Sales Executive | M11: HW | N11: BD | O11: NP | P11: 30000 | Q11: =P11/160% -> 18750 | R11: =40/100*Q11 -> 7500 | S11: =10/100*Q11 -> 1875 | T11: =10/100*Q11 -> 1875 | U11: =Q11+R11+S11+T11 -> 30000 | X11: =P11/$G$4*W11 -> 0 | Y11: 13 | Z11: =P11/$G$4*Y11 -> 19500 | AA11: =P11/$G$4/9 -> 166.66667 | AC11: =AA11*AB11 -> 0 | AD11: =U11+V11+X11-Z11-AC11 -> 10500 | AE11: 0 | AG11: 0 | AH11: 0 | AI11: =AD11-AE11-AG11-AH11-AF11 -> 10500 | AJ11: Habib Bank Limited | AK11: PK70HABB0022567901806303 | AL11: 42301-1466430-6 | AM11: Muhammad Ali | AR11: =AI11 -> 10500 | AS11: =SUM(AN11:AR11) -> 10500 | AU11: =+AS11+AT11 -> 10500 | AV11: Paid | AY11: 10500 | AZ11: 0 | BA11: 0 | BD11: =SUM(AW11:BC11) -> 10500 | BE11: =BD11-AU11 -> 0 | BF11: UK | BG11: =AF11/1*5 -> 0
F12: 228 | I12: Kashan Ahmed | J12: Marketing - SEO | K12: SEO Intern | L12: Muhammad Yousuf | M12: HW | N12: ALL | O12: NP | P12: 35000 | Q12: =P12/160% -> 21875 | R12: =40/100*Q12 -> 8750 | S12: =10/100*Q12 -> 2187.5 | T12: =10/100*Q12 -> 2187.5 | U12: =Q12+R12+S12+T12 -> 35000 | X12: =P12/$G$3*W12 -> 0 | Y12: 14 | Z12: =P12/$G$3*Y12 -> 25789.474 | AA12: =P12/$G$3/9 -> 204.67836 | AC12: =AA12*AB12 -> 0 | AD12: =U12+V12+X12-Z12-AC12 -> 9210.5263 | AE12: 0 | AH12: 0 | AI12: =AD12-AE12-AG12-AH12-AF12 -> 9210.5263 | AJ12: Faysal Bank Limited | AK12: PK62FAYS3573383000001097 | AM12: Kashan Ahmed | AS12: =SUM(AN12:AR12) -> 0 | AT12: =Master[[#This Row],[Net Pay]] -> 9210.5263 | AU12: =+AS12+AT12 -> 9210.5263 | AV12: =+AI12-AU12 -> 0 | AZ12: 0 | BA12: 0 | BC12: 9211 | BD12: =SUM(AW12:BC12) -> 9211 | BE12: =BD12-AU12 -> 0.47368421 | BF12: Local | BG12: =AF12/1*5 -> 0
B13: 16 | F13: 224 | G13: 43861 | I13: Taha Ahmed | J13: Data Analysis | K13: Trainee | L13: Azmeer | M13: HW | N13: ALL | O13: NP | P13: 15000 | Q13: =P13/160% -> 9375 | R13: =40/100*Q13 -> 3750 | S13: =10/100*Q13 -> 937.5 | T13: =10/100*Q13 -> 937.5 | U13: =Q13+R13+S13+T13 -> 15000 | X13: =P13/$G$3*W13 -> 0 | Z13: =P13/$G$3*Y13 -> 0 | AA13: =P13/$G$3/9 -> 87.719298 | AC13: =AA13*AB13 -> 0 | AD13: =U13+V13+X13-Z13-AC13 -> 15000 | AE13: 0 | AG13: 0 | AH13: 0 | AI13: =AD13-AE13-AG13-AH13-AF13 -> 15000 | AJ13: MCB Bank | AK13: PK27MUCB0006802010077407 | AL13: 42201-9587377-5 | AM13: Zameer Ahmed Usmani | AQ13: =AI13 -> 15000 | AS13: =SUM(AN13:AR13) -> 15000 | AU13: =+AS13+AT13 -> 15000 | AV13: Paid | AX13: 14211 | AZ13: 0 | BA13: 789 | BD13: =SUM(AW13:BC13) -> 15000 | BE13: =BD13-AU13 -> 0 | BF13: Local
B14: 7 | F14: 999 | G14: 43496 | H14: CT | I14: Muhammad Farooq | J14: Administration | K14: Electrician | L14: Mubashir | M14: ALL | N14: ALL | O14: NP | P14: 15000 | Q14: =P14/160% -> 9375 | R14: =40/100*Q14 -> 3750 | S14: =10/100*Q14 -> 937.5 | T14: =10/100*Q14 -> 937.5 | U14: =Q14+R14+S14+T14 -> 15000 | X14: =P14/$G$3*W14 -> 0 | Y14: 0 | Z14: =P14/$G$3*Y14 -> 0 | AA14: =P14/$G$3/9 -> 87.719298 | AC14: =AA14*AB14 -> 0 | AD14: =U14+V14+X14-Z14-AC14 -> 15000 | AE14: 0 | AF14: 0 | AG14: 0 | AH14: 0 | AI14: =AD14-AE14-AG14-AH14-AF14 -> 15000 | AJ14: Standard Chartered Bank | AK14: 01994613601 | AM14: Muhammad Farooq | AQ14: =+AI14 -> 15000 | AS14: =SUM(AN14:AR14) -> 15000 | AU14: =+AS14+AT14 -> 15000 | AZ14: 0 | BA14: 15000 | BD14: =SUM(AW14:BC14) -> 15000 | BE14: =BD14-AU14 -> 0 | BF14: Local | BG14: =AF14/1*5 -> 0
B15: 13 | F15: 221 | G15: 43479 | I15: Abdul Sami Kamali | J15: Data Analysis | K15: Trainee | L15: Azmeer | M15: HW | N15: ALL | O15: NP | P15: 25000 | Q15: =P15/160% -> 15625 | R15: =40/100*Q15 -> 6250 | S15: =10/100*Q15 -> 1562.5 | T15: =10/100*Q15 -> 1562.5 | U15: =Q15+R15+S15+T15 -> 25000 | X15: =P15/$G$3*W15 -> 0 | Y15: =7-7 -> 0 | Z15: =P15/$G$3*Y15 -> 0 | AA15: =P15/$G$3/9 -> 146.19883 | AC15: =AA15*AB15 -> 0 | AD15: =U15+V15+X15-Z15-AC15 -> 25000 | AE15: 0 | AG15: 0 | AH15: 0 | AI15: =AD15-AE15-AG15-AH15-AF15 -> 25000 | AJ15: NAYAPAY | AK15: 03313102701 | AL15: 42000-5277363-3 | AM15: Abdul Sami Kamali | AQ15: =AI15 -> 25000 | AS15: =SUM(AN15:AR15) -> 25000 | AU15: =+AS15+AT15 -> 25000 | AV15: Paid | AX15: 25000 | AZ15: 0 | BD15: =SUM(AW15:BC15) -> 25000 | BE15: =BD15-AU15 -> 0 | BF15: Local | BG15: =AF15/1*5 -> 0
B16: 14 | F16: 225 | G16: 43845 | I16: Aun Zaidi | J16: Data Analysis | K16: Trainee | L16: Azmeer | M16: HW | N16: ALL | O16: NP | P16: =15000+5000 -> 20000 | Q16: =P16/160% -> 12500 | R16: =40/100*Q16 -> 5000 | S16: =10/100*Q16 -> 1250 | T16: =10/100*Q16 -> 1250 | U16: =Q16+R16+S16+T16 -> 20000 | X16: =P16/$G$3*W16 -> 0 | Z16: =P16/$G$3*Y16 -> 0 | AA16: =P16/$G$3/9 -> 116.95906 | AC16: =AA16*AB16 -> 0 | AD16: =U16+V16+X16-Z16-AC16 -> 20000 | AE16: 0 | AG16: 0 | AH16: 0 | AI16: =AD16-AE16-AG16-AH16-AF16 -> 20000 | AJ16: Habib Bank Limited | AK16: 08780017874001 | AL16: 42101-6994069-3 | AM16: SYED AJAZ HUSSAIN ZAIDI | AN16: =AI16 -> 20000 | AS16: =SUM(AN16:AR16) -> 20000 | AU16: =+AS16+AT16 -> 20000 | AV16: Paid | AW16: 15789 | AZ16: 4211 | BA16: 0 | BD16: =SUM(AW16:BC16) -> 20000 | BE16: =BD16-AU16 -> 0 | BF16: Local | BG16: =AF16/1*5 -> 0
B17: 22 | C17: 43890 | D17: 10000 | F17: 202 | G17: 43760 | H17: CT | I17: Muhammad Huzaifa Haleem | J17: Marketing - SEO | K17: SEO Intern | L17: Muhammad Yousuf | M17: HW | N17: ALL | O17: NP | P17: =15000+10000 -> 25000 | Q17: =P17/160% -> 15625 | R17: =40/100*Q17 -> 6250 | S17: =10/100*Q17 -> 1562.5 | T17: =10/100*Q17 -> 1562.5 | U17: =Q17+R17+S17+T17 -> 25000 | X17: =P17/$G$3*W17 -> 0 | Y17: 5 | Z17: =P17/$G$3*Y17 -> 6578.9474 | AA17: =P17/$G$3/9 -> 146.19883 | AB17: 15 | AC17: =AA17*AB17 -> 2192.9825 | AD17: =U17+V17+X17-Z17-AC17 -> 16228.07 | AE17: 0 | AF17: 0 | AG17: 0 | AH17: 0 | AI17: =AD17-AE17-AG17-AH17-AF17 -> 16228.07 | AJ17: NAYAPAY | AK17: 03491838351 | AM17: Muhammad Huzaifa Haleem | AS17: =SUM(AN17:AR17) -> 0 | AT17: =Master[[#This Row],[Net Pay]] -> 16228.07 | AU17: =+AS17+AT17 -> 16228.07 | AV17: =+AI17-AU17 -> 0 | AZ17: 0 | BA17: 0 | BC17: 16228 | BD17: =SUM(AW17:BC17) -> 16228 | BE17: =BD17-AU17 -> -0.070175439 | BF17: Local | BG17: =AF17/1*5 -> 0
B18: 23 | F18: 222 | G18: 43861 | I18: Moin Shaikh | J18: Marketing - SEO | K18: SEO Intern | L18: Muhammad Yousuf | M18: HW | N18: ALL | O18: NP | P18: =15000+5000 -> 20000 | Q18: =P18/160% -> 12500 | R18: =40/100*Q18 -> 5000 | S18: =10/100*Q18 -> 1250 | T18: =10/100*Q18 -> 1250 | U18: =Q18+R18+S18+T18 -> 20000 | X18: =P18/$G$3*W18 -> 0 | Z18: =P18/$G$3*Y18 -> 0 | AA18: =P18/$G$3/9 -> 116.95906 | AC18: =AA18*AB18 -> 0 | AD18: =U18+V18+X18-Z18-AC18 -> 20000 | AE18: 0 | AG18: 0 | AH18: 0 | AI18: =AD18-AE18-AG18-AH18-AF18 -> 20000 | AJ18: Meezan Bank Limited | AK18: PK26MEZN0001430109041892 | AL18: 42101-2622969-7 | AM18: MOHAMMAD MOIN UDDIN | AQ18: =AI18 -> 20000 | AS18: =SUM(AN18:AR18) -> 20000 | AU18: =+AS18+AT18 -> 20000 | AV18: =+AI18-AU18 -> 0 | AZ18: 0 | BA18: =18947+1053 -> 20000 | BD18: =SUM(AW18:BC18) -> 20000 | BE18: =BD18-AU18 -> 0 | BF18: Local
B19: 6 | C19: 43738 | D19: 5000 | E19: =ROUND(_xlfn.DAYS($E$1,C19)/30,0) -> 7 | F19: 144 | G19: Apr 2023 | H19: CT | I19: Salman | J19: Administration | K19: Office Boy | L19: Mubashir | M19: ALL | N19: ALL | O19: P | P19: =20000+5000 -> 25000 | Q19: =P19/160% -> 15625 | R19: =40/100*Q19 -> 6250 | S19: =10/100*Q19 -> 1562.5 | T19: =10/100*Q19 -> 1562.5 | U19: =Q19+R19+S19+T19 -> 25000 | X19: =P19/$G$3*W19 -> 0 | Y19: 0 | Z19: =P19/$G$3*Y19 -> 0 | AA19: =P19/$G$3/9 -> 146.19883 | AC19: =AA19*AB19 -> 0 | AD19: =U19+V19+X19-Z19-AC19 -> 25000 | AE19: 0 | AF19: 0 | AG19: 3000 | AH19: 0 | AI19: =AD19-AE19-AG19-AH19-AF19 -> 22000 | AJ19: Habib Bank Limited | AK19: 0017-79008173-03 | AM19: Amanullah | AR19: =+AI19 -> 22000 | AS19: =SUM(AN19:AR19) -> 22000 | AU19: =+AS19+AT19 -> 22000 | AV19: Paid | AY19: 22000 | AZ19: 0 | BA19: 0 | BD19: =SUM(AW19:BC19) -> 22000 | BE19: =BD19-AU19 -> 0 | BF19: Local | BG19: =AF19/1*5 -> 0
B20: 10 | C20: 43830 | D20: 10000 | E20: =ROUND(_xlfn.DAYS($E$1,C20)/30,0) -> 4 | F20: 147 | G20: 43186 | H20: CT | I20: Shahbaz Khan | J20: Data Analysis | K20: Trainee | L20: Azmeer | M20: HW | N20: ALL | O20: P | P20: =10000+5000+10000+10000 -> 35000 | Q20: =P20/160% -> 21875 | R20: =40/100*Q20 -> 8750 | S20: =10/100*Q20 -> 2187.5 | T20: =10/100*Q20 -> 2187.5 | U20: =Q20+R20+S20+T20 -> 35000 | X20: =P20/$G$3*W20 -> 0 | Y20: 4 | Z20: =P20/$G$3*Y20 -> 7368.4211 | AA20: =P20/$G$3/9 -> 204.67836 | AC20: =AA20*AB20 -> 0 | AD20: =U20+V20+X20-Z20-AC20 -> 27631.579 | AE20: 0 | AF20: 0 | AG20: 0 | AH20: 0 | AI20: =AD20-AE20-AG20-AH20-AF20 -> 27631.579 | AJ20: Meezan Bank Limited | AK20: 01750100943393 | AL20: 42201-3746106-1 | AM20: Ali Osama | AR20: =AI20 -> 27631.579 | AS20: =SUM(AN20:AR20) -> 27631.579 | AU20: =+AS20+AT20 -> 27631.579 | AV20: Paid | AY20: 27632 | AZ20: 0 | BA20: 0 | BD20: =SUM(AW20:BC20) -> 27632 | BE20: =BD20-AU20 -> 0.42105263 | BF20: Local | BG20: =AF20/1*5 -> 0
B21: 4 | C21: 43738 | D21: 5000 | E21: =ROUND(_xlfn.DAYS($E$1,C21)/30,0) -> 7 | F21: 168 | G21: 01 Nov 2020 / 12 Sep 2022 | H21: CT | I21: Ammanullah | J21: Administration | K21: Office Boy | L21: Mubashir | M21: ALL | N21: ALL | O21: P | P21: =25000+5000 -> 30000 | Q21: =P21/160% -> 18750 | R21: =40/100*Q21 -> 7500 | S21: =10/100*Q21 -> 1875 | T21: =10/100*Q21 -> 1875 | U21: =Q21+R21+S21+T21 -> 30000 | X21: =P21/$G$3*W21 -> 0 | Y21: 0 | Z21: =P21/$G$3*Y21 -> 0 | AA21: =P21/$G$3/9 -> 175.4386 | AC21: =AA21*AB21 -> 0 | AD21: =U21+V21+X21-Z21-AC21 -> 30000 | AE21: 0 | AF21: 0 | AG21: 4000 | AH21: 5000 | AI21: =AD21-AE21-AG21-AH21-AF21 -> 21000 | AJ21: Habib Bank Limited | AK21: 0017-79008173-03 | AL21: 32404-9685630-7 | AM21: Amanullah | AN21: =+AI21 -> 21000 | AS21: =SUM(AN21:AR21) -> 21000 | AU21: =+AS21+AT21 -> 21000 | AV21: Paid | AW21: 21000 | BA21: 0 | BD21: =SUM(AW21:BC21) -> 21000 | BE21: =BD21-AU21 -> 0 | BF21: Local | BG21: =AF21/1*5 -> 0
B22: 5 | C22: 43738 | D22: 5000 | E22: =ROUND(_xlfn.DAYS($E$1,C22)/30,0) -> 7 | F22: 176 | G22: 43298 | H22: CT | I22: Muhammad Irfan | J22: Administration | K22: Office Boy | L22: Mubashir | M22: ALL | N22: ALL | O22: P | P22: =20000+5000+5000 -> 30000 | Q22: =P22/160% -> 18750 | R22: =40/100*Q22 -> 7500 | S22: =10/100*Q22 -> 1875 | T22: =10/100*Q22 -> 1875 | U22: =Q22+R22+S22+T22 -> 30000 | X22: =P22/$G$3*W22 -> 0 | Y22: 0 | Z22: =P22/$G$3*Y22 -> 0 | AA22: =P22/$G$3/9 -> 175.4386 | AC22: =AA22*AB22 -> 0 | AD22: =U22+V22+X22-Z22-AC22 -> 30000 | AE22: 0 | AF22: 0 | AG22: 0 | AH22: 0 | AI22: =AD22-AE22-AG22-AH22-AF22 -> 30000 | AM22: Amanullah | AR22: =+AI22 -> 30000 | AS22: =SUM(AN22:AR22) -> 30000 | AU22: =+AS22+AT22 -> 30000 | AV22: Paid | AY22: 30000 | BA22: 0 | BD22: =SUM(AW22:BC22) -> 30000 | BE22: =BD22-AU22 -> 0 | BF22: Local | BG22: =AF22/1*5 -> 0
B23: 11 | C23: 43830 | D23: 10000 | E23: =ROUND(_xlfn.DAYS($E$1,C23)/30,0) -> 4 | F23: 173 | G23: 43270 | H23: CT | I23: Mohammad Uzair | J23: Data Analysis | K23: Trainee | L23: Azmeer | M23: HW | N23: ALL | O23: P | P23: =15000+10000+10000 -> 35000 | Q23: =P23/160% -> 21875 | R23: =40/100*Q23 -> 8750 | S23: =10/100*Q23 -> 2187.5 | T23: =10/100*Q23 -> 2187.5 | U23: =Q23+R23+S23+T23 -> 35000 | X23: =P23/$G$3*W23 -> 0 | Y23: 0 | Z23: =P23/$G$3*Y23 -> 0 | AA23: =P23/$G$3/9 -> 204.67836 | AC23: =AA23*AB23 -> 0 | AD23: =U23+V23+X23-Z23-AC23 -> 35000 | AE23: 0 | AF23: 0 | AG23: 0 | AH23: 0 | AI23: =AD23-AE23-AG23-AH23-AF23 -> 35000 | AJ23: Habib Bank Limited | AK23: 0017-79009071-03 | AL23: 42201-0578753-5 | AM23: JAHANGIR HUSSAIN | AN23: =AI23 -> 35000 | AS23: =SUM(AN23:AR23) -> 35000 | AU23: =+AS23+AT23 -> 35000 | AV23: Paid | AW23: 35000 | AZ23: 0 | BA23: 0 | BD23: =SUM(AW23:BC23) -> 35000 | BE23: =BD23-AU23 -> 0 | BF23: Local | BG23: =AF23/1*5 -> 0
B24: 12 | C24: 43830 | D24: 10000 | E24: =ROUND(_xlfn.DAYS($E$1,C24)/30,0) -> 4 | F24: 174 | G24: 43277 | H24: CT | I24: Sammad | J24: Data Analysis | K24: Trainee | L24: Azmeer | M24: HW | N24: ALL | O24: P | P24: =15000+10000+10000 -> 35000 | Q24: =P24/160% -> 21875 | R24: =40/100*Q24 -> 8750 | S24: =10/100*Q24 -> 2187.5 | T24: =10/100*Q24 -> 2187.5 | U24: =Q24+R24+S24+T24 -> 35000 | X24: =P24/$G$3*W24 -> 0 | Y24: 0 | Z24: =P24/$G$3*Y24 -> 0 | AA24: =P24/$G$3/9 -> 204.67836 | AC24: =AA24*AB24 -> 0 | AD24: =U24+V24+X24-Z24-AC24 -> 35000 | AE24: 0 | AF24: 0 | AG24: 0 | AH24: 0 | AI24: =AD24-AE24-AG24-AH24-AF24 -> 35000 | AJ24: Habib Bank Limited | AK24: 0017-79008732-03 | AL24: 42201-2352763-3 | AM24: Samad Khan | AN24: =AI24 -> 35000 | AS24: =SUM(AN24:AR24) -> 35000 | AU24: =+AS24+AT24 -> 35000 | AV24: Paid | AW24: 35000 | AZ24: 0 | BA24: 0 | BD24: =SUM(AW24:BC24) -> 35000 | BE24: =BD24-AU24 -> 0 | BF24: Local | BG24: =AF24/1*5 -> 0
B25: 36 | F25: 226 | G25: 43862 | I25: Syed Shabi ul Hasan Zaidi | J25: Sales | K25: International Sales Executive | L25: Wasif Azhar | M25: HW | N25: GIT | O25: NP | P25: =20000+20000 -> 40000 | Q25: =P25/160% -> 25000 | R25: =40/100*Q25 -> 10000 | S25: =10/100*Q25 -> 2500 | T25: =10/100*Q25 -> 2500 | U25: =Q25+R25+S25+T25 -> 40000 | X25: =P25/$G$6*W25 -> 0 | Y25: =2-1 -> 1 | Z25: =P25/$G$6*Y25 -> 1904.7619 | AA25: =P25/$G$6/9 -> 211.64021 | AC25: =AA25*AB25 -> 0 | AD25: =U25+V25+X25-Z25-AC25 -> 38095.238 | AE25: 0 | AG25: 0 | AH25: 0 | AI25: =AD25-AE25-AG25-AH25-AF25 -> 38095.238 | AJ25: Bank Al Habib | AK25: 10680048013966014 | AL25: 42101-5066364-1 | AM25: Syed Shabi Ul Hasan Zaidi | AQ25: =AI25 -> 38095.238 | AS25: =SUM(AN25:AR25) -> 38095.238 | AU25: =+AS25+AT25 -> 38095.238 | AV25: =+AI25-AU25 -> 0 | AZ25: 0 | BA25: 38095 | BD25: =SUM(AW25:BC25) -> 38095 | BE25: =BD25-AU25 -> -0.23809524 | BF25: US
B26: 34 | C26: 43830 | D26: 9000 | E26: =ROUND(_xlfn.DAYS($E$1,C26)/30,0) -> 4 | F26: 187 | G26: 43692 | H26: CT | I26: Nahyan Hussain | J26: Sales | K26: International Sales Executive | L26: Wasif Azhar | M26: HW | N26: GIT | O26: NP | P26: =36000+9000 -> 45000 | Q26: =P26/160% -> 28125 | R26: =40/100*Q26 -> 11250 | S26: =10/100*Q26 -> 2812.5 | T26: =10/100*Q26 -> 2812.5 | U26: =Q26+R26+S26+T26 -> 45000 | X26: =P26/$G$6*W26 -> 0 | Y26: 1 | Z26: =P26/$G$6*Y26 -> 2142.8571 | AA26: =P26/$G$6/9 -> 238.09524 | AB26: =17*0 -> 0 | AC26: =AA26*AB26 -> 0 | AD26: =U26+V26+X26-Z26-AC26 -> 42857.143 | AE26: 0 | AF26: 0 | AG26: 0 | AH26: 0 | AI26: =AD26-AE26-AG26-AH26-AF26 -> 42857.143 | AJ26: Meezan Bank Limited | AK26: 99530105424627 | AL26: 42501-9444333-5 | AM26: Asad Hussain | AQ26: =AI26 -> 42857.143 | AS26: =SUM(AN26:AR26) -> 42857.143 | AU26: =+AS26+AT26 -> 42857.143 | AV26: =+AI26-AU26 -> 0 | AZ26: 0 | BA26: 42857 | BD26: =SUM(AW26:BC26) -> 42857 | BE26: =BD26-AU26 -> -0.14285714 | BF26: US | BG26: =AF26/1*5 -> 0
F27: 22 | G27: 43937 | I27: Shahmeer Shaikh | J27: Production - Design | M27: Portal | N27: Portal | O27: P | P27: 100000 | Q27: =P27/160% -> 62500 | R27: =40/100*Q27 -> 25000 | S27: =10/100*Q27 -> 6250 | T27: =10/100*Q27 -> 6250 | U27: =Q27+R27+S27+T27 -> 100000 | X27: =P27/$G$6*W27 -> 0 | Y27: 6 | Z27: =P27/$G$6*Y27 -> 28571.429 | AA27: =P27/$G$6/9 -> 529.10053 | AC27: =AA27*AB27 -> 0 | AD27: =U27+V27+X27-Z27-AC27 -> 71428.571 | AE27: 0 | AG27: 0 | AH27: 0 | AI27: =AD27-AE27-AG27-AH27-AF27 -> 71428.571 | AJ27: Habib Bank Limited | AK27: 0017-79008990-03 | AL27: 42101-2904934-9 | AM27: Shahmeer Shaikh | AN27: =Master[[#This Row],[Net Pay]] -> 71428.571 | AS27: =SUM(AN27:AR27) -> 71428.571 | AU27: =+AS27+AT27 -> 71428.571 | AV27: =+AI27-AU27 -> 0 | AZ27: 71429 | BA27: 0 | BD27: =SUM(AW27:BC27) -> 71429 | BE27: =BD27-AU27 -> 0.42857143 | BF27: US | BG27: =AF27/1*5 -> 0
B28: 3 | F28: 204 | G28: 43769 | H28: NJ | I28: Abdul Hadi Ravasia | J28: Accounts | K28: Accounts Executive | L28: Farooq Khan | M28: ALL | N28: ALL | O28: NP | P28: 45000 | Q28: =P28/160% -> 28125 | R28: =40/100*Q28 -> 11250 | S28: =10/100*Q28 -> 2812.5 | T28: =10/100*Q28 -> 2812.5 | U28: =Q28+R28+S28+T28 -> 45000 | X28: =P28/$G$3*W28 -> 0 | Y28: 0 | Z28: =P28/$G$3*Y28 -> 0 | AA28: =P28/$G$3/9 -> 263.15789 | AC28: =AA28*AB28 -> 0 | AD28: =U28+V28+X28-Z28-AC28 -> 45000 | AE28: 0 | AF28: 0 | AG28: 10000 | AH28: 0 | AI28: =AD28-AE28-AG28-AH28-AF28 -> 35000 | AJ28: Meezan Bank Limited | AK28: PK88MEZN0099180107164710 | AL28: 42101-0956661-3 | AM28: ABDUL HADI RAVASIA | AQ28: =AI28 -> 35000 | AS28: =SUM(AN28:AR28) -> 35000 | AU28: =+AS28+AT28 -> 35000 | AV28: =+AI28-AU28 -> 0 | AZ28: 0 | BA28: 35000 | BD28: =SUM(AW28:BC28) -> 35000 | BE28: =BD28-AU28 -> 0 | BF28: Local | BG28: =AF28/1*5 -> 0
B29: 29 | C29: 43890 | D29: 15000 | E29: =ROUND(_xlfn.DAYS($E$1,C29)/30,0) -> 2 | F29: 97 | G29: 43481 | H29: CT | I29: Waniya | J29: Sales | K29: Trainee | L29: Husnain | M29: HW | N29: BD | O29: P | P29: =15000+5000+5000+5000+15000 -> 45000 | Q29: =P29/160% -> 28125 | R29: =40/100*Q29 -> 11250 | S29: =10/100*Q29 -> 2812.5 | T29: =10/100*Q29 -> 2812.5 | U29: =Q29+R29+S29+T29 -> 45000 | X29: =P29/$G$4*W29 -> 0 | Y29: 0 | Z29: =P29/$G$4*Y29 -> 0 | AA29: =P29/$G$4/9 -> 250 | AC29: =AA29*AB29 -> 0 | AD29: =U29+V29+X29-Z29-AC29 -> 45000 | AE29: 0 | AF29: 0 | AG29: 0 | AH29: 0 | AI29: =AD29-AE29-AG29-AH29-AF29 -> 45000 | AJ29: Habib Bank Limited | AK29: 0017-79009274-03 | AL29: 42201-9133325-0 | AM29: Wania Qureshi | AN29: =AI29 -> 45000 | AS29: =SUM(AN29:AR29) -> 45000 | AU29: =+AS29+AT29 -> 45000 | AV29: =+AI29-AU29 -> 0 | AZ29: 45000 | BA29: 0 | BD29: =SUM(AW29:BC29) -> 45000 | BE29: =BD29-AU29 -> 0 | BF29: UK | BG29: =AF29/1*5 -> 0
B30: 8 | F30: 223 | G30: 43866 | I30: Arsalan Ahmed | J30: HR | L30: Wahaj Qureshi | M30: ALL | N30: ALL | O30: NP | P30: 50000 | Q30: =P30/160% -> 31250 | R30: =40/100*Q30 -> 12500 | S30: =10/100*Q30 -> 3125 | T30: =10/100*Q30 -> 3125 | U30: =Q30+R30+S30+T30 -> 50000 | X30: =P30/$G$3*W30 -> 0 | Y30: 1 | Z30: =P30/$G$3*Y30 -> 2631.5789 | AA30: =P30/$G$3/9 -> 292.39766 | AC30: =AA30*AB30 -> 0 | AD30: =U30+V30+X30-Z30-AC30 -> 47368.421 | AE30: 0 | AH30: 5000 | AI30: =AD30-AE30-AG30-AH30-AF30 -> 42368.421 | AJ30: Dubai Islamic Bank | AK30: PK30DUIB0000000808360001 | AL30: 42101-6288236-7 | AM30: Arsalan Ahmed | AQ30: =AI30 -> 42368.421 | AS30: =SUM(AN30:AR30) -> 42368.421 | AU30: =+AS30+AT30 -> 42368.421 | AV30: =+AI30-AU30 -> 0 | AZ30: 0 | BA30: 42368 | BD30: =SUM(AW30:BC30) -> 42368 | BE30: =BD30-AU30 -> -0.42105263 | BF30: Local
F31: 164 | I31: Hareem Fatima | J31: HR | L31: Wahaj Qureshi | M31: ALL | N31: ALL | O31: P | P31: 50000 | Q31: =P31/160% -> 31250 | R31: =40/100*Q31 -> 12500 | S31: =10/100*Q31 -> 3125 | T31: =10/100*Q31 -> 3125 | U31: =Q31+R31+S31+T31 -> 50000 | X31: =P31/$G$3*W31 -> 0 | Y31: 16 | Z31: =P31/$G$3*Y31 -> 42105.263 | AA31: =P31/$G$3/9 -> 292.39766 | AC31: =AA31*AB31 -> 0 | AD31: =U31+V31+X31-Z31-AC31 -> 7894.7368 | AE31: 0 | AF31: 250 | AG31: 0 | AH31: 0 | AI31: =AD31-AE31-AG31-AH31-AF31 -> 7644.7368 | AJ31: Habib Bank Limited | AK31: 0017-79009306-03 | AL31: 42201-75434755-2 | AM31: Hareem Fatima | AN31: =Master[[#This Row],[Net Pay]] -> 7644.7368 | AS31: =SUM(AN31:AR31) -> 7644.7368 | AU31: =+AS31+AT31 -> 7644.7368 | AV31: =+AI31-AU31 -> 0 | BA31: 0 | BB31: 7645 | BD31: =SUM(AW31:BC31) -> 7645 | BE31: =BD31-AU31 -> 0.26315789 | BF31: Local | BG31: =AF31/1*5 -> 1250
B32: 20 | F32: 149 | G32: 43622 | H32: CT | I32: Muhammad Yousuf | J32: Marketing - SEO | K32: SEO Manager | L32: Umair Kaim Khani | M32: HW | N32: ALL | O32: NP | P32: 50000 | Q32: =P32/160% -> 31250 | R32: =40/100*Q32 -> 12500 | S32: =10/100*Q32 -> 3125 | T32: =10/100*Q32 -> 3125 | U32: =Q32+R32+S32+T32 -> 50000 | X32: =P32/$G$3*W32 -> 0 | Y32: 0 | Z32: =P32/$G$3*Y32 -> 0 | AA32: =P32/$G$3/9 -> 292.39766 | AC32: =AA32*AB32 -> 0 | AD32: =U32+V32+X32-Z32-AC32 -> 50000 | AE32: 0 | AF32: 0 | AG32: 0 | AH32: 0 | AI32: =AD32-AE32-AG32-AH32-AF32 -> 50000 | AJ32: Habib Bank Limited | AK32: 2443-79014079-03 | AL32: 42101-4708804-9 | AM32: Muhammad yousuf | AN32: =Master[[#This Row],[Net Pay]] -> 50000 | AS32: =SUM(AN32:AR32) -> 50000 | AU32: =+AS32+AT32 -> 50000 | AV32: =+AI32-AU32 -> 0 | AZ32: 50000 | BA32: 0 | BD32: =SUM(AW32:BC32) -> 50000 | BE32: =BD32-AU32 -> 0 | BF32: Local | BG32: =AF32/1*5 -> 0
B33: 25 | C33: 43708 | D33: 15000 | E33: =ROUND(_xlfn.DAYS($E$1,C33)/30,0) -> 8 | F33: 113 | G33: 43109 | H33: CT | I33: Affan Khan | J33: Procurement | K33: Procurrement Executive | L33: Khawaja | M33: HW | N33: BD | O33: P | P33: =15000+5000+5000+10000+15000 -> 50000 | Q33: =P33/160% -> 31250 | R33: =40/100*Q33 -> 12500 | S33: =10/100*Q33 -> 3125 | T33: =10/100*Q33 -> 3125 | U33: =Q33+R33+S33+T33 -> 50000 | X33: =P33/$G$4*W33 -> 0 | Y33: 0 | Z33: =P33/$G$4*Y33 -> 0 | AA33: =P33/$G$4/9 -> 277.77778 | AC33: =AA33*AB33 -> 0 | AD33: =U33+V33+X33-Z33-AC33 -> 50000 | AE33: 0 | AF33: 0 | AG33: 0 | AH33: 0 | AI33: =AD33-AE33-AG33-AH33-AF33 -> 50000 | AJ33: Habib Bank Limited | AK33: 0017-79008738-03 | AL33: 42101-4961812-5 | AM33: AFFAN KHAN | AN33: =AI33 -> 50000 | AS33: =SUM(AN33:AR33) -> 50000 | AU33: =+AS33+AT33 -> 50000 | AV33: =+AI33-AU33 -> 0 | AZ33: 50000 | BA33: 0 | BD33: =SUM(AW33:BC33) -> 50000 | BE33: =BD33-AU33 -> 0 | BF33: UK | BG33: =AF33/1*5 -> 0
B34: 33 | C34: 43708 | D34: 10000 | E34: =ROUND(_xlfn.DAYS($E$1,C34)/30,0) -> 8 | F34: 155 | G34: 43207 | H34: CT | I34: Syed Sumair Hussain | J34: Sales | K34: International Sales Executive | L34: Wasif Azhar | M34: HW | N34: GIT | O34: P | P34: =40000+10000 -> 50000 | Q34: =P34/160% -> 31250 | R34: =40/100*Q34 -> 12500 | S34: =10/100*Q34 -> 3125 | T34: =10/100*Q34 -> 3125 | U34: =Q34+R34+S34+T34 -> 50000 | X34: =P34/$G$6*W34 -> 0 | Y34: 0 | Z34: =P34/$G$6*Y34 -> 0 | AA34: =P34/$G$6/9 -> 264.55026 | AC34: =AA34*AB34 -> 0 | AD34: =U34+V34+X34-Z34-AC34 -> 50000 | AE34: 0 | AF34: 0 | AG34: 0 | AH34: 0 | AI34: =AD34-AE34-AG34-AH34-AF34 -> 50000 | AJ34: Habib Bank Limited | AK34: 0017-79008896-03 | AL34: 42201-9040498-9 | AM34: Syed Sumair | AN34: =AI34 -> 50000 | AS34: =SUM(AN34:AR34) -> 50000 | AU34: =+AS34+AT34 -> 50000 | AV34: =+AI34-AU34 -> 0 | AZ34: 50000 | BA34: 0 | BD34: =SUM(AW34:BC34) -> 50000 | BE34: =BD34-AU34 -> 0 | BF34: US | BG34: =AF34/1*5 -> 0
B35: 39 | C35: 43830 | D35: 15000 | E35: =ROUND(_xlfn.DAYS($E$1,C35)/30,0) -> 4 | F35: 150 | G35: 43186 | H35: CT | I35: Humayoun Khan | J35: Procurement | K35: Procurement Executive | L35: Nadeem Akhtar | M35: HW | N35: GIT | O35: P | P35: =15000+10000+10000+15000 -> 50000 | Q35: =P35/160% -> 31250 | R35: =40/100*Q35 -> 12500 | S35: =10/100*Q35 -> 3125 | T35: =10/100*Q35 -> 3125 | U35: =Q35+R35+S35+T35 -> 50000 | X35: =P35/$G$4*W35 -> 0 | Y35: 0 | Z35: =P35/$G$4*Y35 -> 0 | AA35: =P35/$G$4/9 -> 277.77778 | AC35: =AA35*AB35 -> 0 | AD35: =U35+V35+X35-Z35-AC35 -> 50000 | AE35: 0 | AF35: 0 | AG35: 0 | AH35: 0 | AI35: =AD35-AE35-AG35-AH35-AF35 -> 50000 | AJ35: Habib Bank Limited | AK35: 0017-79008735-03 | AL35: 44101-9793357-1 | AM35: HUMAYOUN KHAN | AN35: =AI35 -> 50000 | AS35: =SUM(AN35:AR35) -> 50000 | AU35: =+AS35+AT35 -> 50000 | AV35: =+AI35-AU35 -> 0 | AZ35: 50000 | BA35: 0 | BD35: =SUM(AW35:BC35) -> 50000 | BE35: =BD35-AU35 -> 0 | BF35: UK | BG35: =AF35/1*5 -> 0
B36: 19 | C36: 43646 | D36: 20000 | E36: =ROUND(_xlfn.DAYS($E$1,C36)/30,0) -> 10 | F36: 26 | G36: 42601 | H36: CT | I36: Azmeer Sheikh | J36: Data Analysis | K36: Trainee | L36: Umair Kaim Khani | M36: HW | N36: ALL | O36: P | P36: 60000 | Q36: =P36/160% -> 37500 | R36: =40/100*Q36 -> 15000 | S36: =10/100*Q36 -> 3750 | T36: =10/100*Q36 -> 3750 | U36: =Q36+R36+S36+T36 -> 60000 | X36: =P36/$G$3*W36 -> 0 | Y36: 0 | Z36: =P36/$G$3*Y36 -> 0 | AA36: =P36/$G$3/9 -> 350.87719 | AC36: =AA36*AB36 -> 0 | AD36: =U36+V36+X36-Z36-AC36 -> 60000 | AE36: 0 | AF36: 0 | AG36: 0 | AH36: 5000 | AI36: =AD36-AE36-AG36-AH36-AF36 -> 55000 | AJ36: Habib Bank Limited | AK36: 0017-79009066-03 | AL36: 42101-2818484-9 | AM36: AZMEER SHAIKH | AN36: =AI36 -> 55000 | AS36: =SUM(AN36:AR36) -> 55000 | AU36: =+AS36+AT36 -> 55000 | AV36: =+AI36-AU36 -> 0 | AZ36: 55000 | BA36: 0 | BD36: =SUM(AW36:BC36) -> 55000 | BE36: =BD36-AU36 -> 0 | BF36: Local | BG36: =AF36/1*5 -> 0
B37: 38 | C37: 43830 | D37: 15000 | E37: =ROUND(_xlfn.DAYS($E$1,C37)/30,0) -> 4 | F37: 8 | G37: 42308 | H37: CT | I37: Khawar Qureshi | J37: Procurement | K37: Procurement Executive | L37: Nadeem Akhtar | M37: HW | N37: ITN | O37: P | P37: =50000+15000 -> 65000 | Q37: =P37/160% -> 40625 | R37: =40/100*Q37 -> 16250 | S37: =10/100*Q37 -> 4062.5 | T37: =10/100*Q37 -> 4062.5 | U37: =Q37+R37+S37+T37 -> 65000 | X37: =P37/$G$4*W37 -> 0 | Y37: 0 | Z37: =P37/$G$4*Y37 -> 0 | AA37: =P37/$G$4/9 -> 361.11111 | AC37: =AA37*AB37 -> 0 | AD37: =U37+V37+X37-Z37-AC37 -> 65000 | AE37: 0 | AF37: 250 | AG37: 0 | AH37: 0 | AI37: =AD37-AE37-AG37-AH37-AF37 -> 64750 | AJ37: Habib Bank Limited | AK37: 0017-79008521-03 | AL37: 42201-8365639-3 | AM37: Muhammad Khawar | AN37: =AI37 -> 64750 | AS37: =SUM(AN37:AR37) -> 64750 | AU37: =+AS37+AT37 -> 64750 | AV37: =+AI37-AU37 -> 0 | AZ37: 64750 | BA37: 0 | BD37: =SUM(AW37:BC37) -> 64750 | BE37: =BD37-AU37 -> 0 | BF37: UK | BG37: =AF37/1*5 -> 1250
B38: 28 | C38: 43616 | D38: 35000 | E38: =ROUND(_xlfn.DAYS($E$1,C38)/30,0) -> 11 | F38: 107 | G38: 43508 | H38: CT | I38: Hussnain ali farooqi | J38: Sales | K38: International Sales Executive | L38: Wahaj Qureshi | M38: HW | N38: BD | O38: P | P38: =70000-35000+35000 -> 70000 | Q38: =P38/160% -> 43750 | R38: =40/100*Q38 -> 17500 | S38: =10/100*Q38 -> 4375 | T38: =10/100*Q38 -> 4375 | U38: =Q38+R38+S38+T38 -> 70000 | X38: =P38/$G$4*W38 -> 0 | Y38: 0 | Z38: =P38/$G$4*Y38 -> 0 | AA38: =P38/$G$4/9 -> 388.88889 | AC38: =AA38*AB38 -> 0 | AD38: =U38+V38+X38-Z38-AC38 -> 70000 | AE38: 241.2 | AF38: 0 | AG38: 0 | AH38: 0 | AI38: =AD38-AE38-AG38-AH38-AF38 -> 69758.8 | AJ38: Habib Bank Limited | AK38: 0017-79009306-03 | AL38: 31304-0957356-1 | AM38: Hareem Fatima | AN38: =AI38 -> 69758.8 | AS38: =SUM(AN38:AR38) -> 69758.8 | AU38: =+AS38+AT38 -> 69758.8 | AV38: =+AI38-AU38 -> 0 | AZ38: 69759 | BA38: 0 | BD38: =SUM(AW38:BC38) -> 69759 | BE38: =BD38-AU38 -> 0.2 | BF38: UK | BG38: =AF38/1*5 -> 0
B39: 9 | C39: 43861 | D39: 15000 | E39: =ROUND(_xlfn.DAYS($E$1,C39)/30,0) -> 3 | F39: 135 | G39: 43524 | H39: CT | I39: Farhad Muhammad Khan | J39: IT | K39: Support Engineer | L39: Wahaj Qureshi | M39: ALL | N39: ALL | O39: P | P39: =50000+15000+15000 -> 80000 | Q39: =P39/160% -> 50000 | R39: =40/100*Q39 -> 20000 | S39: =10/100*Q39 -> 5000 | T39: =10/100*Q39 -> 5000 | U39: =Q39+R39+S39+T39 -> 80000 | X39: =P39/$G$3*W39 -> 0 | Y39: 0 | Z39: =P39/$G$3*Y39 -> 0 | AA39: =P39/$G$3/9 -> 467.83626 | AC39: =AA39*AB39 -> 0 | AD39: =U39+V39+X39-Z39-AC39 -> 80000 | AE39: 467.8 | AF39: 0 | AG39: 0 | AH39: 0 | AI39: =AD39-AE39-AG39-AH39-AF39 -> 79532.2 | AJ39: Meezan Bank Limited | AK39: PK40MEZN0099090107351285 | AL39: 42401-0634733-9 | AM39: Farhad Muhammad Khan | AQ39: =AI39 -> 79532.2 | AS39: =SUM(AN39:AR39) -> 79532.2 | AU39: =+AS39+AT39 -> 79532.2 | AV39: =+AI39-AU39 -> 0 | AZ39: 0 | BA39: 79532 | BD39: =SUM(AW39:BC39) -> 79532 | BE39: =BD39-AU39 -> -0.2 | BF39: Local | BG39: =AF39/1*5 -> 0
B40: 26 | C40: 43708 | D40: 40000 | E40: =ROUND(_xlfn.DAYS($E$1,C40)/30,0) -> 8 | F40: 133 | G40: 21 | H40: CT | I40: Eraj Khalid | J40: Sales | K40: Sales/CSE | L40: Husnain | M40: HW | N40: BD | O40: P | P40: =20000+10000+10000+40000 -> 80000 | Q40: =P40/160% -> 50000 | R40: =40/100*Q40 -> 20000 | S40: =10/100*Q40 -> 5000 | T40: =10/100*Q40 -> 5000 | U40: =Q40+R40+S40+T40 -> 80000 | X40: =P40/$G$4*W40 -> 0 | Y40: 0 | Z40: =P40/$G$4*Y40 -> 0 | AA40: =P40/$G$4/9 -> 444.44444 | AC40: =AA40*AB40 -> 0 | AD40: =U40+V40+X40-Z40-AC40 -> 80000 | AE40: 487.4 | AF40: 250 | AG40: 0 | AH40: 0 | AI40: =AD40-AE40-AG40-AH40-AF40 -> 79262.6 | AJ40: Habib Bank Limited | AK40: 0017-79008733-03 | AL40: 42201-1039448-6 | AM40: ERAJ KHALID | AN40: =AI40 -> 79262.6 | AS40: =SUM(AN40:AR40) -> 79262.6 | AU40: =+AS40+AT40 -> 79262.6 | AV40: =+AI40-AU40 -> 0 | AZ40: 79263 | BA40: 0 | BD40: =SUM(AW40:BC40) -> 79263 | BE40: =BD40-AU40 -> 0.4 | BF40: UK | BG40: =AF40/1*5 -> 1250
B41: 42 | C41: 43830 | D41: 30000 | E41: =ROUND(_xlfn.DAYS($E$1,C41)/30,0) -> 4 | F41: 182 | G41: 43404 | H41: CT | I41: Muhammad Haris Khan | J41: Sales | K41: International Sales Executive | L41: Nadeem Akhtar | M41: HW | N41: ITN | O41: P | P41: =50000+30000 -> 80000 | Q41: =P41/160% -> 50000 | R41: =40/100*Q41 -> 20000 | S41: =10/100*Q41 -> 5000 | T41: =10/100*Q41 -> 5000 | U41: =Q41+R41+S41+T41 -> 80000 | X41: =P41/$G$4*W41 -> 0 | Y41: 0 | Z41: =P41/$G$4*Y41 -> 0 | AA41: =P41/$G$4/9 -> 444.44444 | AC41: =AA41*AB41 -> 0 | AD41: =U41+V41+X41-Z41-AC41 -> 80000 | AE41: 492 | AF41: 0 | AG41: 0 | AH41: 0 | AI41: =AD41-AE41-AG41-AH41-AF41 -> 79508 | AJ41: Habib Bank Limited | AK41: 0017-79008955-03 | AL41: 42201-9177582-9 | AM41: Muhammad Haris | AN41: =AI41 -> 79508 | AS41: =SUM(AN41:AR41) -> 79508 | AU41: =+AS41+AT41 -> 79508 | AV41: =+AI41-AU41 -> 0 | AZ41: 79508 | BA41: 0 | BD41: =SUM(AW41:BC41) -> 79508 | BE41: =BD41-AU41 -> 0 | BF41: UK | BG41: =AF41/1*5 -> 0
B42: 27 | C42: 43890 | D42: 15000 | E42: =ROUND(_xlfn.DAYS($E$1,C42)/30,0) -> 2 | F42: 82 | G42: 42874 | H42: CT | I42: Fatima Hasan | J42: Sales | K42: International Sales Executive | L42: Husnain | M42: HW | N42: BD | O42: P | P42: =75000+15000 -> 90000 | Q42: =P42/160% -> 56250 | R42: =40/100*Q42 -> 22500 | S42: =10/100*Q42 -> 5625 | T42: =10/100*Q42 -> 5625 | U42: =Q42+R42+S42+T42 -> 90000 | X42: =P42/$G$4*W42 -> 0 | Y42: 0 | Z42: =P42/$G$4*Y42 -> 0 | AA42: =P42/$G$4/9 -> 500 | AC42: =AA42*AB42 -> 0 | AD42: =U42+V42+X42-Z42-AC42 -> 90000 | AE42: 671.5 | AF42: 0 | AG42: 0 | AH42: 0 | AI42: =AD42-AE42-AG42-AH42-AF42 -> 89328.5 | AJ42: Habib Bank Limited | AK42: 0017-79008282-03 | AL42: 42201-9210659-4 | AM42: Fatima Hasan | AN42: =AI42 -> 89328.5 | AS42: =SUM(AN42:AR42) -> 89328.5 | AU42: =+AS42+AT42 -> 89328.5 | AV42: =+AI42-AU42 -> 0 | AZ42: 89329 | BA42: 0 | BD42: =SUM(AW42:BC42) -> 89329 | BE42: =BD42-AU42 -> 0.5 | BF42: UK | BG42: =AF42/1*5 -> 0
B43: 41 | C43: 43830 | D43: 35000 | E43: =ROUND(_xlfn.DAYS($E$1,C43)/30,0) -> 4 | F43: 180 | G43: 43307 | H43: CT | I43: Asif Ahmed | J43: Sales | K43: International Sales Executive | L43: Nadeem Akhtar | M43: HW | N43: ITN | O43: P | P43: =70000+35000 -> 105000 | Q43: =P43/160% -> 65625 | R43: =40/100*Q43 -> 26250 | S43: =10/100*Q43 -> 6562.5 | T43: =10/100*Q43 -> 6562.5 | U43: =Q43+R43+S43+T43 -> 105000 | X43: =P43/$G$4*W43 -> 0 | Y43: 0 | Z43: =P43/$G$4*Y43 -> 0 | AA43: =P43/$G$4/9 -> 583.33333 | AC43: =AA43*AB43 -> 0 | AD43: =U43+V43+X43-Z43-AC43 -> 105000 | AE43: 1011.4 | AF43: 0 | AG43: 0 | AH43: 0 | AI43: =AD43-AE43-AG43-AH43-AF43 -> 103988.6 | AJ43: Habib Bank Limited | AK43: 0017-79008816-03 | AL43: 45203-6460366-1 | AM43: ASIF AHMED | AN43: =AI43 -> 103988.6 | AS43: =SUM(AN43:AR43) -> 103988.6 | AU43: =+AS43+AT43 -> 103988.6 | AV43: =+AI43-AU43 -> 0 | AZ43: 103989 | BA43: 0 | BD43: =SUM(AW43:BC43) -> 103989 | BE43: =BD43-AU43 -> 0.4 | BF43: UK | BG43: =AF43/1*5 -> 0
B44: 31 | C44: 43861 | D44: 5000 | E44: =ROUND(_xlfn.DAYS($E$1,C44)/30,0) -> 3 | F44: 162 | G44: 43236 | H44: CT | I44: Faraz Hussain | J44: Procurement | K44: Manager Procurement | L44: Wasif Azhar | M44: HW | N44: GIT | O44: P | P44: =90000+15000+5000 -> 110000 | Q44: =P44/160% -> 68750 | R44: =40/100*Q44 -> 27500 | S44: =10/100*Q44 -> 6875 | T44: =10/100*Q44 -> 6875 | U44: =Q44+R44+S44+T44 -> 110000 | X44: =P44/$G$6*W44 -> 0 | Y44: 0 | Z44: =P44/$G$6*Y44 -> 0 | AA44: =P44/$G$6/9 -> 582.01058 | AC44: =AA44*AB44 -> 0 | AD44: =U44+V44+X44-Z44-AC44 -> 110000 | AE44: 1134.25 | AF44: 0 | AG44: 0 | AH44: 0 | AI44: =AD44-AE44-AG44-AH44-AF44 -> 108865.75 | AJ44: Habib Bank Limited | AK44: 0583-79011770-03 | AL44: 42201-9303716-3 | AM44: Faraz Hussain | AN44: =AI44 -> 108865.75 | AS44: =SUM(AN44:AR44) -> 108865.75 | AU44: =+AS44+AT44 -> 108865.75 | AV44: =+AI44-AU44 -> 0 | AZ44: 108866 | BA44: 0 | BD44: =SUM(AW44:BC44) -> 108866 | BE44: =BD44-AU44 -> 0.25 | BF44: US | BG44: =AF44/1*5 -> 0
B45: 37 | C45: 43830 | D45: 20000 | E45: =ROUND(_xlfn.DAYS($E$1,C45)/30,0) -> 4 | F45: 7 | G45: 42185 | H45: CT | I45: Ebad Qureshi | J45: Procurement | K45: Manager Procurement | L45: Nadeem Akhtar | M45: HW | N45: ITN | O45: P | P45: =60000+15000+15000+20000 -> 110000 | Q45: =P45/160% -> 68750 | R45: =40/100*Q45 -> 27500 | S45: =10/100*Q45 -> 6875 | T45: =10/100*Q45 -> 6875 | U45: =Q45+R45+S45+T45 -> 110000 | X45: =P45/$G$4*W45 -> 0 | Y45: 0 | Z45: =P45/$G$4*Y45 -> 0 | AA45: =P45/$G$4/9 -> 611.11111 | AC45: =AA45*AB45 -> 0 | AD45: =U45+V45+X45-Z45-AC45 -> 110000 | AE45: 3062 | AF45: 250 | AG45: 0 | AH45: 10000 | AI45: =AD45-AE45-AG45-AH45-AF45 -> 96688 | AJ45: Habib Bank Limited | AK45: 0017-79008145-03 | AL45: 42201-0463606-9 | AM45: M Ebad Qureshi | AN45: =AI45 -> 96688 | AS45: =SUM(AN45:AR45) -> 96688 | AU45: =+AS45+AT45 -> 96688 | AV45: =+AI45-AU45 -> 0 | AZ45: 96688 | BA45: 0 | BD45: =SUM(AW45:BC45) -> 96688 | BE45: =BD45-AU45 -> 0 | BF45: UK | BG45: =AF45/1*5 -> 1250
B46: 30 | C46: 43861 | D46: 30000 | E46: =ROUND(_xlfn.DAYS($E$1,C46)/30,0) -> 3 | F46: 702 | G46: 43684 | H46: CT | I46: Fahad Naveed | J46: Sales | K46: International Sales Executive | L46: Umer Shahjahan | M46: HW | N46: BNS | O46: NP | P46: =100000+30000 -> 130000 | Q46: =P46/160% -> 81250 | R46: =40/100*Q46 -> 32500 | S46: =10/100*Q46 -> 8125 | T46: =10/100*Q46 -> 8125 | U46: =Q46+R46+S46+T46 -> 130000 | X46: =P46/$G$6*W46 -> 0 | Y46: 0 | Z46: =P46/$G$6*Y46 -> 0 | AA46: =P46/$G$6/9 -> 687.83069 | AC46: =AA46*AB46 -> 0 | AD46: =U46+V46+X46-Z46-AC46 -> 130000 | AE46: 1790.25 | AF46: 0 | AG46: 0 | AH46: 0 | AI46: =AD46-AE46-AG46-AH46-AF46 -> 128209.75 | AJ46: Habib Bank Limited | AK46: 12427949370603 | AL46: 34603-4887839-9 | AM46: Fahad naveed | AN46: =AI46 -> 128209.75 | AS46: =SUM(AN46:AR46) -> 128209.75 | AU46: =+AS46+AT46 -> 128209.75 | AV46: =+AI46-AU46 -> 0 | AZ46: 128210 | BA46: 0 | BD46: =SUM(AW46:BC46) -> 128210 | BE46: =BD46-AU46 -> 0.25 | BF46: US | BG46: =AF46/1*5 -> 0
B47: 2 | C47: 43890 | D47: 15000 | E47: =ROUND(_xlfn.DAYS($E$1,C47)/30,0) -> 2 | F47: 53 | G47: 42752 | H47: CT | I47: Muhammad Mubashir | J47: Accounts | K47: Assiatant Manager Accounts | L47: Farooq Khan | M47: ALL | N47: ALL | O47: P | P47: =100000+30000+15000 -> 145000 | Q47: =P47/160% -> 90625 | R47: =40/100*Q47 -> 36250 | S47: =10/100*Q47 -> 9062.5 | T47: =10/100*Q47 -> 9062.5 | U47: =Q47+R47+S47+T47 -> 145000 | X47: =P47/$G$3*W47 -> 0 | Y47: 0 | Z47: =P47/$G$3*Y47 -> 0 | AA47: =P47/$G$3/9 -> 847.95322 | AC47: =AA47*AB47 -> 0 | AD47: =U47+V47+X47-Z47-AC47 -> 145000 | AE47: 1321 | AF47: 250 | AG47: 0 | AH47: 0 | AI47: =AD47-AE47-AG47-AH47-AF47 -> 143429 | AJ47: Habib Bank Limited | AK47: 0017-79008158-03 | AL47: 42201-7208948-9 | AM47: Mubashir | AN47: =AI47 -> 143429 | AS47: =SUM(AN47:AR47) -> 143429 | AU47: =+AS47+AT47 -> 143429 | AV47: =+AI47-AU47 -> 0 | AZ47: 143429 | BA47: 0 | BD47: =SUM(AW47:BC47) -> 143429 | BE47: =BD47-AU47 -> 0 | BF47: Local | BG47: =AF47/1*5 -> 1250
B48: 1 | C48: 43677 | D48: 17000 | E48: =ROUND(_xlfn.DAYS($E$1,C48)/30,0) -> 9 | F48: 78 | G48: 42927 | H48: CT | I48: Muhammad Farooq Khan | J48: Accounts | K48: Manager Accounts | L48: Wahaj Qureshi | M48: ALL | N48: ALL | O48: P | P48: =170000+17000 -> 187000 | Q48: =P48/160% -> 116875 | R48: =40/100*Q48 -> 46750 | S48: =10/100*Q48 -> 11687.5 | T48: =10/100*Q48 -> 11687.5 | U48: =Q48+R48+S48+T48 -> 187000 | X48: =P48/$G$3*W48 -> 0 | Y48: 0 | Z48: =P48/$G$3*Y48 -> 0 | AA48: =P48/$G$3/9 -> 1093.5673 | AC48: =AA48*AB48 -> 0 | AD48: =U48+V48+X48-Z48-AC48 -> 187000 | AE48: 3485.4 | AF48: 250 | AG48: 0 | AH48: 0 | AI48: =AD48-AE48-AG48-AH48-AF48 -> 183264.6 | AJ48: Habib Bank Limited | AK48: 0017-79008339-03 | AL48: 42201-0755649-5 | AM48: M Farooq Khan | AN48: =183265-50000 -> 133265 | AQ48: 50000 | AS48: =SUM(AN48:AR48) -> 183265 | AU48: =+AS48+AT48 -> 183265 | AV48: =+AI48-AU48 -> -0.4 | AZ48: 133265 | BA48: 50000 | BD48: =SUM(AW48:BC48) -> 183265 | BE48: =BD48-AU48 -> 0 | BF48: Local | BG48: =AF48/1*5 -> 1250
B49: 32 | C49: 43465 | D49: 50000 | E49: =ROUND(_xlfn.DAYS($E$1,C49)/30,0) -> 16 | F49: 47 | G49: 43039 | H49: CT | I49: Wasif Azhar | J49: Sales | K49: International Sales Executive | L49: Umer Shahjahan | M49: HW | N49: GIT | O49: P | P49: =70000+20000+40000+20000+50000 -> 200000 | Q49: =P49/160% -> 125000 | R49: =40/100*Q49 -> 50000 | S49: =10/100*Q49 -> 12500 | T49: =10/100*Q49 -> 12500 | U49: =Q49+R49+S49+T49 -> 200000 | X49: =P49/$G$6*W49 -> 0 | Y49: 0 | Z49: =P49/$G$6*Y49 -> 0 | AA49: =P49/$G$6/9 -> 1058.2011 | AC49: =AA49*AB49 -> 0 | AD49: =U49+V49+X49-Z49-AC49 -> 200000 | AE49: 9661.6 | AF49: 250 | AG49: 0 | AH49: 0 | AI49: =AD49-AE49-AG49-AH49-AF49 -> 190088.4 | AJ49: Habib Bank Limited | AK49: 0830-79009967-03 | AL49: 42101-9384181-3 | AM49: Wasif Azhar | AN49: =AI49 -> 190088.4 | AS49: =SUM(AN49:AR49) -> 190088.4 | AU49: =+AS49+AT49 -> 190088.4 | AV49: =+AI49-AU49 -> 0 | AZ49: 190088 | BA49: 0 | BD49: =SUM(AW49:BC49) -> 190088 | BE49: =BD49-AU49 -> -0.4 | BF49: US | BG49: =AF49/1*5 -> 1250
B50: 40 | C50: 43830 | D50: 50000 | E50: =ROUND(_xlfn.DAYS($E$1,C50)/30,0) -> 4 | F50: 44 | G50: 42825 | H50: CT | I50: Nadeem Akhtar | J50: Sales | K50: International Sales Executive | L50: Wahaj Qureshi | M50: HW | N50: ITN | O50: P | P50: =150000+50000 -> 200000 | Q50: =P50/160% -> 125000 | R50: =40/100*Q50 -> 50000 | S50: =10/100*Q50 -> 12500 | T50: =10/100*Q50 -> 12500 | U50: =Q50+R50+S50+T50 -> 200000 | X50: =P50/$G$4*W50 -> 0 | Y50: 0 | Z50: =P50/$G$4*Y50 -> 0 | AA50: =P50/$G$4/9 -> 1111.1111 | AC50: =AA50*AB50 -> 0 | AD50: =U50+V50+X50-Z50-AC50 -> 200000 | AE50: 10302.6 | AF50: 250 | AG50: 0 | AH50: 0 | AI50: =AD50-AE50-AG50-AH50-AF50 -> 189447.4 | AJ50: Habib Bank Limited | AK50: 0017-79008162-03 | AL50: 42201-0590958-3 | AM50: Nadeem Akhtar | AN50: =AI50 -> 189447.4 | AS50: =SUM(AN50:AR50) -> 189447.4 | AU50: =+AS50+AT50 -> 189447.4 | AV50: =+AI50-AU50 -> 0 | AZ50: 189447 | BA50: 0 | BD50: =SUM(AW50:BC50) -> 189447 | BE50: =BD50-AU50 -> -0.4 | BF50: UK | BG50: =AF50/1*5 -> 1250
B51: 24 | C51: 43677 | D51: 25000 | E51: =ROUND(_xlfn.DAYS($E$1,C51)/30,0) -> 9 | F51: 70 | G51: 42808 | H51: CT | I51: Khawaja Muhammad Ali | J51: Procurement | K51: Procurrement Executive | L51: Wahaj Qureshi | M51: HW | N51: BD | O51: P | P51: 125000 | Q51: =P51/160% -> 78125 | R51: =40/100*Q51 -> 31250 | S51: =10/100*Q51 -> 7812.5 | T51: =10/100*Q51+85000 -> 92812.5 | U51: =Q51+R51+S51+T51 -> 210000 | X51: =P51/$G$4*W51 -> 0 | Y51: 0 | Z51: =P51/$G$4*Y51 -> 0 | AA51: =P51/$G$4/9 -> 694.44444 | AC51: =AA51*AB51 -> 0 | AD51: =U51+V51+X51-Z51-AC51 -> 210000 | AE51: 1941.2 | AF51: 250 | AG51: 85000 | AH51: 0 | AI51: =AD51-AE51-AG51-AH51-AF51 -> 122808.8 | AJ51: Habib Bank Limited | AK51: 0017-79008153-03 | AL51: 42301-6647406-1 | AM51: Khawaja | AN51: =AI51 -> 122808.8 | AS51: =SUM(AN51:AR51) -> 122808.8 | AU51: =+AS51+AT51 -> 122808.8 | AV51: =+AI51-AU51 -> 0 | AZ51: 122809 | BA51: 0 | BD51: =SUM(AW51:BC51) -> 122809 | BE51: =BD51-AU51 -> 0.2 | BF51: UK | BG51: =AF51/1*5 -> 1250
B52: 17 | C52: 43555 | D52: 50000 | E52: =ROUND(_xlfn.DAYS($E$1,C52)/30,0) -> 13 | F52: 18 | G52: 42618 | H52: CT | I52: Umair Kaim Khani | J52: Marketing | K52: Project Coordinator | L52: Wahaj Qureshi | M52: HW | N52: ALL | O52: P | P52: =150000+50000 -> 200000 | Q52: =P52/160% -> 125000 | R52: =40/100*Q52 -> 50000 | S52: =10/100*Q52 -> 12500 | T52: =10/100*Q52+(75000) -> 87500 | U52: =Q52+R52+S52+T52 -> 275000 | X52: =P52/$G$3*W52 -> 0 | Y52: 0 | Z52: =P52/$G$3*Y52 -> 0 | AA52: =P52/$G$3/9 -> 1169.5906 | AC52: =AA52*AB52 -> 0 | AD52: =U52+V52+X52-Z52-AC52 -> 275000 | AE52: 9790 | AF52: 250 | AG52: 75000 | AH52: 0 | AI52: =AD52-AE52-AG52-AH52-AF52 -> 189960 | AJ52: Habib Bank Limited | AK52: 0017-79008182-03 | AL52: 42101-7702531-1 | AM52: Muhammad Umair | AN52: =AI52 -> 189960 | AS52: =SUM(AN52:AR52) -> 189960 | AU52: =+AS52+AT52 -> 189960 | AV52: =+AI52-AU52 -> 0 | AZ52: 189960 | BA52: 0 | BD52: =SUM(AW52:BC52) -> 189960 | BE52: =BD52-AU52 -> 0 | BF52: Local | BG52: =AF52/1*5 -> 1250
F53: 80 | I53: Ibtihaj Ali Haider | J53: Sales | M53: Portal | N53: Portal | P53: 175000 | Q53: =P53/160% -> 109375 | R53: =40/100*Q53 -> 43750 | S53: =10/100*Q53 -> 10937.5 | T53: =10/100*Q53 -> 10937.5 | U53: =Q53+R53+S53+T53 -> 175000 | X53: =P53/$G$5*W53 -> 0 | Z53: =P53/$G$5*Y53 -> 0 | AA53: =P53/$G$5/9 -> 925.92593 | AC53: =AA53*AB53 -> 0 | AD53: =U53+V53+X53-Z53-AC53 -> 175000 | AI53: =AD53-AE53-AG53-AH53-AF53 -> 175000 | AJ53: Habib Bank Limited | AK53: 0017-79008290-03 | AL53: 42201-8991394-3 | AM53: Muhammad Ibtehaj Ali Haider | AN53: =AI53 -> 175000 | AS53: =SUM(AN53:AR53) -> 175000 | AU53: =+AS53+AT53 -> 175000 | AV53: =+AI53-AU53 -> 0 | AZ53: 175000 | BD53: =SUM(AW53:BC53) -> 175000 | BE53: =BD53-AU53 -> 0 | BG53: =AF53/1*5 -> 0
P56: =SUBTOTAL(9,P8:P55) -> 3212000 | Q56: =SUBTOTAL(9,Q8:Q55) -> 2007500 | R56: =SUBTOTAL(9,R8:R55) -> 803000 | S56: =SUBTOTAL(9,S8:S55) -> 200750 | T56: =SUBTOTAL(9,T8:T55) -> 360750 | U56: =SUBTOTAL(9,U8:U55) -> 3372000 | V56: =SUBTOTAL(9,V8:V55) -> 0 | X56: =SUBTOTAL(9,X8:X55) -> 0 | Z56: =SUBTOTAL(9,Z8:Z55) -> 177395.36 | AC56: =SUBTOTAL(9,AC8:AC55) -> 2192.9825 | AD56: =SUBTOTAL(9,AD8:AD55) -> 3192411.7 | AE56: =SUBTOTAL(9,AE8:AE55) -> 45859.6 | AF56: =SUBTOTAL(9,AF8:AF55) -> 2500 | AG56: =SUBTOTAL(9,AG8:AG55) -> 177000 | AH56: =SUBTOTAL(9,AH8:AH55) -> 25000 | AI56: =SUBTOTAL(9,AI8:AI55) -> 2942052.1 | AN56: =SUBTOTAL(9,AN8:AN55) -> 2454431.9 | AO56: =SUBTOTAL(9,AO8:AO55) -> 0 | AP56: =SUBTOTAL(9,AP8:AP55) -> 0 | AQ56: =SUBTOTAL(9,AQ8:AQ55) -> 368103 | AR56: =SUBTOTAL(9,AR8:AR55) -> 94078.947 | AS56: =SUBTOTAL(9,AS8:AS55) -> 2916613.9 | AT56: =SUBTOTAL(9,AT8:AT55) -> 25438.596 | AU56: =SUBTOTAL(9,AU8:AU55) -> 2942052.5 | AW56: =SUBTOTAL(9,AW8:AW55) -> 106789 | AX56: =SUBTOTAL(9,AX8:AX55) -> 44461 | AY56: =SUBTOTAL(9,AY8:AY55) -> 94079 | AZ56: =SUBTOTAL(9,AZ8:AZ55) -> 2340000 | BA56: =SUBTOTAL(9,BA8:BA55) -> 323641 | BB56: =SUBTOTAL(9,BB8:BB55) -> 7645 | BC56: =SUBTOTAL(9,BC8:BC55) -> 25439 | BD56: =SUBTOTAL(9,BD8:BD55) -> 2942054 | BF56: =SUBTOTAL(9,BF8:BF55) -> 0 | BG56: =SUBTOTAL(9,BG8:BG55) -> 12500
AU57: =+AU56-AI56 -> 0.4 | BC57: =+AT56-BC56 -> -0.40350877 | BD57: =AU56-BD56 -> -1.5458647
P58: ='Payroll DES Apr24'!P18+'Payroll HW Apr24'!P54+'Payroll Support Apr24'!P17-P56 -> 0 | Q58: ='Payroll DES Apr24'!Q18+'Payroll HW Apr24'!Q54+'Payroll Support Apr24'!Q17-Q56 -> 0 | R58: ='Payroll DES Apr24'!R18+'Payroll HW Apr24'!R54+'Payroll Support Apr24'!R17-R56 -> 0 | S58: ='Payroll DES Apr24'!S18+'Payroll HW Apr24'!S54+'Payroll Support Apr24'!S17-S56 -> 0 | T58: ='Payroll DES Apr24'!T18+'Payroll HW Apr24'!T54+'Payroll Support Apr24'!T17-T56 -> 0 | U58: ='Payroll DES Apr24'!U18+'Payroll HW Apr24'!U54+'Payroll Support Apr24'!U17-U56 -> 0 | V58: ='Payroll DES Apr24'!V18+'Payroll HW Apr24'!V54+'Payroll Support Apr24'!V17-V56 -> 0 | X58: ='Payroll DES Apr24'!X18+'Payroll HW Apr24'!X54+'Payroll Support Apr24'!X17-X56 -> 0 | Z58: ='Payroll DES Apr24'!Z18+'Payroll HW Apr24'!Z54+'Payroll Support Apr24'!Z17-Z56 -> 0 | AC58: ='Payroll DES Apr24'!AC18+'Payroll HW Apr24'!AC54+'Payroll Support Apr24'!AC17-AC56 -> 0 | AD58: ='Payroll DES Apr24'!AD18+'Payroll HW Apr24'!AD54+'Payroll Support Apr24'!AD17-AD56 -> 0 | AE58: ='Payroll DES Apr24'!AE18+'Payroll HW Apr24'!AE54+'Payroll Support Apr24'!AE17-AE56 -> 0 | AF58: ='Payroll DES Apr24'!AF18+'Payroll HW Apr24'!AF54+'Payroll Support Apr24'!AF17-AF56 -> 0 | AG58: ='Payroll DES Apr24'!AG18+'Payroll HW Apr24'!AG54+'Payroll Support Apr24'!AG17-AG56 -> 0 | AH58: ='Payroll DES Apr24'!AH18+'Payroll HW Apr24'!AH54+'Payroll Support Apr24'!AH17-AH56 -> 0 | AI58: ='Payroll DES Apr24'!AI18+'Payroll HW Apr24'!AI54+'Payroll Support Apr24'!AI17-AI56 -> 0 | AN58: ='Payroll DES Apr24'!AN18+'Payroll HW Apr24'!AN54+'Payroll Support Apr24'!AN17-AN56 -> 0 | AO58: ='Payroll DES Apr24'!AO18+'Payroll HW Apr24'!AO54+'Payroll Support Apr24'!AO17-AO56 -> 0 | AP58: ='Payroll DES Apr24'!AP18+'Payroll HW Apr24'!AP54+'Payroll Support Apr24'!AP17-AP56 -> 0 | AQ58: ='Payroll DES Apr24'!AQ18+'Payroll HW Apr24'!AQ54+'Payroll Support Apr24'!AQ17-AQ56 -> 0 | AR58: ='Payroll DES Apr24'!AR18+'Payroll HW Apr24'!AR54+'Payroll Support Apr24'!AR17-AR56 -> 0 | AS58: ='Payroll DES Apr24'!AS18+'Payroll HW Apr24'!AS54+'Payroll Support Apr24'!AS17-AS56 -> 0 | AT58: ='Payroll DES Apr24'!AT18+'Payroll HW Apr24'!AT54+'Payroll Support Apr24'!AT17-AT56 -> 0 | AU58: ='Payroll DES Apr24'!AU18+'Payroll HW Apr24'!AU54+'Payroll Support Apr24'!AU17-AU56 -> 0
AI60: =+AI56-AI12 -> 2932841.5 | AS60: 2650832
AI62: =2863764-25000+AR56 -> 2932842.9 | AS62: =+AS56-AS60 -> 265781.86
AI64: =+AI60-AI62 -> -1.4195489

Sheet Brandwise Allocation
D2: Gross Salary | E2: Gross salary with Conveyance | F2: Net Gross | G2: Net Pay | H2: EOBI Employers' Contribution | I2: Total Expense
B3: {=_xlfn.UNIQUE(Master[MCS]:Master[BRAND])} -> HW | C3: BNS | D3: =SUMIFS(Master[Gross Salary],Master[MCS],B3,Master[BRAND],C3) -> 130000 | E3: =SUMIFS(Master[Gross salary with Conveyance],Master[MCS],B3,Master[BRAND],C3) -> 130000 | F3: =SUMIFS(Master[Net Gross],Master[MCS],B3,Master[BRAND],C3) -> 130000 | G3: =SUMIFS(Master[Net Pay],Master[MCS],B3,Master[BRAND],C3) -> 128209.75 | H3: =SUMIFS(Master[EOBI Employers'' Contribution],Master[MCS],B3,Master[BRAND],C3) -> 0 | I3: =F3+H3 -> 130000
B4: HW | C4: ALL | D4: =SUMIFS(Master[Gross Salary],Master[MCS],B4,Master[BRAND],C4) -> 570000 | E4: =SUMIFS(Master[Gross salary with Conveyance],Master[MCS],B4,Master[BRAND],C4) -> 645000 | F4: =SUMIFS(Master[Net Gross],Master[MCS],B4,Master[BRAND],C4) -> 592017.54 | G4: =SUMIFS(Master[Net Pay],Master[MCS],B4,Master[BRAND],C4) -> 501977.54 | H4: =SUMIFS(Master[EOBI Employers'' Contribution],Master[MCS],B4,Master[BRAND],C4) -> 1250 | I4: =F4+H4 -> 593267.54
B5: HW | C5: BD | D5: =SUMIFS(Master[Gross Salary],Master[MCS],B5,Master[BRAND],C5) -> 525000 | E5: =SUMIFS(Master[Gross salary with Conveyance],Master[MCS],B5,Master[BRAND],C5) -> 610000 | F5: =SUMIFS(Master[Net Gross],Master[MCS],B5,Master[BRAND],C5) -> 560750 | G5: =SUMIFS(Master[Net Pay],Master[MCS],B5,Master[BRAND],C5) -> 471908.7 | H5: =SUMIFS(Master[EOBI Employers'' Contribution],Master[MCS],B5,Master[BRAND],C5) -> 2500 | I5: =F5+H5 -> 563250
B6: ALL | C6: ALL | D6: =SUMIFS(Master[Gross Salary],Master[MCS],B6,Master[BRAND],C6) -> 657000 | E6: =SUMIFS(Master[Gross salary with Conveyance],Master[MCS],B6,Master[BRAND],C6) -> 657000 | F6: =SUMIFS(Master[Net Gross],Master[MCS],B6,Master[BRAND],C6) -> 612263.16 | G6: =SUMIFS(Master[Net Pay],Master[MCS],B6,Master[BRAND],C6) -> 579238.96 | H6: =SUMIFS(Master[EOBI Employers'' Contribution],Master[MCS],B6,Master[BRAND],C6) -> 3750 | I6: =F6+H6 -> 616013.16
B7: HW | C7: GIT | D7: =SUMIFS(Master[Gross Salary],Master[MCS],B7,Master[BRAND],C7) -> 495000 | E7: =SUMIFS(Master[Gross salary with Conveyance],Master[MCS],B7,Master[BRAND],C7) -> 495000 | F7: =SUMIFS(Master[Net Gross],Master[MCS],B7,Master[BRAND],C7) -> 490952.38 | G7: =SUMIFS(Master[Net Pay],Master[MCS],B7,Master[BRAND],C7) -> 479906.53 | H7: =SUMIFS(Master[EOBI Employers'' Contribution],Master[MCS],B7,Master[BRAND],C7) -> 1250 | I7: =F7+H7 -> 492202.38
B8: Portal | C8: Portal | D8: =SUMIFS(Master[Gross Salary],Master[MCS],B8,Master[BRAND],C8) -> 275000 | E8: =SUMIFS(Master[Gross salary with Conveyance],Master[MCS],B8,Master[BRAND],C8) -> 275000 | F8: =SUMIFS(Master[Net Gross],Master[MCS],B8,Master[BRAND],C8) -> 246428.57 | G8: =SUMIFS(Master[Net Pay],Master[MCS],B8,Master[BRAND],C8) -> 246428.57 | H8: =SUMIFS(Master[EOBI Employers'' Contribution],Master[MCS],B8,Master[BRAND],C8) -> 0 | I8: =F8+H8 -> 246428.57
B9: HW | C9: ITN | D9: =SUMIFS(Master[Gross Salary],Master[MCS],B9,Master[BRAND],C9) -> 560000 | E9: =SUMIFS(Master[Gross salary with Conveyance],Master[MCS],B9,Master[BRAND],C9) -> 560000 | F9: =SUMIFS(Master[Net Gross],Master[MCS],B9,Master[BRAND],C9) -> 560000 | G9: =SUMIFS(Master[Net Pay],Master[MCS],B9,Master[BRAND],C9) -> 534382 | H9: =SUMIFS(Master[EOBI Employers'' Contribution],Master[MCS],B9,Master[BRAND],C9) -> 3750 | I9: =F9+H9 -> 563750
D10: =SUMIFS(Master[Gross Salary],Master[MCS],B10,Master[BRAND],C10) -> 0 | E10: =SUMIFS(Master[Gross salary with Conveyance],Master[MCS],B10,Master[BRAND],C10) -> 0 | F10: =SUMIFS(Master[Net Gross],Master[MCS],B10,Master[BRAND],C10) -> 0 | G10: =SUMIFS(Master[Net Pay],Master[MCS],B10,Master[BRAND],C10) -> 0 | H10: =SUMIFS(Master[EOBI Employers'' Contribution],Master[MCS],B10,Master[BRAND],C10) -> 0 | I10: =F10+H10 -> 0
D11: =SUMIFS(Master[Gross Salary],Master[MCS],B11,Master[BRAND],C11) -> 0 | E11: =SUMIFS(Master[Gross salary with Conveyance],Master[MCS],B11,Master[BRAND],C11) -> 0 | F11: =SUMIFS(Master[Net Gross],Master[MCS],B11,Master[BRAND],C11) -> 0 | G11: =SUMIFS(Master[Net Pay],Master[MCS],B11,Master[BRAND],C11) -> 0 | H11: =SUMIFS(Master[EOBI Employers'' Contribution],Master[MCS],B11,Master[BRAND],C11) -> 0 | I11: =F11+H11 -> 0
D12: =SUMIFS(Master[Gross Salary],Master[MCS],B12,Master[BRAND],C12) -> 0 | E12: =SUMIFS(Master[Gross salary with Conveyance],Master[MCS],B12,Master[BRAND],C12) -> 0 | F12: =SUMIFS(Master[Net Gross],Master[MCS],B12,Master[BRAND],C12) -> 0 | G12: =SUMIFS(Master[Net Pay],Master[MCS],B12,Master[BRAND],C12) -> 0 | H12: =SUMIFS(Master[EOBI Employers'' Contribution],Master[MCS],B12,Master[BRAND],C12) -> 0 | I12: =F12+H12 -> 0 | K12: 127640
K13: 183000
D14: =SUM(D3:D13) -> 3212000 | E14: =SUM(E3:E13) -> 3372000 | F14: =SUM(F3:F13) -> 3192411.7 | G14: =SUM(G3:G13) -> 2942052.1 | H14: =SUM(H3:H13) -> 12500 | I14: =SUM(I3:I13) -> 3204911.7 | K14: =5000*276 -> 1380000
D15: =SUM(Master[Gross Salary]) -> 3212000 | E15: =SUM(Master[Gross salary with Conveyance]) -> 3372000 | F15: =SUM(Master[Net Gross]) -> 3192411.7 | G15: =SUM(Master[Net Pay]) -> 2942052.1 | H15: =SUM(Master[EOBI Employers'' Contribution]) -> 12500 | K15: =7000*345 -> 2415000
D16: =+D14-D15 -> 0 | E16: =+E14-E15 -> 0 | F16: =+F14-F15 -> 0 | G16: =+G14-G15 -> 0 | H16: =+H14-H15 -> 0 | K16: =SUM(K12:K15) -> 4105640
G17: 1953000 | K17: -2754533
G18: =+G14-G17 -> 989052.05
D20: Direct | E20: Indirect | F20: Shared | G20: Total | K20: -200000
K21: =-751634-200000 -> -951634
B22: Bulk Devices UK | D22: =I5 -> 563250 | E22: =$I$4/2 -> 296633.77 | F22: =$I$6/3 -> 205337.72 | G22: =SUM(D22:F22) -> 1065221.5
B23: ITNHub Ltd | D23: =I9 -> 563750 | E23: 0 | F23: =$I$6/3 -> 205337.72 | G23: =SUM(D23:F23) -> 769087.72
B24: Gracile IT | D24: =I7 -> 492202.38 | E24: =$I$4/2 -> 296633.77 | F24: =$I$6/3 -> 205337.72 | G24: =SUM(D24:F24) -> 994173.87
B25: Blitz Network Solutions | D25: =I3 -> 130000 | E25: 0 | G25: =SUM(D25:F25) -> 130000 | K25: =SUM(K16:K24) -> 199473
B26: Design Portal | D26: =I10 -> 0 | E26: =I8 -> 246428.57 | G26: =SUM(D26:F26) -> 246428.57
D28: =SUM(D22:D27) -> 1749202.4 | E28: =SUM(E22:E27) -> 839696.12 | F28: =SUM(F22:F27) -> 616013.16 | G28: =SUM(G22:G27) -> 3204911.7 | H28: =G28-I14 -> 0
I45: Shahmeer Shaikh
I47: 40000 | J47: 10 | K47: =I47/21*J47 -> 19047.619
I48: 100000 | J48: 11 | K48: =I48/21*J48 -> 52380.952
K50: =SUM(K47:K49) -> 71428.571
K51: 100000
K52: =+K50-K51 -> -28571.429

Sheet <35K
A1: BSD Technologies - Salaries <= 35K | H1: HIDE | I1: Increment | J1: Forex | K1: 280 | Q1: HIDE | R1: HIDE | S1: HIDE | T1: HIDE | AG1: 2000
A2: Payroll | I2: New Joining
A3: Wkg Days (Local) | G3: 22 | I3: Last Month | AJ3: 1.1666667
A4: Wkg Days (Hardware UK) | G4: 22 | I4: Probation | Q4: =COLUMN()-2 -> 15 | R4: =COLUMN()-2 -> 16 | S4: =COLUMN()-2 -> 17 | T4: =COLUMN()-2 -> 18 | AJ4: =COLUMN()-2 -> 34 | AK4: =COLUMN()-2 -> 35 | AL4: =COLUMN()-2 -> 36
A5: Wkg Days (Design US) | G5: 21
A6: Wkg Days (Hardware US) | G6: 21 | J6: =COLUMN()-5 -> 5 | K6: =COLUMN()-5 -> 6 | M6: =COLUMN()-5 -> 8 | N6: =COLUMN()-5 -> 9 | O6: =COLUMN()-5 -> 10 | P6: =COLUMN()-5 -> 11 | Q6: =COLUMN()-5 -> 12 | R6: =COLUMN()-5 -> 13 | S6: =COLUMN()-5 -> 14 | T6: =COLUMN()-5 -> 15 | ... AL6: =COLUMN()-5 -> 33
B7: Sr.No | C7: date of last increment | D7: last incremnet | E7: # Months Since Last Increment | F7: Emp Code | G7: DOJ (DD/MM/Y) | H7: CURRENT STATUS | I7: Employee Name (CNIC) | J7: Department | K7: Designation | L7: Reporting Manager | M7: MCS | N7: BRAND | O7: Status | P7: Gross Salary | Q7: Basic Salary | R7: H.Rent All | S7: Ut. All | T7: Conv. All | U7: Gross salary | V7: Bonus/Incentive/ Reimbursemet | W7: No.Extra Days | X7: Amount Ex. Days | Y7: DISAPPROVED Absent Days | Z7: Deduction absent Days | AA7: Hourly Rate | AB7: No. of Ded Hours | AC7: Ded Amt Hrs | AD7: Net Gross | AE7: Tax | AF7: EOBI | AG7: Advance | AH7: Loan | AI7: Net Pay | AJ7: Bank Name | AK7: AC Number | AL7: CNIC | AM7: Account Title | AN7: HBL | AO7: Samba | AP7: Cheque | AQ7: IBFT | AR7: Cash | AS7: Payments | AT7: Hold | AU7: Total
B8: {=_xlfn._xlws.FILTER(Master!B8:AU28,Master!U8:U28<=30000,"")} -> 49 | C8: 0 | D8: 0 | E8: 0 | F8: 701 | G8: 43684 | H8: CT | I8: Usman Amin | J8: Sales | K8: International Sales Executive | L8: Umer Shahjahan | M8: HW | N8: BNS | O8: NP | P8: 0 | Q8: 0 | R8: 0 | S8: 0 | T8: 0 | U8: 0 | V8: 0 | W8: 0 | X8: 0 | Y8: 0 | Z8: 0 | AA8: 0 | AB8: 0 | AC8: 0 | AD8: 0 | AE8: 0 | AF8: 0 | AG8: 0 | AH8: 0 | AI8: 0 | AJ8: Habib Bank Limited | AK8: 0445-79012790-99 | AL8: 35202-7785641-9 | AM8: Muhammad ADA | AN8: 0 | AO8: 0 | AP8: 0 | AQ8: 0 | AR8: 0 | AS8: 0 | AT8: 0 | AU8: 0 | AW8: 144 | AX8: =+F8-AW8 -> 557
B9: 15 | C9: 0 | D9: 0 | E9: 0 | F9: 191 | G9: 43788 | H9: NJ | I9: Usman | J9: Data Analysis | K9: Trainee | L9: Azmeer | M9: HW | N9: ALL | O9: NP | P9: 15000 | Q9: 9375 | R9: 3750 | S9: 937.5 | T9: 937.5 | U9: 15000 | V9: 0 | W9: 0 | X9: 0 | Y9: 14 | Z9: 11052.632 | AA9: 87.719298 | AB9: 0 | AC9: 0 | AD9: 3947.3684 | AE9: 0 | AF9: 0 | AG9: 0 | AH9: 0 | AI9: 3947.3684 | AJ9: 0 | AK9: 0 | AL9: 0 | AM9: Muhammad Khawar | AN9: 0 | AO9: 0 | AP9: 0 | AQ9: 0 | AR9: 3947.3684 | AS9: 3947.3684 | AT9: 0 | AU9: 3947.3684 | AW9: 999 | AX9: =+F9-AW9 -> -808
B10: 0 | C10: 0 | D10: 0 | E10: 0 | F10: 229 | G10: 43942 | H10: 0 | I10: Maham Khan | J10: Sales | K10: International Sales Executive | L10: 0 | M10: HW | N10: BD | O10: NP | P10: 30000 | Q10: 18750 | R10: 7500 | S10: 1875 | T10: 1875 | U10: 30000 | V10: 0 | W10: 0 | X10: 0 | Y10: 13 | Z10: 19500 | AA10: 166.66667 | AB10: 0 | AC10: 0 | AD10: 10500 | AE10: 0 | AF10: 0 | AG10: 0 | AH10: 0 | AI10: 10500 | AJ10: Habib Bank Limited | AK10: PK70HABB0022567901806303 | AL10: 42301-1466430-6 | AM10: Muhammad Ali | AN10: 0 | AO10: 0 | AP10: 0 | AQ10: 0 | AR10: 10500 | AS10: 10500 | AT10: 0 | AU10: 10500 | AW10: 168 | AX10: =+F10-AW10 -> 61
B11: 16 | C11: 0 | D11: 0 | E11: 0 | F11: 224 | G11: 43861 | H11: 0 | I11: Taha Ahmed | J11: Data Analysis | K11: Trainee | L11: Azmeer | M11: HW | N11: ALL | O11: NP | P11: 15000 | Q11: 9375 | R11: 3750 | S11: 937.5 | T11: 937.5 | U11: 15000 | V11: 0 | W11: 0 | X11: 0 | Y11: 0 | Z11: 0 | AA11: 87.719298 | AB11: 0 | AC11: 0 | AD11: 15000 | AE11: 0 | AF11: 0 | AG11: 0 | AH11: 0 | AI11: 15000 | AJ11: MCB Bank | AK11: PK27MUCB0006802010077407 | AL11: 42201-9587377-5 | AM11: Zameer Ahmed Usmani | AN11: 0 | AO11: 0 | AP11: 0 | AQ11: 15000 | AR11: 0 | AS11: 15000 | AT11: 0 | AU11: 15000 | AW11: 176 | AX11: =+F11-AW11 -> 48
B12: 7 | C12: 0 | D12: 0 | E12: 0 | F12: 999 | G12: 43496 | H12: CT | I12: Muhammad Farooq | J12: Administration | K12: Electrician | L12: Mubashir | M12: ALL | N12: ALL | O12: NP | P12: 15000 | Q12: 9375 | R12: 3750 | S12: 937.5 | T12: 937.5 | U12: 15000 | V12: 0 | W12: 0 | X12: 0 | Y12: 0 | Z12: 0 | AA12: 87.719298 | AB12: 0 | AC12: 0 | AD12: 15000 | AE12: 0 | AF12: 0 | AG12: 0 | AH12: 0 | AI12: 15000 | AJ12: Standard Chartered Bank | AK12: 01994613601 | AL12: 0 | AM12: Muhammad Farooq | AN12: 0 | AO12: 0 | AP12: 0 | AQ12: 15000 | AR12: 0 | AS12: 15000 | AT12: 0 | AU12: 15000 | AW12: 164 | AX12: =+F12-AW12 -> 835
B13: 13 | C13: 0 | D13: 0 | E13: 0 | F13: 221 | G13: 43479 | H13: 0 | I13: Abdul Sami Kamali | J13: Data Analysis | K13: Trainee | L13: Azmeer | M13: HW | N13: ALL | O13: NP | P13: 25000 | Q13: 15625 | R13: 6250 | S13: 1562.5 | T13: 1562.5 | U13: 25000 | V13: 0 | W13: 0 | X13: 0 | Y13: 0 | Z13: 0 | AA13: 146.19883 | AB13: 0 | AC13: 0 | AD13: 25000 | AE13: 0 | AF13: 0 | AG13: 0 | AH13: 0 | AI13: 25000 | AJ13: NAYAPAY | AK13: 03313102701 | AL13: 42000-5277363-3 | AM13: Abdul Sami Kamali | AN13: 0 | AO13: 0 | AP13: 0 | AQ13: 25000 | AR13: 0 | AS13: 25000 | AT13: 0 | AU13: 25000 | AW13: 204 | AX13: =+F13-AW13 -> 17
B14: 14 | C14: 0 | D14: 0 | E14: 0 | F14: 225 | G14: 43845 | H14: 0 | I14: Aun Zaidi | J14: Data Analysis | K14: Trainee | L14: Azmeer | M14: HW | N14: ALL | O14: NP | P14: 20000 | Q14: 12500 | R14: 5000 | S14: 1250 | T14: 1250 | U14: 20000 | V14: 0 | W14: 0 | X14: 0 | Y14: 0 | Z14: 0 | AA14: 116.95906 | AB14: 0 | AC14: 0 | AD14: 20000 | AE14: 0 | AF14: 0 | AG14: 0 | AH14: 0 | AI14: 20000 | AJ14: Habib Bank Limited | AK14: 08780017874001 | AL14: 42101-6994069-3 | AM14: SYED AJAZ HUSSAIN ZAIDI | AN14: 20000 | AO14: 0 | AP14: 0 | AQ14: 0 | AR14: 0 | AS14: 20000 | AT14: 0 | AU14: 20000 | AW14: 135 | AX14: =+F14-AW14 -> 90
B15: 22 | C15: 43890 | D15: 10000 | E15: 0 | F15: 202 | G15: 43760 | H15: CT | I15: Muhammad Huzaifa Haleem | J15: Marketing - SEO | K15: SEO Intern | L15: Muhammad Yousuf | M15: HW | N15: ALL | O15: NP | P15: 25000 | Q15: 15625 | R15: 6250 | S15: 1562.5 | T15: 1562.5 | U15: 25000 | V15: 0 | W15: 0 | X15: 0 | Y15: 5 | Z15: 6578.9474 | AA15: 146.19883 | AB15: 15 | AC15: 2192.9825 | AD15: 16228.07 | AE15: 0 | AF15: 0 | AG15: 0 | AH15: 0 | AI15: 16228.07 | AJ15: NAYAPAY | AK15: 03491838351 | AL15: 0 | AM15: Muhammad Huzaifa Haleem | AN15: 0 | AO15: 0 | AP15: 0 | AQ15: 0 | AR15: 0 | AS15: 0 | AT15: 16228.07 | AU15: 16228.07 | AW15: 142 | AX15: =+F15-AW15 -> 60
B16: 23 | C16: 0 | D16: 0 | E16: 0 | F16: 222 | G16: 43861 | H16: 0 | I16: Moin Shaikh | J16: Marketing - SEO | K16: SEO Intern | L16: Muhammad Yousuf | M16: HW | N16: ALL | O16: NP | P16: 20000 | Q16: 12500 | R16: 5000 | S16: 1250 | T16: 1250 | U16: 20000 | V16: 0 | W16: 0 | X16: 0 | Y16: 0 | Z16: 0 | AA16: 116.95906 | AB16: 0 | AC16: 0 | AD16: 20000 | AE16: 0 | AF16: 0 | AG16: 0 | AH16: 0 | AI16: 20000 | AJ16: Meezan Bank Limited | AK16: PK26MEZN0001430109041892 | AL16: 42101-2622969-7 | AM16: MOHAMMAD MOIN UDDIN | AN16: 0 | AO16: 0 | AP16: 0 | AQ16: 20000 | AR16: 0 | AS16: 20000 | AT16: 0 | AU16: 20000 | AW16: 149 | AX16: =+F16-AW16 -> 73
B17: 6 | C17: 43738 | D17: 5000 | E17: 7 | F17: 144 | G17: Apr 2023 | H17: CT | I17: Salman | J17: Administration | K17: Office Boy | L17: Mubashir | M17: ALL | N17: ALL | O17: P | P17: 25000 | Q17: 15625 | R17: 6250 | S17: 1562.5 | T17: 1562.5 | U17: 25000 | V17: 0 | W17: 0 | X17: 0 | Y17: 0 | Z17: 0 | AA17: 146.19883 | AB17: 0 | AC17: 0 | AD17: 25000 | AE17: 0 | AF17: 0 | AG17: 3000 | AH17: 0 | AI17: 22000 | AJ17: Habib Bank Limited | AK17: 0017-79008173-03 | AL17: 0 | AM17: Amanullah | AN17: 0 | AO17: 0 | AP17: 0 | AQ17: 0 | AR17: 22000 | AS17: 22000 | AT17: 0 | AU17: 22000 | AW17: 191 | AX17: =+F17-AW17 -> -47
B18: 4 | C18: 43738 | D18: 5000 | E18: 7 | F18: 168 | G18: 01 Nov 2020 / 12 Sep 2022 | H18: CT | I18: Ammanullah | J18: Administration | K18: Office Boy | L18: Mubashir | M18: ALL | N18: ALL | O18: P | P18: 30000 | Q18: 18750 | R18: 7500 | S18: 1875 | T18: 1875 | U18: 30000 | V18: 0 | W18: 0 | X18: 0 | Y18: 0 | Z18: 0 | AA18: 175.4386 | AB18: 0 | AC18: 0 | AD18: 30000 | AE18: 0 | AF18: 0 | AG18: 4000 | AH18: 5000 | AI18: 21000 | AJ18: Habib Bank Limited | AK18: 0017-79008173-03 | AL18: 32404-9685630-7 | AM18: Amanullah | AN18: 21000 | AO18: 0 | AP18: 0 | AQ18: 0 | AR18: 0 | AS18: 21000 | AT18: 0 | AU18: 21000 | AW18: 210 | AX18: =+F18-AW18 -> -42
B19: 5 | C19: 43738 | D19: 5000 | E19: 7 | F19: 176 | G19: 43298 | H19: CT | I19: Muhammad Irfan | J19: Administration | K19: Office Boy | L19: Mubashir | M19: ALL | N19: ALL | O19: P | P19: 30000 | Q19: 18750 | R19: 7500 | S19: 1875 | T19: 1875 | U19: 30000 | V19: 0 | W19: 0 | X19: 0 | Y19: 0 | Z19: 0 | AA19: 175.4386 | AB19: 0 | AC19: 0 | AD19: 30000 | AE19: 0 | AF19: 0 | AG19: 0 | AH19: 0 | AI19: 30000 | AJ19: 0 | AK19: 0 | AL19: 0 | AM19: Amanullah | AN19: 0 | AO19: 0 | AP19: 0 | AQ19: 0 | AR19: 30000 | AS19: 30000 | AT19: 0 | AU19: 30000 | AW19: 202 | AX19: =+F19-AW19 -> -26
AW20: 250 | AX20: =+F20-AW20 -> -250
AW21: 147 | AX21: =+F21-AW21 -> -147
AW22: 173 | AX22: =+F22-AW22 -> -173
AW23: 174 | AX23: =+F23-AW23 -> -174
AW24: 177 | AX24: =+F24-AW24 -> -177
AW25: 26 | AX25: =+F25-AW25 -> -26
AW26: 189 | AX26: =+F26-AW26 -> -189
AW27: 221 | AX27: =+F27-AW27 -> -221
AW28: 97 | AX28: =+F28-AW28 -> -97
AW29: 113 | AX29: =+F29-AW29 -> -113
AW30: 107 | AX30: =+F30-AW30 -> -107
AW31: 82 | AX31: =+F31-AW31 -> -82
... AW42: 184 | AX42: =+F42-AW42 -> -184
P57: =SUBTOTAL(9,P8:P56) -> 250000 | Q57: =SUBTOTAL(9,Q8:Q56) -> 156250 | R57: =SUBTOTAL(9,R8:R56) -> 62500 | S57: =SUBTOTAL(9,S8:S56) -> 15625 | T57: =SUBTOTAL(9,T8:T56) -> 15625 | U57: =SUBTOTAL(9,U8:U56) -> 250000 | V57: =SUBTOTAL(9,V8:V56) -> 0 | X57: =SUBTOTAL(9,X8:X56) -> 0 | Z57: =SUBTOTAL(9,Z8:Z56) -> 37131.579 | AC57: =SUBTOTAL(9,AC8:AC56) -> 2192.9825 | AD57: =SUBTOTAL(9,AD8:AD56) -> 210675.44 | AE57: =SUBTOTAL(9,AE8:AE56) -> 0 | AF57: =SUBTOTAL(9,AF8:AF56) -> 0 | AG57: =SUBTOTAL(9,AG8:AG56) -> 7000 | AH57: =SUBTOTAL(9,AH8:AH56) -> 5000 | AI57: =SUBTOTAL(9,AI8:AI56) -> 198675.44 | AN57: =SUBTOTAL(9,AN8:AN56) -> 41000 | AO57: =SUBTOTAL(9,AO8:AO56) -> 0 | AP57: =SUBTOTAL(9,AP8:AP56) -> 0 | AQ57: =SUBTOTAL(9,AQ8:AQ56) -> 75000 | AR57: =SUBTOTAL(9,AR8:AR56) -> 66447.368 | AS57: =SUBTOTAL(9,AS8:AS56) -> 182447.37 | AT57: =SUBTOTAL(9,AT8:AT56) -> 16228.07 | AU57: =SUBTOTAL(9,AU8:AU56) -> 198675.44
AU58: =+AU57-AI57 -> 0
AS59: 1429657.2
AS60: -3694 | AT60: Optome
AS61: -4053 | AT61: Transworld Home
AS62: -157400 | AT62: DIB
AS63: =SUM(AS59:AS62) -> 1264510.2 | AT63: Available Balance
AS64: =+AS63-AS57 -> 1082062.9

Sheet Payroll DES Apr24
A1: BSD Technologies (Design Division) | O1: HIDE | Q1: HIDE | R1: HIDE | S1: HIDE | T1: HIDE | AA1: HIDE | AB1: HIDE | AC1: HIDE
A2: Payroll | C2: April | G2: 2024
G4: 2 | H4: 3 | I4: 4 | J4: 5 | K4: 6 | L4: 7 | M4: 8 | N4: 9 | O4: 10 | P4: 11 | Q4: 12 | R4: 13 | S4: 14 | T4: 15 | U4: 16 | V4: 17 | W4: 18 | X4: 19 | Y4: 20 | Z4: 21 | AA4: 22 | AB4: 23 | AC4: 24 | AD4: 25 | AE4: 26 | AF4: 27 | AG4: 28 | AH4: 29 | AI4: 30 | AJ4: 31 | AK4: 32 | AL4: 33 | AM4: 34 | AN4: 35 | AO4: 36 | AP4: 37 | AQ4: 38 | AR4: 39 | AS4: 40 | AT4: 41 | AU4: 42
B5: Sr.No | C5: Emp Code | D5: Incr. Date | E5: Incr. Amount | F5: Incr. Months | G5: DOJ (DD/MM/Y) | H5: CURRENT STATUS | I5: Employee Name (CNIC) | J5: Department | K5: Designation | L5: Reporting Manager | M5: MCS | N5: BRAND | O5: Status | P5: Gross Salary | Q5: Basic Salary | R5: H.Rent All | S5: Ut. All | T5: Conv. All | U5: Gross salary | V5: Bonus/Incentive/Reimbursemet | W5: No.Extra Days | X5: Amount Ex. Days | Y5: DISAPPROVED Absent Days | Z5: Deduction absent Days | AA5: Hourly Rate | AB5: No. of Ded Hours | AC5: Ded Amt Hrs | AD5: Net Gross (PKR) | AE5: Tax | AF5: EOBI | AG5: Advance | AH5: Loan | AI5: Net Pay | AJ5: Bank Name | AK5: AC Number | AL5: CNIC | AM5: Account Title | AN5: HBL | AO5: Samba | AP5: Cheque | AQ5: IBFT | AR5: Cash | AS5: Payments | AT5: Hold | AU5: Total | AW5: FOREX | AX5: Net Gross (USD)
B7: 1 | C7: 22 | D7: =_xlfn.XLOOKUP(C7,Master[Emp Code],Master[date of last increment]) -> 0 | E7: =_xlfn.XLOOKUP(C7,Master[Emp Code],Master[[last incremnet ]]) -> 0 | F7: =_xlfn.XLOOKUP(C7,Master[Emp Code],Master['# Months Since Last Increment]) -> 0 | G7: =VLOOKUP($C7,Master!$F:$AU,G$4,FALSE) -> 43937 | H7: =VLOOKUP($C7,Master!$F:$AU,H$4,FALSE) -> 0 | I7: =VLOOKUP($C7,Master!$F:$AU,I$4,FALSE) -> Shahmeer Shaikh | J7: =VLOOKUP($C7,Master!$F:$AU,J$4,FALSE) -> Production - Design | K7: =VLOOKUP($C7,Master!$F:$AU,K$4,FALSE) -> 0 | L7: =VLOOKUP($C7,Master!$F:$AU,L$4,FALSE) -> 0 | M7: =VLOOKUP($C7,Master!$F:$AU,M$4,FALSE) -> Portal | N7: =VLOOKUP($C7,Master!$F:$AU,N$4,FALSE) -> Portal | ... AK7: =VLOOKUP($C7,Master!$F:$AU,AK$4,FALSE) -> 0017-79008990-03 | AL7: 4220137461061 | AM7: =VLOOKUP($C7,Master!$F:$AU,AM$4,FALSE) -> Shahmeer Shaikh | AN7: =VLOOKUP($C7,Master!$F:$AU,AN$4,FALSE) -> 71428.571 | AO7: =VLOOKUP($C7,Master!$F:$AU,AO$4,FALSE) -> 0 | AP7: =VLOOKUP($C7,Master!$F:$AU,AP$4,FALSE) -> 0 | AQ7: =VLOOKUP($C7,Master!$F:$AU,AQ$4,FALSE) -> 0 | AR7: =VLOOKUP($C7,Master!$F:$AU,AR$4,FALSE) -> 0 | AS7: =VLOOKUP($C7,Master!$F:$AU,AS$4,FALSE) -> 71428.571 | AT7: =VLOOKUP($C7,Master!$F:$AU,AT$4,FALSE) -> 0 | AU7: =VLOOKUP($C7,Master!$F:$AU,AU$4,FALSE) -> 71428.571 | AW7: =+Master!$K$1 -> 276 | AX7: =+AD7/AW7 -> 258.79917 | AY7: =+AD7/AW7 -> 258.79917
B8: 1 | C8: 80 | D8: =_xlfn.XLOOKUP(C8,Master[Emp Code],Master[date of last increment]) -> 0 | E8: =_xlfn.XLOOKUP(C8,Master[Emp Code],Master[[last incremnet ]]) -> 0 | F8: =_xlfn.XLOOKUP(C8,Master[Emp Code],Master['# Months Since Last Increment]) -> 0 | G8: =VLOOKUP($C8,Master!$F:$AU,G$4,FALSE) -> 0 | H8: =VLOOKUP($C8,Master!$F:$AU,H$4,FALSE) -> 0 | I8: =VLOOKUP($C8,Master!$F:$AU,I$4,FALSE) -> Ibtihaj Ali Haider | J8: =VLOOKUP($C8,Master!$F:$AU,J$4,FALSE) -> Sales | K8: =VLOOKUP($C8,Master!$F:$AU,K$4,FALSE) -> 0 | L8: =VLOOKUP($C8,Master!$F:$AU,L$4,FALSE) -> 0 | M8: =VLOOKUP($C8,Master!$F:$AU,M$4,FALSE) -> Portal | N8: =VLOOKUP($C8,Master!$F:$AU,N$4,FALSE) -> Portal | ... AK8: =VLOOKUP($C8,Master!$F:$AU,AK$4,FALSE) -> 0017-79008290-03 | AL8: 4220137461061 | AM8: =VLOOKUP($C8,Master!$F:$AU,AM$4,FALSE) -> Muhammad Ibtehaj Ali Haider | AN8: =VLOOKUP($C8,Master!$F:$AU,AN$4,FALSE) -> 175000 | AO8: =VLOOKUP($C8,Master!$F:$AU,AO$4,FALSE) -> 0 | AP8: =VLOOKUP($C8,Master!$F:$AU,AP$4,FALSE) -> 0 | AQ8: =VLOOKUP($C8,Master!$F:$AU,AQ$4,FALSE) -> 0 | AR8: =VLOOKUP($C8,Master!$F:$AU,AR$4,FALSE) -> 0 | AS8: =VLOOKUP($C8,Master!$F:$AU,AS$4,FALSE) -> 175000 | AT8: =VLOOKUP($C8,Master!$F:$AU,AT$4,FALSE) -> 0 | AU8: =VLOOKUP($C8,Master!$F:$AU,AU$4,FALSE) -> 175000 | AW8: =+Master!$K$1 -> 276 | AX8: =+AD8/AW8 -> 634.05797 | AY8: =+AD8/AW8 -> 634.05797
P11: =SUBTOTAL(9,P7:P10) -> 275000 | Q11: =SUBTOTAL(9,Q7:Q10) -> 171875 | R11: =SUBTOTAL(9,R7:R10) -> 68750 | S11: =SUBTOTAL(9,S7:S10) -> 17187.5 | T11: =SUBTOTAL(9,T7:T10) -> 17187.5 | U11: =SUBTOTAL(9,U7:U10) -> 275000 | V11: =SUBTOTAL(9,V7:V10) -> 0 | X11: =SUBTOTAL(9,X7:X10) -> 0 | Z11: =SUBTOTAL(9,Z7:Z10) -> 28571.429 | AC11: =SUBTOTAL(9,AC7:AC10) -> 0 | AD11: =SUBTOTAL(9,AD7:AD10) -> 246428.57 | AE11: =SUBTOTAL(9,AE7:AE10) -> 0 | AF11: =SUBTOTAL(9,AF7:AF10) -> 0 | AG11: =SUBTOTAL(9,AG7:AG10) -> 0 | AH11: =SUBTOTAL(9,AH7:AH10) -> 0 | AI11: =SUBTOTAL(9,AI7:AI10) -> 246428.57 | AN11: =SUBTOTAL(9,AN7:AN10) -> 246428.57 | AO11: =SUBTOTAL(9,AO7:AO10) -> 0 | AP11: =SUBTOTAL(9,AP7:AP10) -> 0 | AQ11: =SUBTOTAL(9,AQ7:AQ10) -> 0 | AR11: =SUBTOTAL(9,AR7:AR10) -> 0 | AS11: =SUBTOTAL(9,AS7:AS10) -> 246428.57 | AT11: =SUBTOTAL(9,AT7:AT10) -> 0 | AU11: =SUBTOTAL(9,AU7:AU10) -> 246428.57 | AX11: =SUBTOTAL(9,AX7:AX10) -> 892.85714
P16: =SUBTOTAL(9,P13:P15) -> 0 | Q16: =SUBTOTAL(9,Q13:Q15) -> 0 | R16: =SUBTOTAL(9,R13:R15) -> 0 | S16: =SUBTOTAL(9,S13:S15) -> 0 | T16: =SUBTOTAL(9,T13:T15) -> 0 | U16: =SUBTOTAL(9,U13:U15) -> 0 | V16: =SUBTOTAL(9,V13:V15) -> 0 | X16: =SUBTOTAL(9,X13:X14) -> 0 | Z16: =SUBTOTAL(9,Z13:Z15) -> 0 | AD16: =SUBTOTAL(9,AD13:AD15) -> 0 | AE16: =SUBTOTAL(9,AE13:AE15) -> 0 | AF16: =SUBTOTAL(9,AF13:AF15) -> 0 | AG16: =SUBTOTAL(9,AG13:AG15) -> 0 | AH16: =SUBTOTAL(9,AH13:AH15) -> 0 | AI16: =SUBTOTAL(9,AI13:AI15) -> 0 | AJ16: =SUBTOTAL(9,AJ13:AJ15) -> 0 | AK16: =SUBTOTAL(9,AK13:AK15) -> 0 | ... AU16: =SUBTOTAL(9,AU13:AU15) -> 0 | AX16: =SUBTOTAL(9,AX13:AX14) -> 0
P18: =SUBTOTAL(9,P6:P17) -> 275000 | Q18: =SUBTOTAL(9,Q6:Q17) -> 171875 | R18: =SUBTOTAL(9,R6:R17) -> 68750 | S18: =SUBTOTAL(9,S6:S17) -> 17187.5 | T18: =SUBTOTAL(9,T6:T17) -> 17187.5 | U18: =SUBTOTAL(9,U6:U17) -> 275000 | V18: =SUBTOTAL(9,V6:V17) -> 0 | X18: =SUBTOTAL(9,X6:X17) -> 0 | Z18: =SUBTOTAL(9,Z6:Z17) -> 28571.429 | AC18: =SUBTOTAL(9,AC6:AC17) -> 0 | AD18: =SUBTOTAL(9,AD6:AD17) -> 246428.57 | AE18: =SUBTOTAL(9,AE6:AE17) -> 0 | AF18: =SUBTOTAL(9,AF6:AF17) -> 0 | AG18: =SUBTOTAL(9,AG6:AG17) -> 0 | AH18: =SUBTOTAL(9,AH6:AH17) -> 0 | AI18: =SUBTOTAL(9,AI6:AI17) -> 246428.57 | AN18: =SUBTOTAL(9,AN6:AN17) -> 246428.57 | AO18: =SUBTOTAL(9,AO6:AO17) -> 0 | AP18: =SUBTOTAL(9,AP6:AP17) -> 0 | AQ18: =SUBTOTAL(9,AQ6:AQ17) -> 0 | AR18: =SUBTOTAL(9,AR6:AR17) -> 0 | AS18: =SUBTOTAL(9,AS6:AS17) -> 246428.57 | AT18: =SUBTOTAL(9,AT6:AT17) -> 0 | AU18: =SUBTOTAL(9,AU6:AU17) -> 246428.57 | AX18: =SUBTOTAL(9,AX6:AX17) -> 892.85714
M20: PORTAL | N20: Unit - I | P20: =SUMIFS(Master!P$7:P$57,Master!$M$7:$M$57,'Payroll DES Apr24'!$M20,Master!$N$7:$N$57,'Payroll DES Apr24'!$N20) -> 0 | U20: =SUMIFS(Master!U$7:U$57,Master!$M$7:$M$57,'Payroll DES Apr24'!$M20,Master!$N$7:$N$57,'Payroll DES Apr24'!$N20) -> 0 | Z20: =SUMIFS(Master!Z$7:Z$57,Master!$M$7:$M$57,'Payroll DES Apr24'!$M20,Master!$N$7:$N$57,'Payroll DES Apr24'!$N20) -> 0 | AC20: =SUMIFS(Master!AC$7:AC$57,Master!$M$7:$M$57,'Payroll DES Apr24'!$M20,Master!$N$7:$N$57,'Payroll DES Apr24'!$N20) -> 0 | AD20: =SUMIFS(Master!AD$7:AD$57,Master!$M$7:$M$57,'Payroll DES Apr24'!$M20,Master!$N$7:$N$57,'Payroll DES Apr24'!$N20) -> 0 | AE20: =SUMIFS(Master!AE$7:AE$57,Master!$M$7:$M$57,'Payroll DES Apr24'!$M20,Master!$N$7:$N$57,'Payroll DES Apr24'!$N20) -> 0 | AF20: =SUMIFS(Master!AF$7:AF$57,Master!$M$7:$M$57,'Payroll DES Apr24'!$M20,Master!$N$7:$N$57,'Payroll DES Apr24'!$N20) -> 0 | AG20: =SUMIFS(Master!AG$7:AG$57,Master!$M$7:$M$57,'Payroll DES Apr24'!$M20,Master!$N$7:$N$57,'Payroll DES Apr24'!$N20) -> 0 | AH20: =SUMIFS(Master!AH$7:AH$57,Master!$M$7:$M$57,'Payroll DES Apr24'!$M20,Master!$N$7:$N$57,'Payroll DES Apr24'!$N20) -> 0 | AI20: =SUMIFS(Master!AI$7:AI$57,Master!$M$7:$M$57,'Payroll DES Apr24'!$M20,Master!$N$7:$N$57,'Payroll DES Apr24'!$N20) -> 0 | AN20: =SUMIFS(Master!AN$7:AN$57,Master!$M$7:$M$57,'Payroll DES Apr24'!$M20,Master!$N$7:$N$57,'Payroll DES Apr24'!$N20) -> 0 | AO20: =SUMIFS(Master!AO$7:AO$57,Master!$M$7:$M$57,'Payroll DES Apr24'!$M20,Master!$N$7:$N$57,'Payroll DES Apr24'!$N20) -> 0 | AP20: =SUMIFS(Master!AP$7:AP$57,Master!$M$7:$M$57,'Payroll DES Apr24'!$M20,Master!$N$7:$N$57,'Payroll DES Apr24'!$N20) -> 0 | AQ20: =SUMIFS(Master!AQ$7:AQ$57,Master!$M$7:$M$57,'Payroll DES Apr24'!$M20,Master!$N$7:$N$57,'Payroll DES Apr24'!$N20) -> 0 | AR20: =SUMIFS(Master!AR$7:AR$57,Master!$M$7:$M$57,'Payroll DES Apr24'!$M20,Master!$N$7:$N$57,'Payroll DES Apr24'!$N20) -> 0 | AS20: =SUMIFS(Master!AS$7:AS$57,Master!$M$7:$M$57,'Payroll DES Apr24'!$M20,Master!$N$7:$N$57,'Payroll DES Apr24'!$N20) -> 0 | AT20: =SUMIFS(Master!AT$7:AT$57,Master!$M$7:$M$57,'Payroll DES Apr24'!$M20,Master!$N$7:$N$57,'Payroll DES Apr24'!$N20) -> 0 | AU20: =SUMIFS(Master!AU$7:AU$57,Master!$M$7:$M$57,'Payroll DES Apr24'!$M20,Master!$N$7:$N$57,'Payroll DES Apr24'!$N20) -> 0
M21: DD | N21: ALL | P21: =SUMIFS(Master!P$7:P$57,Master!$M$7:$M$57,'Payroll DES Apr24'!$M21,Master!$N$7:$N$57,'Payroll DES Apr24'!$N21) -> 0 | U21: =SUMIFS(Master!U$7:U$57,Master!$M$7:$M$57,'Payroll DES Apr24'!$M21,Master!$N$7:$N$57,'Payroll DES Apr24'!$N21) -> 0 | Z21: =SUMIFS(Master!Z$7:Z$57,Master!$M$7:$M$57,'Payroll DES Apr24'!$M21,Master!$N$7:$N$57,'Payroll DES Apr24'!$N21) -> 0 | AC21: =SUMIFS(Master!AC$7:AC$57,Master!$M$7:$M$57,'Payroll DES Apr24'!$M21,Master!$N$7:$N$57,'Payroll DES Apr24'!$N21) -> 0 | AD21: =SUMIFS(Master!AD$7:AD$57,Master!$M$7:$M$57,'Payroll DES Apr24'!$M21,Master!$N$7:$N$57,'Payroll DES Apr24'!$N21) -> 0 | AE21: =SUMIFS(Master!AE$7:AE$57,Master!$M$7:$M$57,'Payroll DES Apr24'!$M21,Master!$N$7:$N$57,'Payroll DES Apr24'!$N21) -> 0 | AF21: =SUMIFS(Master!AF$7:AF$57,Master!$M$7:$M$57,'Payroll DES Apr24'!$M21,Master!$N$7:$N$57,'Payroll DES Apr24'!$N21) -> 0 | AG21: =SUMIFS(Master!AG$7:AG$57,Master!$M$7:$M$57,'Payroll DES Apr24'!$M21,Master!$N$7:$N$57,'Payroll DES Apr24'!$N21) -> 0 | AH21: =SUMIFS(Master!AH$7:AH$57,Master!$M$7:$M$57,'Payroll DES Apr24'!$M21,Master!$N$7:$N$57,'Payroll DES Apr24'!$N21) -> 0 | AI21: =SUMIFS(Master!AI$7:AI$57,Master!$M$7:$M$57,'Payroll DES Apr24'!$M21,Master!$N$7:$N$57,'Payroll DES Apr24'!$N21) -> 0 | AN21: =SUMIFS(Master!AN$7:AN$57,Master!$M$7:$M$57,'Payroll DES Apr24'!$M21,Master!$N$7:$N$57,'Payroll DES Apr24'!$N21) -> 0 | AO21: =SUMIFS(Master!AO$7:AO$57,Master!$M$7:$M$57,'Payroll DES Apr24'!$M21,Master!$N$7:$N$57,'Payroll DES Apr24'!$N21) -> 0 | AP21: =SUMIFS(Master!AP$7:AP$57,Master!$M$7:$M$57,'Payroll DES Apr24'!$M21,Master!$N$7:$N$57,'Payroll DES Apr24'!$N21) -> 0 | AQ21: =SUMIFS(Master!AQ$7:AQ$57,Master!$M$7:$M$57,'Payroll DES Apr24'!$M21,Master!$N$7:$N$57,'Payroll DES Apr24'!$N21) -> 0 | AR21: =SUMIFS(Master!AR$7:AR$57,Master!$M$7:$M$57,'Payroll DES Apr24'!$M21,Master!$N$7:$N$57,'Payroll DES Apr24'!$N21) -> 0 | AS21: =SUMIFS(Master!AS$7:AS$57,Master!$M$7:$M$57,'Payroll DES Apr24'!$M21,Master!$N$7:$N$57,'Payroll DES Apr24'!$N21) -> 0 | AT21: =SUMIFS(Master!AT$7:AT$57,Master!$M$7:$M$57,'Payroll DES Apr24'!$M21,Master!$N$7:$N$57,'Payroll DES Apr24'!$N21) -> 0 | AU21: =SUMIFS(Master!AU$7:AU$57,Master!$M$7:$M$57,'Payroll DES Apr24'!$M21,Master!$N$7:$N$57,'Payroll DES Apr24'!$N21) -> 0
P22: =SUM(P20:P21) -> 0 | U22: =SUM(U20:U21) -> 0 | Z22: =SUM(Z20:Z21) -> 0 | AC22: =SUM(AC20:AC21) -> 0 | AD22: =SUM(AD20:AD21) -> 0 | AE22: =SUM(AE20:AE21) -> 0 | AF22: =SUM(AF20:AF21) -> 0 | AG22: =SUM(AG20:AG21) -> 0 | AH22: =SUM(AH20:AH21) -> 0 | AI22: =SUM(AI20:AI21) -> 0 | AN22: =SUM(AN20:AN21) -> 0 | AO22: =SUM(AO20:AO21) -> 0 | AP22: =SUM(AP20:AP21) -> 0 | AQ22: =SUM(AQ20:AQ21) -> 0 | AR22: =SUM(AR20:AR21) -> 0 | AS22: =SUM(AS20:AS21) -> 0 | AT22: =SUM(AT20:AT21) -> 0 | AU22: =SUM(AU20:AU21) -> 0
AK88: Name Title= Muhammad Rehan
AK90: Bank Name= JS
AK92: ACCOUNT NUMBER: 1251641
AK94: MY IBAN NUMBER: 753557259504000000125164
AK96: My Phone Number: 03048352385

Sheet Payroll HW Apr24
A1: BSD Technologies (Hardware Division) | O1: HIDE | Q1: HIDE | R1: HIDE | S1: HIDE | T1: HIDE | AA1: HIDE | AB1: HIDE | AC1: HIDE
A2: Payroll | C2: April | G2: 2024 | AD2: =#REF!-#REF! -> #REF!
G4: 2 | H4: 3 | I4: 4 | J4: 5 | K4: 6 | L4: 7 | M4: 8 | N4: 9 | O4: 10 | P4: 11 | Q4: 12 | R4: 13 | S4: 14 | T4: 15 | U4: 16 | V4: 17 | W4: 18 | X4: 19 | Y4: 20 | Z4: 21 | AA4: 22 | AB4: 23 | AC4: 24 | AD4: 25 | AE4: 26 | AF4: 27 | AG4: 28 | AH4: 29 | AI4: 30 | AJ4: 31 | AK4: 32 | AL4: 33 | AM4: 34 | AN4: 35 | AO4: 36 | AP4: 37 | AQ4: 38 | AR4: 39 | AS4: 40 | AT4: 41 | AU4: 42
B5: Sr.No | C5: Emp Code | D5: Incr. Date | E5: Incr. Amount | F5: Incr. Months | G5: DOJ (DD/MM/Y) | H5: CURRENT STATUS | I5: Employee Name (CNIC) | J5: Department | K5: Designation | L5: Reporting Manager | M5: MCS | N5: BRAND | O5: Status | P5: Gross Salary | Q5: Basic Salary | R5: H.Rent All | S5: Ut. All | T5: Conv. All | U5: Gross salary | V5: Bonus/Incentive/Reimbursemet | W5: No.Extra Days | X5: Amount Ex. Days | Y5: DISAPPROVED Absent Days | Z5: Deduction absent Days | AA5: Hourly Rate | AB5: No. of Ded Hours | AC5: Ded Amt Hrs | AD5: Net Gross | AE5: Tax | AF5: EOBI | AG5: Advance | AH5: Loan | AI5: Net Pay | AJ5: Bank Name | AK5: AC Number | AL5: CNIC | AM5: Account Title | AN5: HBL | AO5: Samba | AP5: Cheque | AQ5: IBFT | AR5: Cash | AS5: Payments | AT5: Hold | AU5: Total | AX5: FOREX | AY5: Net Gross (USD)
B6: 1 | C6: 174 | D6: =_xlfn.XLOOKUP(C6,Master[Emp Code],Master[date of last increment]) -> 43830 | E6: =_xlfn.XLOOKUP(C6,Master[Emp Code],Master[[last incremnet ]]) -> 10000 | F6: =_xlfn.XLOOKUP(C6,Master[Emp Code],Master['# Months Since Last Increment]) -> 4 | G6: =VLOOKUP($C6,Master!$F:$AU,G$4,FALSE) -> 43277 | H6: =VLOOKUP($C6,Master!$F:$AU,H$4,FALSE) -> CT | I6: =VLOOKUP($C6,Master!$F:$AU,I$4,FALSE) -> Sammad | J6: =VLOOKUP($C6,Master!$F:$AU,J$4,FALSE) -> Data Analysis | K6: =VLOOKUP($C6,Master!$F:$AU,K$4,FALSE) -> Trainee | L6: =VLOOKUP($C6,Master!$F:$AU,L$4,FALSE) -> Azmeer | M6: =VLOOKUP($C6,Master!$F:$AU,M$4,FALSE) -> HW | N6: =VLOOKUP($C6,Master!$F:$AU,N$4,FALSE) -> ALL | ... AU6: =VLOOKUP($C6,Master!$F:$AU,AU$4,FALSE) -> 35000 | AX6: =+Master!$K$1 -> 276 | AY6: =+AD6/AX6 -> 126.81159
B7: 2 | C7: 173 | D7: =_xlfn.XLOOKUP(C7,Master[Emp Code],Master[date of last increment]) -> 43830 | E7: =_xlfn.XLOOKUP(C7,Master[Emp Code],Master[[last incremnet ]]) -> 10000 | F7: =_xlfn.XLOOKUP(C7,Master[Emp Code],Master['# Months Since Last Increment]) -> 4 | G7: =VLOOKUP($C7,Master!$F:$AU,G$4,FALSE) -> 43270 | H7: =VLOOKUP($C7,Master!$F:$AU,H$4,FALSE) -> CT | I7: =VLOOKUP($C7,Master!$F:$AU,I$4,FALSE) -> Mohammad Uzair | J7: =VLOOKUP($C7,Master!$F:$AU,J$4,FALSE) -> Data Analysis | K7: =VLOOKUP($C7,Master!$F:$AU,K$4,FALSE) -> Trainee | L7: =VLOOKUP($C7,Master!$F:$AU,L$4,FALSE) -> Azmeer | M7: =VLOOKUP($C7,Master!$F:$AU,M$4,FALSE) -> HW | N7: =VLOOKUP($C7,Master!$F:$AU,N$4,FALSE) -> ALL | ... AU7: =VLOOKUP($C7,Master!$F:$AU,AU$4,FALSE) -> 35000 | AX7: =+Master!$K$1 -> 276 | AY7: =+AD7/AX7 -> 126.81159
B8: 3 | C8: 147 | D8: =_xlfn.XLOOKUP(C8,Master[Emp Code],Master[date of last increment]) -> 43830 | E8: =_xlfn.XLOOKUP(C8,Master[Emp Code],Master[[last incremnet ]]) -> 10000 | F8: =_xlfn.XLOOKUP(C8,Master[Emp Code],Master['# Months Since Last Increment]) -> 4 | G8: =VLOOKUP($C8,Master!$F:$AU,G$4,FALSE) -> 43186 | H8: =VLOOKUP($C8,Master!$F:$AU,H$4,FALSE) -> CT | I8: =VLOOKUP($C8,Master!$F:$AU,I$4,FALSE) -> Shahbaz Khan | J8: =VLOOKUP($C8,Master!$F:$AU,J$4,FALSE) -> Data Analysis | K8: =VLOOKUP($C8,Master!$F:$AU,K$4,FALSE) -> Trainee | L8: =VLOOKUP($C8,Master!$F:$AU,L$4,FALSE) -> Azmeer | M8: =VLOOKUP($C8,Master!$F:$AU,M$4,FALSE) -> HW | N8: =VLOOKUP($C8,Master!$F:$AU,N$4,FALSE) -> ALL | ... AU8: =VLOOKUP($C8,Master!$F:$AU,AU$4,FALSE) -> 27631.579 | AX8: =+Master!$K$1 -> 276 | AY8: =+AD8/AX8 -> 100.11442
B9: 4 | C9: 191 | D9: =_xlfn.XLOOKUP(C9,Master[Emp Code],Master[date of last increment]) -> 0 | E9: =_xlfn.XLOOKUP(C9,Master[Emp Code],Master[[last incremnet ]]) -> 0 | F9: =_xlfn.XLOOKUP(C9,Master[Emp Code],Master['# Months Since Last Increment]) -> 0 | G9: =VLOOKUP($C9,Master!$F:$AU,G$4,FALSE) -> 43788 | H9: =VLOOKUP($C9,Master!$F:$AU,H$4,FALSE) -> NJ | I9: =VLOOKUP($C9,Master!$F:$AU,I$4,FALSE) -> Usman | J9: =VLOOKUP($C9,Master!$F:$AU,J$4,FALSE) -> Data Analysis | K9: Trainee | L9: Azmeer | M9: HW | N9: ALL | O9: =VLOOKUP($C9,Master!$F:$AU,O$4,FALSE) -> NP | P9: =VLOOKUP($C9,Master!$F:$AU,P$4,FALSE) -> 15000 | Q9: =VLOOKUP($C9,Master!$F:$AU,Q$4,FALSE) -> 9375 | R9: =VLOOKUP($C9,Master!$F:$AU,R$4,FALSE) -> 3750 | S9: =VLOOKUP($C9,Master!$F:$AU,S$4,FALSE) -> 937.5 | T9: =VLOOKUP($C9,Master!$F:$AU,T$4,FALSE) -> 937.5 | U9: =VLOOKUP($C9,Master!$F:$AU,U$4,FALSE) -> 15000 | V9: =VLOOKUP($C9,Master!$F:$AU,V$4,FALSE) -> 0 | ... AK9: =VLOOKUP($C9,Master!$F:$AU,AK$4,FALSE) -> 0 | AL9: 4210149618125 | AM9: =VLOOKUP($C9,Master!$F:$AU,AM$4,FALSE) -> Muhammad Khawar | AN9: =VLOOKUP($C9,Master!$F:$AU,AN$4,FALSE) -> 0 | AO9: =VLOOKUP($C9,Master!$F:$AU,AO$4,FALSE) -> 0 | AP9: =VLOOKUP($C9,Master!$F:$AU,AP$4,FALSE) -> 0 | AQ9: =VLOOKUP($C9,Master!$F:$AU,AQ$4,FALSE) -> 0 | AR9: =VLOOKUP($C9,Master!$F:$AU,AR$4,FALSE) -> 3947.3684 | AS9: =VLOOKUP($C9,Master!$F:$AU,AS$4,FALSE) -> 3947.3684 | AT9: =VLOOKUP($C9,Master!$F:$AU,AT$4,FALSE) -> 0 | AU9: =VLOOKUP($C9,Master!$F:$AU,AU$4,FALSE) -> 3947.3684 | AX9: =+Master!$K$1 -> 276 | AY9: =+AD9/AX9 -> 14.302059
B10: 10 | C10: 26 | D10: =_xlfn.XLOOKUP(C10,Master[Emp Code],Master[date of last increment]) -> 43646 | E10: =_xlfn.XLOOKUP(C10,Master[Emp Code],Master[[last incremnet ]]) -> 20000 | F10: =_xlfn.XLOOKUP(C10,Master[Emp Code],Master['# Months Since Last Increment]) -> 10 | G10: =VLOOKUP($C10,Master!$F:$AU,G$4,FALSE) -> 42601 | H10: =VLOOKUP($C10,Master!$F:$AU,H$4,FALSE) -> CT | I10: =VLOOKUP($C10,Master!$F:$AU,I$4,FALSE) -> Azmeer Sheikh | J10: =VLOOKUP($C10,Master!$F:$AU,J$4,FALSE) -> Data Analysis | K10: =VLOOKUP($C10,Master!$F:$AU,K$4,FALSE) -> Trainee | L10: =VLOOKUP($C10,Master!$F:$AU,L$4,FALSE) -> Umair Kaim Khani | M10: =VLOOKUP($C10,Master!$F:$AU,M$4,FALSE) -> HW | N10: =VLOOKUP($C10,Master!$F:$AU,N$4,FALSE) -> ALL | ... AK10: =VLOOKUP($C10,Master!$F:$AU,AK$4,FALSE) -> 0017-79009066-03 | AL10: 4220137461061 | AM10: =VLOOKUP($C10,Master!$F:$AU,AM$4,FALSE) -> AZMEER SHAIKH | AN10: =VLOOKUP($C10,Master!$F:$AU,AN$4,FALSE) -> 55000 | AO10: =VLOOKUP($C10,Master!$F:$AU,AO$4,FALSE) -> 0 | AP10: =VLOOKUP($C10,Master!$F:$AU,AP$4,FALSE) -> 0 | AQ10: =VLOOKUP($C10,Master!$F:$AU,AQ$4,FALSE) -> 0 | AR10: =VLOOKUP($C10,Master!$F:$AU,AR$4,FALSE) -> 0 | AS10: =VLOOKUP($C10,Master!$F:$AU,AS$4,FALSE) -> 55000 | AT10: =VLOOKUP($C10,Master!$F:$AU,AT$4,FALSE) -> 0 | AU10: =VLOOKUP($C10,Master!$F:$AU,AU$4,FALSE) -> 55000 | AX10: =+Master!$K$1 -> 276 | AY10: =+AD10/AX10 -> 217.3913
B11: 11 | C11: 221 | D11: =_xlfn.XLOOKUP(C11,Master[Emp Code],Master[date of last increment]) -> 0 | E11: =_xlfn.XLOOKUP(C11,Master[Emp Code],Master[[last incremnet ]]) -> 0 | F11: =_xlfn.XLOOKUP(C11,Master[Emp Code],Master['# Months Since Last Increment]) -> 0 | G11: =VLOOKUP($C11,Master!$F:$AU,G$4,FALSE) -> 43479 | H11: =VLOOKUP($C11,Master!$F:$AU,H$4,FALSE) -> 0 | I11: =VLOOKUP($C11,Master!$F:$AU,I$4,FALSE) -> Abdul Sami Kamali | J11: =VLOOKUP($C11,Master!$F:$AU,J$4,FALSE) -> Data Analysis | K11: =VLOOKUP($C11,Master!$F:$AU,K$4,FALSE) -> Trainee | L11: =VLOOKUP($C11,Master!$F:$AU,L$4,FALSE) -> Azmeer | M11: =VLOOKUP($C11,Master!$F:$AU,M$4,FALSE) -> HW | N11: =VLOOKUP($C11,Master!$F:$AU,N$4,FALSE) -> ALL | ... AK11: =VLOOKUP($C11,Master!$F:$AU,AK$4,FALSE) -> 03313102701 | AL11: 4220137461061 | AM11: =VLOOKUP($C11,Master!$F:$AU,AM$4,FALSE) -> Abdul Sami Kamali | AN11: =VLOOKUP($C11,Master!$F:$AU,AN$4,FALSE) -> 0 | AO11: =VLOOKUP($C11,Master!$F:$AU,AO$4,FALSE) -> 0 | AP11: =VLOOKUP($C11,Master!$F:$AU,AP$4,FALSE) -> 0 | AQ11: =VLOOKUP($C11,Master!$F:$AU,AQ$4,FALSE) -> 25000 | AR11: =VLOOKUP($C11,Master!$F:$AU,AR$4,FALSE) -> 0 | AS11: =VLOOKUP($C11,Master!$F:$AU,AS$4,FALSE) -> 25000 | AT11: =VLOOKUP($C11,Master!$F:$AU,AT$4,FALSE) -> 0 | AU11: =VLOOKUP($C11,Master!$F:$AU,AU$4,FALSE) -> 25000 | AX11: =+Master!$K$1 -> 276 | AY11: =+AD11/AX11 -> 90.57971
B12: 12 | C12: 225 | D12: =_xlfn.XLOOKUP(C12,Master[Emp Code],Master[date of last increment]) -> 0 | E12: =_xlfn.XLOOKUP(C12,Master[Emp Code],Master[[last incremnet ]]) -> 0 | F12: =_xlfn.XLOOKUP(C12,Master[Emp Code],Master['# Months Since Last Increment]) -> 0 | G12: =VLOOKUP($C12,Master!$F:$AU,G$4,FALSE) -> 43845 | H12: =VLOOKUP($C12,Master!$F:$AU,H$4,FALSE) -> 0 | I12: =VLOOKUP($C12,Master!$F:$AU,I$4,FALSE) -> Aun Zaidi | J12: =VLOOKUP($C12,Master!$F:$AU,J$4,FALSE) -> Data Analysis | K12: =VLOOKUP($C12,Master!$F:$AU,K$4,FALSE) -> Trainee | L12: =VLOOKUP($C12,Master!$F:$AU,L$4,FALSE) -> Azmeer | M12: =VLOOKUP($C12,Master!$F:$AU,M$4,FALSE) -> HW | N12: =VLOOKUP($C12,Master!$F:$AU,N$4,FALSE) -> ALL | ... AK12: =VLOOKUP($C12,Master!$F:$AU,AK$4,FALSE) -> 08780017874001 | AL12: 4210128184849 | AM12: =VLOOKUP($C12,Master!$F:$AU,AM$4,FALSE) -> SYED AJAZ HUSSAIN ZAIDI | AN12: =VLOOKUP($C12,Master!$F:$AU,AN$4,FALSE) -> 20000 | AO12: =VLOOKUP($C12,Master!$F:$AU,AO$4,FALSE) -> 0 | AP12: =VLOOKUP($C12,Master!$F:$AU,AP$4,FALSE) -> 0 | AQ12: =VLOOKUP($C12,Master!$F:$AU,AQ$4,FALSE) -> 0 | AR12: =VLOOKUP($C12,Master!$F:$AU,AR$4,FALSE) -> 0 | AS12: =VLOOKUP($C12,Master!$F:$AU,AS$4,FALSE) -> 20000 | AT12: =VLOOKUP($C12,Master!$F:$AU,AT$4,FALSE) -> 0 | AU12: =VLOOKUP($C12,Master!$F:$AU,AU$4,FALSE) -> 20000 | AX12: =+Master!$K$1 -> 276 | AY12: =+AD12/AX12 -> 72.463768
B13: 13 | C13: 224 | D13: =_xlfn.XLOOKUP(C13,Master[Emp Code],Master[date of last increment]) -> 0 | E13: =_xlfn.XLOOKUP(C13,Master[Emp Code],Master[[last incremnet ]]) -> 0 | F13: =_xlfn.XLOOKUP(C13,Master[Emp Code],Master['# Months Since Last Increment]) -> 0 | G13: =VLOOKUP($C13,Master!$F:$AU,G$4,FALSE) -> 43861 | H13: =VLOOKUP($C13,Master!$F:$AU,H$4,FALSE) -> 0 | I13: =VLOOKUP($C13,Master!$F:$AU,I$4,FALSE) -> Taha Ahmed | J13: =VLOOKUP($C13,Master!$F:$AU,J$4,FALSE) -> Data Analysis | K13: =VLOOKUP($C13,Master!$F:$AU,K$4,FALSE) -> Trainee | L13: =VLOOKUP($C13,Master!$F:$AU,L$4,FALSE) -> Azmeer | M13: =VLOOKUP($C13,Master!$F:$AU,M$4,FALSE) -> HW | N13: =VLOOKUP($C13,Master!$F:$AU,N$4,FALSE) -> ALL | ... AK13: =VLOOKUP($C13,Master!$F:$AU,AK$4,FALSE) -> PK27MUCB0006802010077407 | AL13: 4210128184849 | AM13: =VLOOKUP($C13,Master!$F:$AU,AM$4,FALSE) -> Zameer Ahmed Usmani | AN13: =VLOOKUP($C13,Master!$F:$AU,AN$4,FALSE) -> 0 | AO13: =VLOOKUP($C13,Master!$F:$AU,AO$4,FALSE) -> 0 | AP13: =VLOOKUP($C13,Master!$F:$AU,AP$4,FALSE) -> 0 | AQ13: =VLOOKUP($C13,Master!$F:$AU,AQ$4,FALSE) -> 15000 | AR13: =VLOOKUP($C13,Master!$F:$AU,AR$4,FALSE) -> 0 | AS13: =VLOOKUP($C13,Master!$F:$AU,AS$4,FALSE) -> 15000 | AT13: =VLOOKUP($C13,Master!$F:$AU,AT$4,FALSE) -> 0 | AU13: =VLOOKUP($C13,Master!$F:$AU,AU$4,FALSE) -> 15000 | AX13: =+Master!$K$1 -> 276 | AY13: =+AD13/AX13 -> 54.347826
P14: =SUBTOTAL(9,P6:P13) -> 240000 | Q14: =SUBTOTAL(9,Q10:Q13) -> 75000 | R14: =SUBTOTAL(9,R10:R13) -> 30000 | S14: =SUBTOTAL(9,S10:S13) -> 7500 | T14: =SUBTOTAL(9,T10:T13) -> 7500 | U14: =SUBTOTAL(9,U6:U13) -> 240000 | V14: =SUBTOTAL(9,#REF!) -> #REF! | X14: =SUBTOTAL(9,X6:X13) -> 0 | Z14: =SUBTOTAL(9,Z6:Z13) -> 18421.053 | AA14: =SUBTOTAL(9,AA10:AA13) -> 701.75439 | AB14: =SUBTOTAL(9,AB6:AB13) -> 0 | AC14: =SUBTOTAL(9,AC6:AC13) -> 0 | AD14: =SUBTOTAL(9,AD6:AD13) -> 221578.95 | AE14: =SUBTOTAL(9,AE6:AE13) -> 0 | AF14: =SUBTOTAL(9,AF6:AF13) -> 0 | AG14: =SUBTOTAL(9,AG6:AG13) -> 0 | AH14: =SUBTOTAL(9,AH6:AH13) -> 5000 | AI14: =SUBTOTAL(9,AI6:AI13) -> 216578.95 | ... AU14: =SUBTOTAL(9,AU6:AU13) -> 216578.95 | AY14: =SUBTOTAL(9,AY10:AY13) -> 434.78261
B16: 6 | C16: 228 | D16: =_xlfn.XLOOKUP(C16,Master[Emp Code],Master[date of last increment]) -> 0 | E16: =_xlfn.XLOOKUP(C16,Master[Emp Code],Master[[last incremnet ]]) -> 0 | F16: =_xlfn.XLOOKUP(C16,Master[Emp Code],Master['# Months Since Last Increment]) -> 0 | G16: =VLOOKUP($C16,Master!$F:$AU,G$4,FALSE) -> 0 | H16: =VLOOKUP($C16,Master!$F:$AU,H$4,FALSE) -> 0 | I16: =VLOOKUP($C16,Master!$F:$AU,I$4,FALSE) -> Kashan Ahmed | J16: =VLOOKUP($C16,Master!$F:$AU,J$4,FALSE) -> Marketing - SEO | K16: =VLOOKUP($C16,Master!$F:$AU,K$4,FALSE) -> SEO Intern | L16: =VLOOKUP($C16,Master!$F:$AU,L$4,FALSE) -> Muhammad Yousuf | M16: =VLOOKUP($C16,Master!$F:$AU,M$4,FALSE) -> HW | N16: =VLOOKUP($C16,Master!$F:$AU,N$4,FALSE) -> ALL | ... AK16: =VLOOKUP($C16,Master!$F:$AU,AK$4,FALSE) -> PK62FAYS3573383000001097 | AL16: 4220137649911 | AM16: =VLOOKUP($C16,Master!$F:$AU,AM$4,FALSE) -> Kashan Ahmed | AN16: =VLOOKUP($C16,Master!$F:$AU,AN$4,FALSE) -> 0 | AO16: =VLOOKUP($C16,Master!$F:$AU,AO$4,FALSE) -> 0 | AP16: =VLOOKUP($C16,Master!$F:$AU,AP$4,FALSE) -> 0 | AQ16: =VLOOKUP($C16,Master!$F:$AU,AQ$4,FALSE) -> 0 | AR16: =VLOOKUP($C16,Master!$F:$AU,AR$4,FALSE) -> 0 | AS16: =VLOOKUP($C16,Master!$F:$AU,AS$4,FALSE) -> 0 | AT16: =VLOOKUP($C16,Master!$F:$AU,AT$4,FALSE) -> 9210.5263 | AU16: =VLOOKUP($C16,Master!$F:$AU,AU$4,FALSE) -> 9210.5263 | AX16: =+Master!$K$1 -> 276 | AY16: =+AD16/AX16 -> 33.371472
B17: 7 | C17: 202 | D17: =_xlfn.XLOOKUP(C17,Master[Emp Code],Master[date of last increment]) -> 43890 | E17: =_xlfn.XLOOKUP(C17,Master[Emp Code],Master[[last incremnet ]]) -> 10000 | F17: =_xlfn.XLOOKUP(C17,Master[Emp Code],Master['# Months Since Last Increment]) -> 0 | G17: =VLOOKUP($C17,Master!$F:$AU,G$4,FALSE) -> 43760 | H17: =VLOOKUP($C17,Master!$F:$AU,H$4,FALSE) -> CT | I17: =VLOOKUP($C17,Master!$F:$AU,I$4,FALSE) -> Muhammad Huzaifa Haleem | J17: =VLOOKUP($C17,Master!$F:$AU,J$4,FALSE) -> Marketing - SEO | K17: =VLOOKUP($C17,Master!$F:$AU,K$4,FALSE) -> SEO Intern | L17: =VLOOKUP($C17,Master!$F:$AU,L$4,FALSE) -> Muhammad Yousuf | M17: =VLOOKUP($C17,Master!$F:$AU,M$4,FALSE) -> HW | N17: =VLOOKUP($C17,Master!$F:$AU,N$4,FALSE) -> ALL | ... AK17: =VLOOKUP($C17,Master!$F:$AU,AK$4,FALSE) -> 03491838351 | AL17: 4220137649911 | AM17: =VLOOKUP($C17,Master!$F:$AU,AM$4,FALSE) -> Muhammad Huzaifa Haleem | AN17: =VLOOKUP($C17,Master!$F:$AU,AN$4,FALSE) -> 0 | AO17: =VLOOKUP($C17,Master!$F:$AU,AO$4,FALSE) -> 0 | AP17: =VLOOKUP($C17,Master!$F:$AU,AP$4,FALSE) -> 0 | AQ17: =VLOOKUP($C17,Master!$F:$AU,AQ$4,FALSE) -> 0 | AR17: =VLOOKUP($C17,Master!$F:$AU,AR$4,FALSE) -> 0 | AS17: =VLOOKUP($C17,Master!$F:$AU,AS$4,FALSE) -> 0 | AT17: =VLOOKUP($C17,Master!$F:$AU,AT$4,FALSE) -> 16228.07 | AU17: =VLOOKUP($C17,Master!$F:$AU,AU$4,FALSE) -> 16228.07 | AX17: =+Master!$K$1 -> 276 | AY17: =+AD17/AX17 -> 58.797356
B18: 8 | C18: 149 | D18: =_xlfn.XLOOKUP(C18,Master[Emp Code],Master[date of last increment]) -> 0 | E18: =_xlfn.XLOOKUP(C18,Master[Emp Code],Master[[last incremnet ]]) -> 0 | F18: =_xlfn.XLOOKUP(C18,Master[Emp Code],Master['# Months Since Last Increment]) -> 0 | G18: =VLOOKUP($C18,Master!$F:$AU,G$4,FALSE) -> 43622 | H18: =VLOOKUP($C18,Master!$F:$AU,H$4,FALSE) -> CT | I18: =VLOOKUP($C18,Master!$F:$AU,I$4,FALSE) -> Muhammad Yousuf | J18: =VLOOKUP($C18,Master!$F:$AU,J$4,FALSE) -> Marketing - SEO | K18: =VLOOKUP($C18,Master!$F:$AU,K$4,FALSE) -> SEO Manager | L18: =VLOOKUP($C18,Master!$F:$AU,L$4,FALSE) -> Umair Kaim Khani | M18: =VLOOKUP($C18,Master!$F:$AU,M$4,FALSE) -> HW | N18: =VLOOKUP($C18,Master!$F:$AU,N$4,FALSE) -> ALL | ... AK18: =VLOOKUP($C18,Master!$F:$AU,AK$4,FALSE) -> 2443-79014079-03 | AL18: 4220137649911 | AM18: =VLOOKUP($C18,Master!$F:$AU,AM$4,FALSE) -> Muhammad yousuf | AN18: =VLOOKUP($C18,Master!$F:$AU,AN$4,FALSE) -> 50000 | AO18: =VLOOKUP($C18,Master!$F:$AU,AO$4,FALSE) -> 0 | AP18: =VLOOKUP($C18,Master!$F:$AU,AP$4,FALSE) -> 0 | AQ18: =VLOOKUP($C18,Master!$F:$AU,AQ$4,FALSE) -> 0 | AR18: =VLOOKUP($C18,Master!$F:$AU,AR$4,FALSE) -> 0 | AS18: =VLOOKUP($C18,Master!$F:$AU,AS$4,FALSE) -> 50000 | AT18: =VLOOKUP($C18,Master!$F:$AU,AT$4,FALSE) -> 0 | AU18: =VLOOKUP($C18,Master!$F:$AU,AU$4,FALSE) -> 50000 | AX18: =+Master!$K$1 -> 276 | AY18: =+AD18/AX18 -> 181.15942
B19: 14 | C19: 222 | D19: =_xlfn.XLOOKUP(C19,Master[Emp Code],Master[date of last increment]) -> 0 | E19: =_xlfn.XLOOKUP(C19,Master[Emp Code],Master[[last incremnet ]]) -> 0 | F19: =_xlfn.XLOOKUP(C19,Master[Emp Code],Master['# Months Since Last Increment]) -> 0 | G19: =VLOOKUP($C19,Master!$F:$AU,G$4,FALSE) -> 43861 | H19: =VLOOKUP($C19,Master!$F:$AU,H$4,FALSE) -> 0 | I19: =VLOOKUP($C19,Master!$F:$AU,I$4,FALSE) -> Moin Shaikh | J19: =VLOOKUP($C19,Master!$F:$AU,J$4,FALSE) -> Marketing - SEO | K19: =VLOOKUP($C19,Master!$F:$AU,K$4,FALSE) -> SEO Intern | L19: =VLOOKUP($C19,Master!$F:$AU,L$4,FALSE) -> Muhammad Yousuf | M19: =VLOOKUP($C19,Master!$F:$AU,M$4,FALSE) -> HW | N19: =VLOOKUP($C19,Master!$F:$AU,N$4,FALSE) -> ALL | ... AK19: =VLOOKUP($C19,Master!$F:$AU,AK$4,FALSE) -> PK26MEZN0001430109041892 | AL19: 4210128184849 | AM19: =VLOOKUP($C19,Master!$F:$AU,AM$4,FALSE) -> MOHAMMAD MOIN UDDIN | AN19: =VLOOKUP($C19,Master!$F:$AU,AN$4,FALSE) -> 0 | AO19: =VLOOKUP($C19,Master!$F:$AU,AO$4,FALSE) -> 0 | AP19: =VLOOKUP($C19,Master!$F:$AU,AP$4,FALSE) -> 0 | AQ19: =VLOOKUP($C19,Master!$F:$AU,AQ$4,FALSE) -> 20000 | AR19: =VLOOKUP($C19,Master!$F:$AU,AR$4,FALSE) -> 0 | AS19: =VLOOKUP($C19,Master!$F:$AU,AS$4,FALSE) -> 20000 | AT19: =VLOOKUP($C19,Master!$F:$AU,AT$4,FALSE) -> 0 | AU19: =VLOOKUP($C19,Master!$F:$AU,AU$4,FALSE) -> 20000 | AX19: =+Master!$K$1 -> 276 | AY19: =+AD19/AX19 -> 72.463768
P20: =SUBTOTAL(9,P16:P19) -> 130000 | Q20: =SUBTOTAL(9,Q16:Q19) -> 81250 | R20: =SUBTOTAL(9,R16:R19) -> 32500 | S20: =SUBTOTAL(9,S16:S19) -> 8125 | T20: =SUBTOTAL(9,T16:T19) -> 8125 | U20: =SUBTOTAL(9,U16:U19) -> 130000 | V20: =SUBTOTAL(9,V3:V19) -> 17 | X20: =SUBTOTAL(9,X16:X19) -> 0 | Z20: =SUBTOTAL(9,Z16:Z19) -> 32368.421 | AA20: =SUBTOTAL(9,AA16:AA19) -> 760.23392 | AB20: =SUBTOTAL(9,AB16:AB19) -> 15 | AC20: =SUBTOTAL(9,AC16:AC19) -> 2192.9825 | AD20: =SUBTOTAL(9,AD16:AD19) -> 95438.596 | AE20: =SUBTOTAL(9,AE16:AE19) -> 0 | AF20: =SUBTOTAL(9,AF16:AF19) -> 0 | AG20: =SUBTOTAL(9,AG16:AG19) -> 0 | ... AU20: =SUBTOTAL(9,AU16:AU19) -> 95438.596 | AY20: =SUBTOTAL(9,AY16:AY19) -> 345.79202
B22: 6 | C22: 18 | D22: =_xlfn.XLOOKUP(C22,Master[Emp Code],Master[date of last increment]) -> 43555 | E22: =_xlfn.XLOOKUP(C22,Master[Emp Code],Master[[last incremnet ]]) -> 50000 | F22: =_xlfn.XLOOKUP(C22,Master[Emp Code],Master['# Months Since Last Increment]) -> 13 | G22: =VLOOKUP($C22,Master!$F:$AU,G$4,FALSE) -> 42618 | H22: =VLOOKUP($C22,Master!$F:$AU,H$4,FALSE) -> CT | I22: =VLOOKUP($C22,Master!$F:$AU,I$4,FALSE) -> Umair Kaim Khani | J22: =VLOOKUP($C22,Master!$F:$AU,J$4,FALSE) -> Marketing | K22: =VLOOKUP($C22,Master!$F:$AU,K$4,FALSE) -> Project Coordinator | L22: =VLOOKUP($C22,Master!$F:$AU,L$4,FALSE) -> Wahaj Qureshi | M22: =VLOOKUP($C22,Master!$F:$AU,M$4,FALSE) -> HW | N22: =VLOOKUP($C22,Master!$F:$AU,N$4,FALSE) -> ALL | ... AK22: =VLOOKUP($C22,Master!$F:$AU,AK$4,FALSE) -> 0017-79008182-03 | AL22: 4220137649911 | AM22: =VLOOKUP($C22,Master!$F:$AU,AM$4,FALSE) -> Muhammad Umair | AN22: =VLOOKUP($C22,Master!$F:$AU,AN$4,FALSE) -> 189960 | AO22: =VLOOKUP($C22,Master!$F:$AU,AO$4,FALSE) -> 0 | AP22: =VLOOKUP($C22,Master!$F:$AU,AP$4,FALSE) -> 0 | AQ22: =VLOOKUP($C22,Master!$F:$AU,AQ$4,FALSE) -> 0 | AR22: =VLOOKUP($C22,Master!$F:$AU,AR$4,FALSE) -> 0 | AS22: =VLOOKUP($C22,Master!$F:$AU,AS$4,FALSE) -> 189960 | AT22: =VLOOKUP($C22,Master!$F:$AU,AT$4,FALSE) -> 0 | AU22: =VLOOKUP($C22,Master!$F:$AU,AU$4,FALSE) -> 189960 | AX22: =+Master!$K$1 -> 276 | AY22: =+AD22/AX22 -> 996.37681
P23: =SUBTOTAL(9,P22:P22) -> 200000 | Q23: =SUBTOTAL(9,Q6:Q22) -> 356250 | R23: =SUBTOTAL(9,R6:R22) -> 142500 | S23: =SUBTOTAL(9,S6:S22) -> 35625 | T23: =SUBTOTAL(9,T6:T22) -> 110625 | U23: =SUBTOTAL(9,U22:U22) -> 275000 | V23: =SUBTOTAL(9,V6:V22) -> 0 | X23: =SUBTOTAL(9,X22:X22) -> 0 | Z23: =SUBTOTAL(9,Z22:Z22) -> 0 | AD23: =SUBTOTAL(9,AD22:AD22) -> 275000 | AE23: =SUBTOTAL(9,AE22:AE22) -> 9790 | AF23: =SUBTOTAL(9,AF22:AF22) -> 250 | AG23: =SUBTOTAL(9,AG22:AG22) -> 75000 | AH23: =SUBTOTAL(9,AH22:AH22) -> 0 | AI23: =SUBTOTAL(9,AI22:AI22) -> 189960 | AJ23: =SUBTOTAL(9,AJ22:AJ22) -> 0 | AK23: =SUBTOTAL(9,AK22:AK22) -> 0 | ... AU23: =SUBTOTAL(9,AU22:AU22) -> 189960 | AY23: =SUBTOTAL(9,AY22:AY22) -> 996.37681
B25: 15 | C25: 70 | D25: =_xlfn.XLOOKUP(C25,Master[Emp Code],Master[date of last increment]) -> 43677 | E25: =_xlfn.XLOOKUP(C25,Master[Emp Code],Master[[last incremnet ]]) -> 25000 | F25: =_xlfn.XLOOKUP(C25,Master[Emp Code],Master['# Months Since Last Increment]) -> 9 | G25: =VLOOKUP($C25,Master!$F:$AU,G$4,FALSE) -> 42808 | H25: =VLOOKUP($C25,Master!$F:$AU,H$4,FALSE) -> CT | I25: =VLOOKUP($C25,Master!$F:$AU,I$4,FALSE) -> Khawaja Muhammad Ali | J25: =VLOOKUP($C25,Master!$F:$AU,J$4,FALSE) -> Procurement | K25: =VLOOKUP($C25,Master!$F:$AU,K$4,FALSE) -> Procurrement Executive | L25: =VLOOKUP($C25,Master!$F:$AU,L$4,FALSE) -> Wahaj Qureshi | M25: =VLOOKUP($C25,Master!$F:$AU,M$4,FALSE) -> HW | N25: =VLOOKUP($C25,Master!$F:$AU,N$4,FALSE) -> BD | ... AU25: =VLOOKUP($C25,Master!$F:$AU,AU$4,FALSE) -> 122808.8 | AX25: =+Master!$K$1 -> 276 | AY25: =+AD25/AX25 -> 760.86957
B26: =+B25+1 -> 16 | C26: 113 | D26: =_xlfn.XLOOKUP(C26,Master[Emp Code],Master[date of last increment]) -> 43708 | E26: =_xlfn.XLOOKUP(C26,Master[Emp Code],Master[[last incremnet ]]) -> 15000 | F26: =_xlfn.XLOOKUP(C26,Master[Emp Code],Master['# Months Since Last Increment]) -> 8 | G26: =VLOOKUP($C26,Master!$F:$AU,G$4,FALSE) -> 43109 | H26: =VLOOKUP($C26,Master!$F:$AU,H$4,FALSE) -> CT | I26: =VLOOKUP($C26,Master!$F:$AU,I$4,FALSE) -> Affan Khan | J26: =VLOOKUP($C26,Master!$F:$AU,J$4,FALSE) -> Procurement | K26: =VLOOKUP($C26,Master!$F:$AU,K$4,FALSE) -> Procurrement Executive | L26: =VLOOKUP($C26,Master!$F:$AU,L$4,FALSE) -> Khawaja | M26: =VLOOKUP($C26,Master!$F:$AU,M$4,FALSE) -> HW | N26: =VLOOKUP($C26,Master!$F:$AU,N$4,FALSE) -> BD | ... AK26: =VLOOKUP($C26,Master!$F:$AU,AK$4,FALSE) -> 0017-79008738-03 | AL26: 4210149618125 | AM26: =VLOOKUP($C26,Master!$F:$AU,AM$4,FALSE) -> AFFAN KHAN | AN26: =VLOOKUP($C26,Master!$F:$AU,AN$4,FALSE) -> 50000 | AO26: =VLOOKUP($C26,Master!$F:$AU,AO$4,FALSE) -> 0 | AP26: =VLOOKUP($C26,Master!$F:$AU,AP$4,FALSE) -> 0 | AQ26: =VLOOKUP($C26,Master!$F:$AU,AQ$4,FALSE) -> 0 | AR26: =VLOOKUP($C26,Master!$F:$AU,AR$4,FALSE) -> 0 | AS26: =VLOOKUP($C26,Master!$F:$AU,AS$4,FALSE) -> 50000 | AT26: =VLOOKUP($C26,Master!$F:$AU,AT$4,FALSE) -> 0 | AU26: =VLOOKUP($C26,Master!$F:$AU,AU$4,FALSE) -> 50000 | AX26: =+Master!$K$1 -> 276 | AY26: =+AD26/AX26 -> 181.15942
B27: =+B26+1 -> 17 | C27: 82 | D27: =_xlfn.XLOOKUP(C27,Master[Emp Code],Master[date of last increment]) -> 43890 | E27: =_xlfn.XLOOKUP(C27,Master[Emp Code],Master[[last incremnet ]]) -> 15000 | F27: =_xlfn.XLOOKUP(C27,Master[Emp Code],Master['# Months Since Last Increment]) -> 2 | G27: =VLOOKUP($C27,Master!$F:$AU,G$4,FALSE) -> 42874 | H27: =VLOOKUP($C27,Master!$F:$AU,H$4,FALSE) -> CT | I27: =VLOOKUP($C27,Master!$F:$AU,I$4,FALSE) -> Fatima Hasan | J27: =VLOOKUP($C27,Master!$F:$AU,J$4,FALSE) -> Sales | K27: =VLOOKUP($C27,Master!$F:$AU,K$4,FALSE) -> International Sales Executive | L27: =VLOOKUP($C27,Master!$F:$AU,L$4,FALSE) -> Husnain | M27: =VLOOKUP($C27,Master!$F:$AU,M$4,FALSE) -> HW | N27: =VLOOKUP($C27,Master!$F:$AU,N$4,FALSE) -> BD | ... AU27: =VLOOKUP($C27,Master!$F:$AU,AU$4,FALSE) -> 89328.5 | AX27: =+Master!$K$1 -> 276 | AY27: =+AD27/AX27 -> 326.08696
B28: =+B27+1 -> 18 | C28: 107 | D28: =_xlfn.XLOOKUP(C28,Master[Emp Code],Master[date of last increment]) -> 43616 | E28: =_xlfn.XLOOKUP(C28,Master[Emp Code],Master[[last incremnet ]]) -> 35000 | F28: =_xlfn.XLOOKUP(C28,Master[Emp Code],Master['# Months Since Last Increment]) -> 11 | G28: =VLOOKUP($C28,Master!$F:$AU,G$4,FALSE) -> 43508 | H28: =VLOOKUP($C28,Master!$F:$AU,H$4,FALSE) -> CT | I28: =VLOOKUP($C28,Master!$F:$AU,I$4,FALSE) -> Hussnain ali farooqi | J28: =VLOOKUP($C28,Master!$F:$AU,J$4,FALSE) -> Sales | K28: =VLOOKUP($C28,Master!$F:$AU,K$4,FALSE) -> International Sales Executive | L28: =VLOOKUP($C28,Master!$F:$AU,L$4,FALSE) -> Wahaj Qureshi | M28: =VLOOKUP($C28,Master!$F:$AU,M$4,FALSE) -> HW | N28: =VLOOKUP($C28,Master!$F:$AU,N$4,FALSE) -> BD | ... AU28: =VLOOKUP($C28,Master!$F:$AU,AU$4,FALSE) -> 69758.8 | AX28: =+Master!$K$1 -> 276 | AY28: =+AD28/AX28 -> 253.62319
B29: =+B28+1 -> 19 | C29: 133 | D29: =_xlfn.XLOOKUP(C29,Master[Emp Code],Master[date of last increment]) -> 43708 | E29: =_xlfn.XLOOKUP(C29,Master[Emp Code],Master[[last incremnet ]]) -> 40000 | F29: =_xlfn.XLOOKUP(C29,Master[Emp Code],Master['# Months Since Last Increment]) -> 8 | G29: =VLOOKUP($C29,Master!$F:$AU,G$4,FALSE) -> 21 | H29: =VLOOKUP($C29,Master!$F:$AU,H$4,FALSE) -> CT | I29: =VLOOKUP($C29,Master!$F:$AU,I$4,FALSE) -> Eraj Khalid | J29: =VLOOKUP($C29,Master!$F:$AU,J$4,FALSE) -> Sales | K29: =VLOOKUP($C29,Master!$F:$AU,K$4,FALSE) -> Sales/CSE | L29: =VLOOKUP($C29,Master!$F:$AU,L$4,FALSE) -> Husnain | M29: =VLOOKUP($C29,Master!$F:$AU,M$4,FALSE) -> HW | N29: =VLOOKUP($C29,Master!$F:$AU,N$4,FALSE) -> BD | ... AU29: =VLOOKUP($C29,Master!$F:$AU,AU$4,FALSE) -> 79262.6 | AX29: =+Master!$K$1 -> 276 | AY29: =+AD29/AX29 -> 289.85507
C30: 97 | D30: =_xlfn.XLOOKUP(C30,Master[Emp Code],Master[date of last increment]) -> 43890 | E30: =_xlfn.XLOOKUP(C30,Master[Emp Code],Master[[last incremnet ]]) -> 15000 | F30: =_xlfn.XLOOKUP(C30,Master[Emp Code],Master['# Months Since Last Increment]) -> 2 | G30: =VLOOKUP($C30,Master!$F:$AU,G$4,FALSE) -> 43481 | H30: =VLOOKUP($C30,Master!$F:$AU,H$4,FALSE) -> CT | I30: =VLOOKUP($C30,Master!$F:$AU,I$4,FALSE) -> Waniya | J30: =VLOOKUP($C30,Master!$F:$AU,J$4,FALSE) -> Sales | K30: =VLOOKUP($C30,Master!$F:$AU,K$4,FALSE) -> Trainee | L30: =VLOOKUP($C30,Master!$F:$AU,L$4,FALSE) -> Husnain | M30: =VLOOKUP($C30,Master!$F:$AU,M$4,FALSE) -> HW | N30: =VLOOKUP($C30,Master!$F:$AU,N$4,FALSE) -> BD | ... AK30: =VLOOKUP($C30,Master!$F:$AU,AK$4,FALSE) -> 0017-79009274-03 | AL30: 4210149618125 | AM30: =VLOOKUP($C30,Master!$F:$AU,AM$4,FALSE) -> Wania Qureshi | AN30: =VLOOKUP($C30,Master!$F:$AU,AN$4,FALSE) -> 45000 | AO30: =VLOOKUP($C30,Master!$F:$AU,AO$4,FALSE) -> 0 | AP30: =VLOOKUP($C30,Master!$F:$AU,AP$4,FALSE) -> 0 | AQ30: =VLOOKUP($C30,Master!$F:$AU,AQ$4,FALSE) -> 0 | AR30: =VLOOKUP($C30,Master!$F:$AU,AR$4,FALSE) -> 0 | AS30: =VLOOKUP($C30,Master!$F:$AU,AS$4,FALSE) -> 45000 | AT30: =VLOOKUP($C30,Master!$F:$AU,AT$4,FALSE) -> 0 | AU30: =VLOOKUP($C30,Master!$F:$AU,AU$4,FALSE) -> 45000 | AX30: =+Master!$K$1 -> 276 | AY30: =+AD30/AX30 -> 163.04348
C31: 229 | D31: =_xlfn.XLOOKUP(C31,Master[Emp Code],Master[date of last increment]) -> 0 | E31: =_xlfn.XLOOKUP(C31,Master[Emp Code],Master[[last incremnet ]]) -> 0 | F31: =_xlfn.XLOOKUP(C31,Master[Emp Code],Master['# Months Since Last Increment]) -> 0 | G31: =VLOOKUP($C31,Master!$F:$AU,G$4,FALSE) -> 43942 | H31: =VLOOKUP($C31,Master!$F:$AU,H$4,FALSE) -> 0 | I31: =VLOOKUP($C31,Master!$F:$AU,I$4,FALSE) -> Maham Khan | J31: =VLOOKUP($C31,Master!$F:$AU,J$4,FALSE) -> Sales | K31: =VLOOKUP($C31,Master!$F:$AU,K$4,FALSE) -> International Sales Executive | L31: =VLOOKUP($C31,Master!$F:$AU,L$4,FALSE) -> 0 | M31: =VLOOKUP($C31,Master!$F:$AU,M$4,FALSE) -> HW | N31: =VLOOKUP($C31,Master!$F:$AU,N$4,FALSE) -> BD | ... AK31: =VLOOKUP($C31,Master!$F:$AU,AK$4,FALSE) -> PK70HABB0022567901806303 | AL31: 4210149618125 | AM31: =VLOOKUP($C31,Master!$F:$AU,AM$4,FALSE) -> Muhammad Ali | AN31: =VLOOKUP($C31,Master!$F:$AU,AN$4,FALSE) -> 0 | AO31: =VLOOKUP($C31,Master!$F:$AU,AO$4,FALSE) -> 0 | AP31: =VLOOKUP($C31,Master!$F:$AU,AP$4,FALSE) -> 0 | AQ31: =VLOOKUP($C31,Master!$F:$AU,AQ$4,FALSE) -> 0 | AR31: =VLOOKUP($C31,Master!$F:$AU,AR$4,FALSE) -> 10500 | AS31: =VLOOKUP($C31,Master!$F:$AU,AS$4,FALSE) -> 10500 | AT31: =VLOOKUP($C31,Master!$F:$AU,AT$4,FALSE) -> 0 | AU31: =VLOOKUP($C31,Master!$F:$AU,AU$4,FALSE) -> 10500 | AX31: =+Master!$K$1 -> 276 | AY31: =+AD31/AX31 -> 38.043478
B32: =+B29+1 -> 20 | C32: 230 | D32: =_xlfn.XLOOKUP(C32,Master[Emp Code],Master[date of last increment]) -> 0 | E32: =_xlfn.XLOOKUP(C32,Master[Emp Code],Master[[last incremnet ]]) -> 0 | F32: =_xlfn.XLOOKUP(C32,Master[Emp Code],Master['# Months Since Last Increment]) -> 0 | G32: =VLOOKUP($C32,Master!$F:$AU,G$4,FALSE) -> 43945 | H32: =VLOOKUP($C32,Master!$F:$AU,H$4,FALSE) -> 0 | I32: =VLOOKUP($C32,Master!$F:$AU,I$4,FALSE) -> Muhammad Yousha | J32: =VLOOKUP($C32,Master!$F:$AU,J$4,FALSE) -> Sales | K32: =VLOOKUP($C32,Master!$F:$AU,K$4,FALSE) -> International Sales Executive | L32: =VLOOKUP($C32,Master!$F:$AU,L$4,FALSE) -> 0 | M32: =VLOOKUP($C32,Master!$F:$AU,M$4,FALSE) -> HW | N32: =VLOOKUP($C32,Master!$F:$AU,N$4,FALSE) -> BD | ... AK32: =VLOOKUP($C32,Master!$F:$AU,AK$4,FALSE) -> PK08MEZN0001130105931538 | AL32: 4210149618125 | AM32: =VLOOKUP($C32,Master!$F:$AU,AM$4,FALSE) -> Muhammad Yousha | AN32: =VLOOKUP($C32,Master!$F:$AU,AN$4,FALSE) -> 0 | AO32: =VLOOKUP($C32,Master!$F:$AU,AO$4,FALSE) -> 0 | AP32: =VLOOKUP($C32,Master!$F:$AU,AP$4,FALSE) -> 0 | AQ32: =VLOOKUP($C32,Master!$F:$AU,AQ$4,FALSE) -> 5250 | AR32: =VLOOKUP($C32,Master!$F:$AU,AR$4,FALSE) -> 0 | AS32: =VLOOKUP($C32,Master!$F:$AU,AS$4,FALSE) -> 5250 | AT32: =VLOOKUP($C32,Master!$F:$AU,AT$4,FALSE) -> 0 | AU32: =VLOOKUP($C32,Master!$F:$AU,AU$4,FALSE) -> 5250 | AX32: =+Master!$K$1 -> 276 | AY32: =+AD32/AX32 -> 19.021739
P33: =SUBTOTAL(9,P25:P32) -> 525000 | Q33: =SUBTOTAL(9,Q25:Q32) -> 328125 | R33: =SUBTOTAL(9,R25:R32) -> 131250 | S33: =SUBTOTAL(9,S25:S32) -> 32812.5 | T33: =SUBTOTAL(9,T25:T32) -> 117812.5 | U33: =SUBTOTAL(9,U25:U32) -> 610000 | V33: =SUBTOTAL(9,V25:V32) -> 0 | X33: =SUBTOTAL(9,X25:X32) -> 0 | Z33: =SUBTOTAL(9,Z25:Z32) -> 49250 | AC33: =SUBTOTAL(9,AC25:AC32) -> 0 | AD33: =SUBTOTAL(9,AD25:AD32) -> 560750 | AE33: =SUBTOTAL(9,AE25:AE32) -> 3341.3 | AF33: =SUBTOTAL(9,AF25:AF32) -> 500 | AG33: =SUBTOTAL(9,AG25:AG32) -> 85000 | AH33: =SUBTOTAL(9,AH25:AH32) -> 0 | AI33: =SUBTOTAL(9,AI25:AI32) -> 471908.7 | AJ33: =SUBTOTAL(9,AJ25:AJ32) -> 0 | ... AU33: =SUBTOTAL(9,AU25:AU32) -> 471908.7 | AY33: =SUBTOTAL(9,AY25:AY32) -> 2031.7029
B35: 21 | C35: 7 | D35: =_xlfn.XLOOKUP(C35,Master[Emp Code],Master[date of last increment]) -> 43830 | E35: =_xlfn.XLOOKUP(C35,Master[Emp Code],Master[[last incremnet ]]) -> 20000 | F35: =_xlfn.XLOOKUP(C35,Master[Emp Code],Master['# Months Since Last Increment]) -> 4 | G35: =VLOOKUP($C35,Master!$F:$AU,G$4,FALSE) -> 42185 | H35: =VLOOKUP($C35,Master!$F:$AU,H$4,FALSE) -> CT | I35: =VLOOKUP($C35,Master!$F:$AU,I$4,FALSE) -> Ebad Qureshi | J35: =VLOOKUP($C35,Master!$F:$AU,J$4,FALSE) -> Procurement | K35: =VLOOKUP($C35,Master!$F:$AU,K$4,FALSE) -> Manager Procurement | L35: =VLOOKUP($C35,Master!$F:$AU,L$4,FALSE) -> Nadeem Akhtar | M35: =VLOOKUP($C35,Master!$F:$AU,M$4,FALSE) -> HW | N35: =VLOOKUP($C35,Master!$F:$AU,N$4,FALSE) -> ITN | ... AU35: =VLOOKUP($C35,Master!$F:$AU,AU$4,FALSE) -> 96688 | AX35: =+Master!$K$1 -> 276 | AY35: =+AD35/AX35 -> 398.55072
B36: =+B35+1 -> 22 | C36: 8 | D36: =_xlfn.XLOOKUP(C36,Master[Emp Code],Master[date of last increment]) -> 43830 | E36: =_xlfn.XLOOKUP(C36,Master[Emp Code],Master[[last incremnet ]]) -> 15000 | F36: =_xlfn.XLOOKUP(C36,Master[Emp Code],Master['# Months Since Last Increment]) -> 4 | G36: =VLOOKUP($C36,Master!$F:$AU,G$4,FALSE) -> 42308 | H36: =VLOOKUP($C36,Master!$F:$AU,H$4,FALSE) -> CT | I36: =VLOOKUP($C36,Master!$F:$AU,I$4,FALSE) -> Khawar Qureshi | J36: =VLOOKUP($C36,Master!$F:$AU,J$4,FALSE) -> Procurement | K36: =VLOOKUP($C36,Master!$F:$AU,K$4,FALSE) -> Procurement Executive | L36: =VLOOKUP($C36,Master!$F:$AU,L$4,FALSE) -> Nadeem Akhtar | M36: =VLOOKUP($C36,Master!$F:$AU,M$4,FALSE) -> HW | N36: =VLOOKUP($C36,Master!$F:$AU,N$4,FALSE) -> ITN | ... AK36: =VLOOKUP($C36,Master!$F:$AU,AK$4,FALSE) -> 0017-79008521-03 | AL36: 4220183656393 | AM36: =VLOOKUP($C36,Master!$F:$AU,AM$4,FALSE) -> Muhammad Khawar | AN36: =VLOOKUP($C36,Master!$F:$AU,AN$4,FALSE) -> 64750 | AO36: =VLOOKUP($C36,Master!$F:$AU,AO$4,FALSE) -> 0 | AP36: =VLOOKUP($C36,Master!$F:$AU,AP$4,FALSE) -> 0 | AQ36: =VLOOKUP($C36,Master!$F:$AU,AQ$4,FALSE) -> 0 | AR36: =VLOOKUP($C36,Master!$F:$AU,AR$4,FALSE) -> 0 | AS36: =VLOOKUP($C36,Master!$F:$AU,AS$4,FALSE) -> 64750 | AT36: =VLOOKUP($C36,Master!$F:$AU,AT$4,FALSE) -> 0 | AU36: =VLOOKUP($C36,Master!$F:$AU,AU$4,FALSE) -> 64750 | AX36: =+Master!$K$1 -> 276 | AY36: =+AD36/AX36 -> 235.50725
B37: =+B36+1 -> 23 | C37: 44 | D37: =_xlfn.XLOOKUP(C37,Master[Emp Code],Master[date of last increment]) -> 43830 | E37: =_xlfn.XLOOKUP(C37,Master[Emp Code],Master[[last incremnet ]]) -> 50000 | F37: =_xlfn.XLOOKUP(C37,Master[Emp Code],Master['# Months Since Last Increment]) -> 4 | G37: =VLOOKUP($C37,Master!$F:$AU,G$4,FALSE) -> 42825 | H37: =VLOOKUP($C37,Master!$F:$AU,H$4,FALSE) -> CT | I37: =VLOOKUP($C37,Master!$F:$AU,I$4,FALSE) -> Nadeem Akhtar | J37: =VLOOKUP($C37,Master!$F:$AU,J$4,FALSE) -> Sales | K37: =VLOOKUP($C37,Master!$F:$AU,K$4,FALSE) -> International Sales Executive | L37: =VLOOKUP($C37,Master!$F:$AU,L$4,FALSE) -> Wahaj Qureshi | M37: =VLOOKUP($C37,Master!$F:$AU,M$4,FALSE) -> HW | N37: =VLOOKUP($C37,Master!$F:$AU,N$4,FALSE) -> ITN | ... AU37: =VLOOKUP($C37,Master!$F:$AU,AU$4,FALSE) -> 189447.4 | AX37: =+Master!$K$1 -> 276 | AY37: =+AD37/AX37 -> 724.63768
B38: =+B37+1 -> 24 | C38: 180 | D38: =_xlfn.XLOOKUP(C38,Master[Emp Code],Master[date of last increment]) -> 43830 | E38: =_xlfn.XLOOKUP(C38,Master[Emp Code],Master[[last incremnet ]]) -> 35000 | F38: =_xlfn.XLOOKUP(C38,Master[Emp Code],Master['# Months Since Last Increment]) -> 4 | G38: =VLOOKUP($C38,Master!$F:$AU,G$4,FALSE) -> 43307 | H38: =VLOOKUP($C38,Master!$F:$AU,H$4,FALSE) -> CT | I38: =VLOOKUP($C38,Master!$F:$AU,I$4,FALSE) -> Asif Ahmed | J38: =VLOOKUP($C38,Master!$F:$AU,J$4,FALSE) -> Sales | K38: =VLOOKUP($C38,Master!$F:$AU,K$4,FALSE) -> International Sales Executive | L38: =VLOOKUP($C38,Master!$F:$AU,L$4,FALSE) -> Nadeem Akhtar | M38: =VLOOKUP($C38,Master!$F:$AU,M$4,FALSE) -> HW | N38: =VLOOKUP($C38,Master!$F:$AU,N$4,FALSE) -> ITN | ... AU38: =VLOOKUP($C38,Master!$F:$AU,AU$4,FALSE) -> 103988.6 | AX38: =+Master!$K$1 -> 276 | AY38: =+AD38/AX38 -> 380.43478
B39: =+B38+1 -> 25 | C39: 182 | D39: =_xlfn.XLOOKUP(C39,Master[Emp Code],Master[date of last increment]) -> 43830 | E39: =_xlfn.XLOOKUP(C39,Master[Emp Code],Master[[last incremnet ]]) -> 30000 | F39: =_xlfn.XLOOKUP(C39,Master[Emp Code],Master['# Months Since Last Increment]) -> 4 | G39: =VLOOKUP($C39,Master!$F:$AU,G$4,FALSE) -> 43404 | H39: =VLOOKUP($C39,Master!$F:$AU,H$4,FALSE) -> CT | I39: =VLOOKUP($C39,Master!$F:$AU,I$4,FALSE) -> Muhammad Haris Khan | J39: =VLOOKUP($C39,Master!$F:$AU,J$4,FALSE) -> Sales | K39: =VLOOKUP($C39,Master!$F:$AU,K$4,FALSE) -> International Sales Executive | L39: =VLOOKUP($C39,Master!$F:$AU,L$4,FALSE) -> Nadeem Akhtar | M39: =VLOOKUP($C39,Master!$F:$AU,M$4,FALSE) -> HW | N39: =VLOOKUP($C39,Master!$F:$AU,N$4,FALSE) -> ITN | ... AU39: =VLOOKUP($C39,Master!$F:$AU,AU$4,FALSE) -> 79508 | AX39: =+Master!$K$1 -> 276 | AY39: =+AD39/AX39 -> 289.85507
P40: =SUBTOTAL(9,P35:P39) -> 560000 | Q40: =SUBTOTAL(9,Q35:Q39) -> 350000 | R40: =SUBTOTAL(9,R35:R39) -> 140000 | S40: =SUBTOTAL(9,S35:S39) -> 35000 | T40: =SUBTOTAL(9,T35:T39) -> 35000 | U40: =SUBTOTAL(9,U35:U39) -> 560000 | V40: =SUBTOTAL(9,V35:V39) -> 0 | X40: =SUBTOTAL(9,X35:X39) -> 0 | Z40: =SUBTOTAL(9,Z35:Z39) -> 0 | AC40: =SUBTOTAL(9,AC35:AC39) -> 0 | AD40: =SUBTOTAL(9,AD35:AD39) -> 560000 | AE40: =SUBTOTAL(9,AE35:AE39) -> 14868 | AF40: =SUBTOTAL(9,AF35:AF39) -> 750 | AG40: =SUBTOTAL(9,AG35:AG39) -> 0 | AH40: =SUBTOTAL(9,AH35:AH39) -> 10000 | AI40: =SUBTOTAL(9,AI35:AI39) -> 534382 | AN40: =SUBTOTAL(9,AN35:AN39) -> 534382 | AO40: =SUBTOTAL(9,AO35:AO39) -> 0 | AP40: =SUBTOTAL(9,AP35:AP39) -> 0 | AQ40: =SUBTOTAL(9,AQ35:AQ39) -> 0 | AR40: =SUBTOTAL(9,AR35:AR39) -> 0 | AS40: =SUBTOTAL(9,AS35:AS39) -> 534382 | AT40: =SUBTOTAL(9,AT35:AT39) -> 0 | AU40: =SUBTOTAL(9,AU35:AU39) -> 534382 | AY40: =SUBTOTAL(9,AY35:AY39) -> 2028.9855
B42: =+B39+1 -> 26 | C42: 702 | D42: =_xlfn.XLOOKUP(C42,Master[Emp Code],Master[date of last increment]) -> 43861 | E42: =_xlfn.XLOOKUP(C42,Master[Emp Code],Master[[last incremnet ]]) -> 30000 | F42: =_xlfn.XLOOKUP(C42,Master[Emp Code],Master['# Months Since Last Increment]) -> 3 | G42: =VLOOKUP($C42,Master!$F:$AU,G$4,FALSE) -> 43684 | H42: =VLOOKUP($C42,Master!$F:$AU,H$4,FALSE) -> CT | I42: =VLOOKUP($C42,Master!$F:$AU,I$4,FALSE) -> Fahad Naveed | J42: =VLOOKUP($C42,Master!$F:$AU,J$4,FALSE) -> Sales | K42: =VLOOKUP($C42,Master!$F:$AU,K$4,FALSE) -> International Sales Executive | L42: =VLOOKUP($C42,Master!$F:$AU,L$4,FALSE) -> Umer Shahjahan | M42: =VLOOKUP($C42,Master!$F:$AU,M$4,FALSE) -> HW | N42: =VLOOKUP($C42,Master!$F:$AU,N$4,FALSE) -> BNS | ... AK42: =VLOOKUP($C42,Master!$F:$AU,AK$4,FALSE) -> 12427949370603 | AL42: 4210128184849 | AM42: =VLOOKUP($C42,Master!$F:$AU,AM$4,FALSE) -> Fahad naveed | AN42: =VLOOKUP($C42,Master!$F:$AU,AN$4,FALSE) -> 128209.75 | AO42: =VLOOKUP($C42,Master!$F:$AU,AO$4,FALSE) -> 0 | AP42: =VLOOKUP($C42,Master!$F:$AU,AP$4,FALSE) -> 0 | AQ42: =VLOOKUP($C42,Master!$F:$AU,AQ$4,FALSE) -> 0 | AR42: =VLOOKUP($C42,Master!$F:$AU,AR$4,FALSE) -> 0 | AS42: =VLOOKUP($C42,Master!$F:$AU,AS$4,FALSE) -> 128209.75 | AT42: =VLOOKUP($C42,Master!$F:$AU,AT$4,FALSE) -> 0 | AU42: =VLOOKUP($C42,Master!$F:$AU,AU$4,FALSE) -> 128209.75 | AX42: =+Master!$K$1 -> 276 | AY42: =+AD42/AX42 -> 471.01449
B43: 27 | C43: 701 | D43: =_xlfn.XLOOKUP(C43,Master[Emp Code],Master[date of last increment]) -> 0 | E43: =_xlfn.XLOOKUP(C43,Master[Emp Code],Master[[last incremnet ]]) -> 0 | F43: =_xlfn.XLOOKUP(C43,Master[Emp Code],Master['# Months Since Last Increment]) -> 0 | G43: =VLOOKUP($C43,Master!$F:$AU,G$4,FALSE) -> 43684 | H43: =VLOOKUP($C43,Master!$F:$AU,H$4,FALSE) -> CT | I43: =VLOOKUP($C43,Master!$F:$AU,I$4,FALSE) -> Usman Amin | J43: =VLOOKUP($C43,Master!$F:$AU,J$4,FALSE) -> Sales | K43: =VLOOKUP($C43,Master!$F:$AU,K$4,FALSE) -> International Sales Executive | L43: =VLOOKUP($C43,Master!$F:$AU,L$4,FALSE) -> Umer Shahjahan | M43: =VLOOKUP($C43,Master!$F:$AU,M$4,FALSE) -> HW | N43: =VLOOKUP($C43,Master!$F:$AU,N$4,FALSE) -> BNS | ... AK43: =VLOOKUP($C43,Master!$F:$AU,AK$4,FALSE) -> 0445-79012790-99 | AL43: 4210128184849 | AM43: =VLOOKUP($C43,Master!$F:$AU,AM$4,FALSE) -> Muhammad ADA | AN43: =VLOOKUP($C43,Master!$F:$AU,AN$4,FALSE) -> 0 | AO43: =VLOOKUP($C43,Master!$F:$AU,AO$4,FALSE) -> 0 | AP43: =VLOOKUP($C43,Master!$F:$AU,AP$4,FALSE) -> 0 | AQ43: =VLOOKUP($C43,Master!$F:$AU,AQ$4,FALSE) -> 0 | AR43: =VLOOKUP($C43,Master!$F:$AU,AR$4,FALSE) -> 0 | AS43: =VLOOKUP($C43,Master!$F:$AU,AS$4,FALSE) -> 0 | AT43: =VLOOKUP($C43,Master!$F:$AU,AT$4,FALSE) -> 0 | AU43: =VLOOKUP($C43,Master!$F:$AU,AU$4,FALSE) -> 0 | AX43: =+Master!$K$1 -> 276 | AY43: =+AD43/AX43 -> 0
P44: =SUBTOTAL(9,P42:P43) -> 130000 | Q44: =SUBTOTAL(9,Q40:Q43) -> 81250 | R44: =SUBTOTAL(9,R40:R43) -> 32500 | S44: =SUBTOTAL(9,S40:S43) -> 8125 | T44: =SUBTOTAL(9,T40:T43) -> 8125 | U44: =SUBTOTAL(9,U42:U43) -> 130000 | V44: =SUBTOTAL(9,V42:V43) -> 0 | X44: =SUBTOTAL(9,X40:X43) -> 0 | Z44: =SUBTOTAL(9,Z42:Z43) -> 0 | AC44: =SUBTOTAL(9,AC42:AC43) -> 0 | AD44: =SUBTOTAL(9,AD42:AD43) -> 130000 | AE44: =SUBTOTAL(9,AE42:AE43) -> 1790.25 | AF44: =SUBTOTAL(9,AF42:AF43) -> 0 | AG44: =SUBTOTAL(9,AG42:AG43) -> 0 | AH44: =SUBTOTAL(9,AH42:AH43) -> 0 | AI44: =SUBTOTAL(9,AI42:AI43) -> 128209.75 | AJ44: =SUBTOTAL(9,AJ42:AJ43) -> 0 | ... AU44: =SUBTOTAL(9,AU42:AU43) -> 128209.75 | AY44: =SUBTOTAL(9,AY42:AY43) -> 471.01449
B46: 28 | C46: 162 | D46: =_xlfn.XLOOKUP(C46,Master[Emp Code],Master[date of last increment]) -> 43861 | E46: =_xlfn.XLOOKUP(C46,Master[Emp Code],Master[[last incremnet ]]) -> 5000 | F46: =_xlfn.XLOOKUP(C46,Master[Emp Code],Master['# Months Since Last Increment]) -> 3 | G46: =VLOOKUP($C46,Master!$F:$AU,G$4,FALSE) -> 43236 | H46: =VLOOKUP($C46,Master!$F:$AU,H$4,FALSE) -> CT | I46: =VLOOKUP($C46,Master!$F:$AU,I$4,FALSE) -> Faraz Hussain | J46: =VLOOKUP($C46,Master!$F:$AU,J$4,FALSE) -> Procurement | K46: =VLOOKUP($C46,Master!$F:$AU,K$4,FALSE) -> Manager Procurement | L46: =VLOOKUP($C46,Master!$F:$AU,L$4,FALSE) -> Wasif Azhar | M46: =VLOOKUP($C46,Master!$F:$AU,M$4,FALSE) -> HW | N46: =VLOOKUP($C46,Master!$F:$AU,N$4,FALSE) -> GIT | ... AK46: =VLOOKUP($C46,Master!$F:$AU,AK$4,FALSE) -> 0583-79011770-03 | AL46: 4210128184849 | AM46: =VLOOKUP($C46,Master!$F:$AU,AM$4,FALSE) -> Faraz Hussain | AN46: =VLOOKUP($C46,Master!$F:$AU,AN$4,FALSE) -> 108865.75 | AO46: =VLOOKUP($C46,Master!$F:$AU,AO$4,FALSE) -> 0 | AP46: =VLOOKUP($C46,Master!$F:$AU,AP$4,FALSE) -> 0 | AQ46: =VLOOKUP($C46,Master!$F:$AU,AQ$4,FALSE) -> 0 | AR46: =VLOOKUP($C46,Master!$F:$AU,AR$4,FALSE) -> 0 | AS46: =VLOOKUP($C46,Master!$F:$AU,AS$4,FALSE) -> 108865.75 | AT46: =VLOOKUP($C46,Master!$F:$AU,AT$4,FALSE) -> 0 | AU46: =VLOOKUP($C46,Master!$F:$AU,AU$4,FALSE) -> 108865.75 | AX46: =+Master!$K$1 -> 276 | AY46: =+AD46/AX46 -> 398.55072
B47: =+B46+1 -> 29 | C47: 47 | D47: =_xlfn.XLOOKUP(C47,Master[Emp Code],Master[date of last increment]) -> 43465 | E47: =_xlfn.XLOOKUP(C47,Master[Emp Code],Master[[last incremnet ]]) -> 50000 | F47: =_xlfn.XLOOKUP(C47,Master[Emp Code],Master['# Months Since Last Increment]) -> 16 | G47: =VLOOKUP($C47,Master!$F:$AU,G$4,FALSE) -> 43039 | H47: =VLOOKUP($C47,Master!$F:$AU,H$4,FALSE) -> CT | I47: =VLOOKUP($C47,Master!$F:$AU,I$4,FALSE) -> Wasif Azhar | J47: =VLOOKUP($C47,Master!$F:$AU,J$4,FALSE) -> Sales | K47: =VLOOKUP($C47,Master!$F:$AU,K$4,FALSE) -> International Sales Executive | L47: =VLOOKUP($C47,Master!$F:$AU,L$4,FALSE) -> Umer Shahjahan | M47: =VLOOKUP($C47,Master!$F:$AU,M$4,FALSE) -> HW | N47: =VLOOKUP($C47,Master!$F:$AU,N$4,FALSE) -> GIT | ... AK47: =VLOOKUP($C47,Master!$F:$AU,AK$4,FALSE) -> 0830-79009967-03 | AL47: 4210128184849 | AM47: =VLOOKUP($C47,Master!$F:$AU,AM$4,FALSE) -> Wasif Azhar | AN47: =VLOOKUP($C47,Master!$F:$AU,AN$4,FALSE) -> 190088.4 | AO47: =VLOOKUP($C47,Master!$F:$AU,AO$4,FALSE) -> 0 | AP47: =VLOOKUP($C47,Master!$F:$AU,AP$4,FALSE) -> 0 | AQ47: =VLOOKUP($C47,Master!$F:$AU,AQ$4,FALSE) -> 0 | AR47: =VLOOKUP($C47,Master!$F:$AU,AR$4,FALSE) -> 0 | AS47: =VLOOKUP($C47,Master!$F:$AU,AS$4,FALSE) -> 190088.4 | AT47: =VLOOKUP($C47,Master!$F:$AU,AT$4,FALSE) -> 0 | AU47: =VLOOKUP($C47,Master!$F:$AU,AU$4,FALSE) -> 190088.4 | AX47: =+Master!$K$1 -> 276 | AY47: =+AD47/AX47 -> 724.63768
B48: =+B47+1 -> 30 | C48: 150 | D48: =_xlfn.XLOOKUP(C48,Master[Emp Code],Master[date of last increment]) -> 43830 | E48: =_xlfn.XLOOKUP(C48,Master[Emp Code],Master[[last incremnet ]]) -> 15000 | F48: =_xlfn.XLOOKUP(C48,Master[Emp Code],Master['# Months Since Last Increment]) -> 4 | G48: =VLOOKUP($C48,Master!$F:$AU,G$4,FALSE) -> 43186 | H48: =VLOOKUP($C48,Master!$F:$AU,H$4,FALSE) -> CT | I48: =VLOOKUP($C48,Master!$F:$AU,I$4,FALSE) -> Humayoun Khan | J48: =VLOOKUP($C48,Master!$F:$AU,J$4,FALSE) -> Procurement | K48: =VLOOKUP($C48,Master!$F:$AU,K$4,FALSE) -> Procurement Executive | L48: =VLOOKUP($C48,Master!$F:$AU,L$4,FALSE) -> Nadeem Akhtar | M48: =VLOOKUP($C48,Master!$F:$AU,M$4,FALSE) -> HW | N48: =VLOOKUP($C48,Master!$F:$AU,N$4,FALSE) -> GIT | ... AK48: =VLOOKUP($C48,Master!$F:$AU,AK$4,FALSE) -> 0017-79008735-03 | AL48: 4210128184849 | AM48: =VLOOKUP($C48,Master!$F:$AU,AM$4,FALSE) -> HUMAYOUN KHAN | AN48: =VLOOKUP($C48,Master!$F:$AU,AN$4,FALSE) -> 50000 | AO48: =VLOOKUP($C48,Master!$F:$AU,AO$4,FALSE) -> 0 | AP48: =VLOOKUP($C48,Master!$F:$AU,AP$4,FALSE) -> 0 | AQ48: =VLOOKUP($C48,Master!$F:$AU,AQ$4,FALSE) -> 0 | AR48: =VLOOKUP($C48,Master!$F:$AU,AR$4,FALSE) -> 0 | AS48: =VLOOKUP($C48,Master!$F:$AU,AS$4,FALSE) -> 50000 | AT48: =VLOOKUP($C48,Master!$F:$AU,AT$4,FALSE) -> 0 | AU48: =VLOOKUP($C48,Master!$F:$AU,AU$4,FALSE) -> 50000 | AX48: =+Master!$K$1 -> 276 | AY48: =+AD48/AX48 -> 181.15942
B49: =+B48+1 -> 31 | C49: 187 | D49: =_xlfn.XLOOKUP(C49,Master[Emp Code],Master[date of last increment]) -> 43830 | E49: =_xlfn.XLOOKUP(C49,Master[Emp Code],Master[[last incremnet ]]) -> 9000 | F49: =_xlfn.XLOOKUP(C49,Master[Emp Code],Master['# Months Since Last Increment]) -> 4 | G49: =VLOOKUP($C49,Master!$F:$AU,G$4,FALSE) -> 43692 | H49: =VLOOKUP($C49,Master!$F:$AU,H$4,FALSE) -> CT | I49: =VLOOKUP($C49,Master!$F:$AU,I$4,FALSE) -> Nahyan Hussain | J49: =VLOOKUP($C49,Master!$F:$AU,J$4,FALSE) -> Sales | K49: =VLOOKUP($C49,Master!$F:$AU,K$4,FALSE) -> International Sales Executive | L49: =VLOOKUP($C49,Master!$F:$AU,L$4,FALSE) -> Wasif Azhar | M49: =VLOOKUP($C49,Master!$F:$AU,M$4,FALSE) -> HW | N49: =VLOOKUP($C49,Master!$F:$AU,N$4,FALSE) -> GIT | ... AK49: =VLOOKUP($C49,Master!$F:$AU,AK$4,FALSE) -> 99530105424627 | AL49: 4210128184849 | AM49: =VLOOKUP($C49,Master!$F:$AU,AM$4,FALSE) -> Asad Hussain | AN49: =VLOOKUP($C49,Master!$F:$AU,AN$4,FALSE) -> 0 | AO49: =VLOOKUP($C49,Master!$F:$AU,AO$4,FALSE) -> 0 | AP49: =VLOOKUP($C49,Master!$F:$AU,AP$4,FALSE) -> 0 | AQ49: =VLOOKUP($C49,Master!$F:$AU,AQ$4,FALSE) -> 42857.143 | AR49: =VLOOKUP($C49,Master!$F:$AU,AR$4,FALSE) -> 0 | AS49: =VLOOKUP($C49,Master!$F:$AU,AS$4,FALSE) -> 42857.143 | AT49: =VLOOKUP($C49,Master!$F:$AU,AT$4,FALSE) -> 0 | AU49: =VLOOKUP($C49,Master!$F:$AU,AU$4,FALSE) -> 42857.143 | AX49: =+Master!$K$1 -> 276 | AY49: =+AD49/AX49 -> 155.2795
B50: =+B49+1 -> 32 | C50: 226 | D50: =_xlfn.XLOOKUP(C50,Master[Emp Code],Master[date of last increment]) -> 0 | E50: =_xlfn.XLOOKUP(C50,Master[Emp Code],Master[[last incremnet ]]) -> 0 | F50: =_xlfn.XLOOKUP(C50,Master[Emp Code],Master['# Months Since Last Increment]) -> 0 | G50: =VLOOKUP($C50,Master!$F:$AU,G$4,FALSE) -> 43862 | H50: =VLOOKUP($C50,Master!$F:$AU,H$4,FALSE) -> 0 | I50: =VLOOKUP($C50,Master!$F:$AU,I$4,FALSE) -> Syed Shabi ul Hasan Zaidi | J50: =VLOOKUP($C50,Master!$F:$AU,J$4,FALSE) -> Sales | K50: =VLOOKUP($C50,Master!$F:$AU,K$4,FALSE) -> International Sales Executive | L50: =VLOOKUP($C50,Master!$F:$AU,L$4,FALSE) -> Wasif Azhar | M50: =VLOOKUP($C50,Master!$F:$AU,M$4,FALSE) -> HW | N50: =VLOOKUP($C50,Master!$F:$AU,N$4,FALSE) -> GIT | ... AK50: =VLOOKUP($C50,Master!$F:$AU,AK$4,FALSE) -> 10680048013966014 | AL50: 4210128184849 | AM50: =VLOOKUP($C50,Master!$F:$AU,AM$4,FALSE) -> Syed Shabi Ul Hasan Zaidi | AN50: =VLOOKUP($C50,Master!$F:$AU,AN$4,FALSE) -> 0 | AO50: =VLOOKUP($C50,Master!$F:$AU,AO$4,FALSE) -> 0 | AP50: =VLOOKUP($C50,Master!$F:$AU,AP$4,FALSE) -> 0 | AQ50: =VLOOKUP($C50,Master!$F:$AU,AQ$4,FALSE) -> 38095.238 | AR50: =VLOOKUP($C50,Master!$F:$AU,AR$4,FALSE) -> 0 | AS50: =VLOOKUP($C50,Master!$F:$AU,AS$4,FALSE) -> 38095.238 | AT50: =VLOOKUP($C50,Master!$F:$AU,AT$4,FALSE) -> 0 | AU50: =VLOOKUP($C50,Master!$F:$AU,AU$4,FALSE) -> 38095.238 | AX50: =+Master!$K$1 -> 276 | AY50: =+AD50/AX50 -> 138.02622
B51: =+B50+1 -> 33 | C51: 155 | D51: =_xlfn.XLOOKUP(C51,Master[Emp Code],Master[date of last increment]) -> 43708 | E51: =_xlfn.XLOOKUP(C51,Master[Emp Code],Master[[last incremnet ]]) -> 10000 | F51: =_xlfn.XLOOKUP(C51,Master[Emp Code],Master['# Months Since Last Increment]) -> 8 | G51: =VLOOKUP($C51,Master!$F:$AU,G$4,FALSE) -> 43207 | H51: =VLOOKUP($C51,Master!$F:$AU,H$4,FALSE) -> CT | I51: =VLOOKUP($C51,Master!$F:$AU,I$4,FALSE) -> Syed Sumair Hussain | J51: =VLOOKUP($C51,Master!$F:$AU,J$4,FALSE) -> Sales | K51: =VLOOKUP($C51,Master!$F:$AU,K$4,FALSE) -> International Sales Executive | L51: =VLOOKUP($C51,Master!$F:$AU,L$4,FALSE) -> Wasif Azhar | M51: =VLOOKUP($C51,Master!$F:$AU,M$4,FALSE) -> HW | N51: =VLOOKUP($C51,Master!$F:$AU,N$4,FALSE) -> GIT | ... AK51: =VLOOKUP($C51,Master!$F:$AU,AK$4,FALSE) -> 0017-79008896-03 | AL51: 4210128184849 | AM51: =VLOOKUP($C51,Master!$F:$AU,AM$4,FALSE) -> Syed Sumair | AN51: =VLOOKUP($C51,Master!$F:$AU,AN$4,FALSE) -> 50000 | AO51: =VLOOKUP($C51,Master!$F:$AU,AO$4,FALSE) -> 0 | AP51: =VLOOKUP($C51,Master!$F:$AU,AP$4,FALSE) -> 0 | AQ51: =VLOOKUP($C51,Master!$F:$AU,AQ$4,FALSE) -> 0 | AR51: =VLOOKUP($C51,Master!$F:$AU,AR$4,FALSE) -> 0 | AS51: =VLOOKUP($C51,Master!$F:$AU,AS$4,FALSE) -> 50000 | AT51: =VLOOKUP($C51,Master!$F:$AU,AT$4,FALSE) -> 0 | AU51: =VLOOKUP($C51,Master!$F:$AU,AU$4,FALSE) -> 50000 | AX51: =+Master!$K$1 -> 276 | AY51: =+AD51/AX51 -> 181.15942
P52: =SUBTOTAL(9,P46:P51) -> 495000 | Q52: =SUBTOTAL(9,Q46:Q51) -> 309375 | R52: =SUBTOTAL(9,R46:R51) -> 123750 | S52: =SUBTOTAL(9,S46:S51) -> 30937.5 | T52: =SUBTOTAL(9,T46:T51) -> 30937.5 | U52: =SUBTOTAL(9,U46:U51) -> 495000 | V52: =SUBTOTAL(9,V46:V51) -> 0 | X52: =SUBTOTAL(9,X46:X51) -> 0 | Z52: =SUBTOTAL(9,Z46:Z51) -> 4047.619 | AC52: =SUBTOTAL(9,AC46:AC51) -> 0 | AD52: =SUBTOTAL(9,AD46:AD51) -> 490952.38 | AE52: =SUBTOTAL(9,AE46:AE51) -> 10795.85 | AF52: =SUBTOTAL(9,AF46:AF51) -> 250 | AG52: =SUBTOTAL(9,AG46:AG51) -> 0 | AH52: =SUBTOTAL(9,AH46:AH51) -> 0 | AI52: =SUBTOTAL(9,AI46:AI51) -> 479906.53 | AJ52: =SUBTOTAL(9,AJ46:AJ51) -> 0 | ... AU52: =SUBTOTAL(9,AU46:AU51) -> 479906.53 | AY52: =SUBTOTAL(9,AY46:AY51) -> 1778.813
P54: =SUBTOTAL(9,P6:P53) -> 2280000 | Q54: =SUBTOTAL(9,Q6:Q53) -> 1425000 | R54: =SUBTOTAL(9,R6:R53) -> 570000 | S54: =SUBTOTAL(9,S6:S53) -> 142500 | T54: =SUBTOTAL(9,T6:T53) -> 302500 | U54: =SUBTOTAL(9,U6:U53) -> 2440000 | V54: =SUBTOTAL(9,V6:V53) -> 0 | W54: =SUBTOTAL(9,W6:W53) -> 0 | X54: =SUBTOTAL(9,X6:X53) -> 0 | Z54: =SUBTOTAL(9,Z6:Z53) -> 104087.09 | AC54: =SUBTOTAL(9,AC6:AC53) -> 2192.9825 | AD54: =SUBTOTAL(9,AD6:AD53) -> 2333719.9 | AE54: =SUBTOTAL(9,AE6:AE53) -> 40585.4 | AF54: =SUBTOTAL(9,AF6:AF53) -> 1750 | AG54: =SUBTOTAL(9,AG6:AG53) -> 160000 | AH54: =SUBTOTAL(9,AH6:AH53) -> 15000 | AI54: =SUBTOTAL(9,AI6:AI53) -> 2116384.5 | AN54: =SUBTOTAL(9,AN6:AN53) -> 1902664.6 | AO54: =SUBTOTAL(9,AO6:AO53) -> 0 | AP54: =SUBTOTAL(9,AP6:AP53) -> 0 | AQ54: =SUBTOTAL(9,AQ6:AQ53) -> 146202.38 | AR54: =SUBTOTAL(9,AR6:AR53) -> 42078.947 | AS54: =SUBTOTAL(9,AS6:AS53) -> 2090945.9 | AT54: =SUBTOTAL(9,AT6:AT53) -> 25438.596 | AU54: =SUBTOTAL(9,AU6:AU53) -> 2116384.5 | AX54: =+Master!$K$1 -> 276 | AY54: =+AD54/AX54 -> 8455.507
AU55: =+AI54-AU54 -> 0

Sheet Payroll Support Apr24
A1: BSD Technologies (Support Division) | N1: HIDE | P1: HIDE | Q1: HIDE | R1: HIDE | S1: HIDE | Z1: HIDE | AA1: HIDE | AB1: HIDE
A2: Payroll | C2: April | G2: 2024
G4: 2 | H4: 3 | I4: 4 | J4: 5 | K4: 6 | L4: 7 | M4: 8 | N4: 9 | O4: 10 | P4: 11 | Q4: 12 | R4: 13 | S4: 14 | T4: 15 | U4: 16 | V4: 17 | W4: 18 | X4: 19 | Y4: 20 | Z4: 21 | AA4: 22 | AB4: 23 | AC4: 24 | AD4: 25 | AE4: 26 | AF4: 27 | AG4: 28 | AH4: 29 | AI4: 30 | AJ4: 31 | AK4: 32 | AL4: 33 | AM4: 34 | AN4: 35 | AO4: 36 | AP4: 37 | AQ4: 38 | AR4: 39 | AS4: 40 | AT4: 41 | AU4: 42
B5: Sr.No | C5: Emp Code | D5: Incr. Date | E5: Incr. Amount | F5: Incr. Months | G5: DOJ (DD/MM/Y) | H5: CURRENT STATUS | I5: Employee Name (CNIC) | J5: Department | K5: Designation | L5: Reporting Manager | M5: MCS | N5: BRAND | O5: Status | P5: Gross Salary | Q5: Basic Salary | R5: H.Rent All | S5: Ut. All | T5: Conv. All | U5: Gross salary | V5: Bonus/Incentive/Reimbursemet | W5: No.Extra Days | X5: Amount Ex. Days | Y5: DISAPPROVED Absent Days | Z5: Deduction absent Days | AA5: Hourly Rate | AB5: No. of Ded Hours | AC5: Ded Amt Hrs | AD5: Net Gross | AE5: Tax | AF5: EOBI | AG5: Advance | AH5: Loan | AI5: Net Pay | AJ5: Bank Name | AK5: AC Number | AL5: CNIC | AM5: Account Title | AN5: HBL | AO5: Samba | AP5: Cheque | AQ5: IBFT | AR5: Cash | AS5: Payments | AT5: Hold | AU5: Total | AX5: FOREX | AY5: Net Gross (USD)
B6: 1 | C6: 53 | D6: =_xlfn.XLOOKUP(C6,Master[Emp Code],Master[date of last increment]) -> 43890 | E6: =_xlfn.XLOOKUP(C6,Master[Emp Code],Master[[last incremnet ]]) -> 15000 | F6: =_xlfn.XLOOKUP(C6,Master[Emp Code],Master['# Months Since Last Increment]) -> 2 | G6: =VLOOKUP($C6,Master!$F:$AU,G$4,FALSE) -> 42752 | H6: =VLOOKUP($C6,Master!$F:$AU,H$4,FALSE) -> CT | I6: =VLOOKUP($C6,Master!$F:$AU,I$4,FALSE) -> Muhammad Mubashir | J6: =VLOOKUP($C6,Master!$F:$AU,J$4,FALSE) -> Accounts | K6: =VLOOKUP($C6,Master!$F:$AU,K$4,FALSE) -> Assiatant Manager Accounts | L6: =VLOOKUP($C6,Master!$F:$AU,L$4,FALSE) -> Farooq Khan | M6: =VLOOKUP($C6,Master!$F:$AU,M$4,FALSE) -> ALL | N6: =VLOOKUP($C6,Master!$F:$AU,N$4,FALSE) -> ALL | ... AU6: =VLOOKUP($C6,Master!$F:$AU,AU$4,FALSE) -> 143429 | AX6: =+Master!$K$1 -> 276 | AY6: =+AD6/AX6 -> 525.36232
B7: 2 | C7: 78 | D7: =_xlfn.XLOOKUP(C7,Master[Emp Code],Master[date of last increment]) -> 43677 | E7: =_xlfn.XLOOKUP(C7,Master[Emp Code],Master[[last incremnet ]]) -> 17000 | F7: =_xlfn.XLOOKUP(C7,Master[Emp Code],Master['# Months Since Last Increment]) -> 9 | G7: =VLOOKUP($C7,Master!$F:$AU,G$4,FALSE) -> 42927 | H7: =VLOOKUP($C7,Master!$F:$AU,H$4,FALSE) -> CT | I7: =VLOOKUP($C7,Master!$F:$AU,I$4,FALSE) -> Muhammad Farooq Khan | J7: =VLOOKUP($C7,Master!$F:$AU,J$4,FALSE) -> Accounts | K7: =VLOOKUP($C7,Master!$F:$AU,K$4,FALSE) -> Manager Accounts | L7: =VLOOKUP($C7,Master!$F:$AU,L$4,FALSE) -> Wahaj Qureshi | M7: =VLOOKUP($C7,Master!$F:$AU,M$4,FALSE) -> ALL | N7: =VLOOKUP($C7,Master!$F:$AU,N$4,FALSE) -> ALL | ... AU7: =VLOOKUP($C7,Master!$F:$AU,AU$4,FALSE) -> 183265 | AX7: =+Master!$K$1 -> 276 | AY7: =+AD7/AX7 -> 677.53623 | BA7: =125000/162 -> 771.60494
B8: 3 | C8: 168 | D8: =_xlfn.XLOOKUP(C8,Master[Emp Code],Master[date of last increment]) -> 43738 | E8: =_xlfn.XLOOKUP(C8,Master[Emp Code],Master[[last incremnet ]]) -> 5000 | F8: =_xlfn.XLOOKUP(C8,Master[Emp Code],Master['# Months Since Last Increment]) -> 7 | G8: =VLOOKUP($C8,Master!$F:$AU,G$4,FALSE) -> 01 Nov 2020 / 12 Sep 2022 | H8: =VLOOKUP($C8,Master!$F:$AU,H$4,FALSE) -> CT | I8: =VLOOKUP($C8,Master!$F:$AU,I$4,FALSE) -> Ammanullah | J8: =VLOOKUP($C8,Master!$F:$AU,J$4,FALSE) -> Administration | K8: =VLOOKUP($C8,Master!$F:$AU,K$4,FALSE) -> Office Boy | L8: =VLOOKUP($C8,Master!$F:$AU,L$4,FALSE) -> Mubashir | M8: =VLOOKUP($C8,Master!$F:$AU,M$4,FALSE) -> ALL | N8: =VLOOKUP($C8,Master!$F:$AU,N$4,FALSE) -> ALL | ... AU8: =VLOOKUP($C8,Master!$F:$AU,AU$4,FALSE) -> 21000 | AX8: =+Master!$K$1 -> 276 | AY8: =+AD8/AX8 -> 108.69565
B9: 4 | C9: 999 | D9: =_xlfn.XLOOKUP(C9,Master[Emp Code],Master[date of last increment]) -> 0 | E9: =_xlfn.XLOOKUP(C9,Master[Emp Code],Master[[last incremnet ]]) -> 0 | F9: =_xlfn.XLOOKUP(C9,Master[Emp Code],Master['# Months Since Last Increment]) -> 0 | G9: =VLOOKUP($C9,Master!$F:$AU,G$4,FALSE) -> 43496 | H9: =VLOOKUP($C9,Master!$F:$AU,H$4,FALSE) -> CT | I9: =VLOOKUP($C9,Master!$F:$AU,I$4,FALSE) -> Muhammad Farooq | J9: =VLOOKUP($C9,Master!$F:$AU,J$4,FALSE) -> Administration | K9: =VLOOKUP($C9,Master!$F:$AU,K$4,FALSE) -> Electrician | L9: =VLOOKUP($C9,Master!$F:$AU,L$4,FALSE) -> Mubashir | M9: =VLOOKUP($C9,Master!$F:$AU,M$4,FALSE) -> ALL | N9: =VLOOKUP($C9,Master!$F:$AU,N$4,FALSE) -> ALL | ... AU9: =VLOOKUP($C9,Master!$F:$AU,AU$4,FALSE) -> 15000 | AX9: =+Master!$K$1 -> 276 | AY9: =+AD9/AX9 -> 54.347826
B10: 5 | C10: 144 | D10: =_xlfn.XLOOKUP(C10,Master[Emp Code],Master[date of last increment]) -> 43738 | E10: =_xlfn.XLOOKUP(C10,Master[Emp Code],Master[[last incremnet ]]) -> 5000 | F10: =_xlfn.XLOOKUP(C10,Master[Emp Code],Master['# Months Since Last Increment]) -> 7 | G10: =VLOOKUP($C10,Master!$F:$AU,G$4,FALSE) -> Apr 2023 | H10: =VLOOKUP($C10,Master!$F:$AU,H$4,FALSE) -> CT | I10: =VLOOKUP($C10,Master!$F:$AU,I$4,FALSE) -> Salman | J10: =VLOOKUP($C10,Master!$F:$AU,J$4,FALSE) -> Administration | K10: =VLOOKUP($C10,Master!$F:$AU,K$4,FALSE) -> Office Boy | L10: =VLOOKUP($C10,Master!$F:$AU,L$4,FALSE) -> Mubashir | M10: =VLOOKUP($C10,Master!$F:$AU,M$4,FALSE) -> ALL | N10: =VLOOKUP($C10,Master!$F:$AU,N$4,FALSE) -> ALL | ... AU10: =VLOOKUP($C10,Master!$F:$AU,AU$4,FALSE) -> 22000 | AX10: =+Master!$K$1 -> 276 | AY10: =+AD10/AX10 -> 90.57971
B11: 6 | C11: 176 | D11: =_xlfn.XLOOKUP(C11,Master[Emp Code],Master[date of last increment]) -> 43738 | E11: =_xlfn.XLOOKUP(C11,Master[Emp Code],Master[[last incremnet ]]) -> 5000 | F11: =_xlfn.XLOOKUP(C11,Master[Emp Code],Master['# Months Since Last Increment]) -> 7 | G11: =VLOOKUP($C11,Master!$F:$AU,G$4,FALSE) -> 43298 | H11: =VLOOKUP($C11,Master!$F:$AU,H$4,FALSE) -> CT | I11: =VLOOKUP($C11,Master!$F:$AU,I$4,FALSE) -> Muhammad Irfan | J11: =VLOOKUP($C11,Master!$F:$AU,J$4,FALSE) -> Administration | K11: =VLOOKUP($C11,Master!$F:$AU,K$4,FALSE) -> Office Boy | L11: =VLOOKUP($C11,Master!$F:$AU,L$4,FALSE) -> Mubashir | M11: =VLOOKUP($C11,Master!$F:$AU,M$4,FALSE) -> ALL | N11: =VLOOKUP($C11,Master!$F:$AU,N$4,FALSE) -> ALL | ... AU11: =VLOOKUP($C11,Master!$F:$AU,AU$4,FALSE) -> 30000 | AX11: =+Master!$K$1 -> 276 | AY11: =+AD11/AX11 -> 108.69565
B12: 7 | C12: 135 | D12: =_xlfn.XLOOKUP(C12,Master[Emp Code],Master[date of last increment]) -> 43861 | E12: =_xlfn.XLOOKUP(C12,Master[Emp Code],Master[[last incremnet ]]) -> 15000 | F12: =_xlfn.XLOOKUP(C12,Master[Emp Code],Master['# Months Since Last Increment]) -> 3 | G12: =VLOOKUP($C12,Master!$F:$AU,G$4,FALSE) -> 43524 | H12: =VLOOKUP($C12,Master!$F:$AU,H$4,FALSE) -> CT | I12: =VLOOKUP($C12,Master!$F:$AU,I$4,FALSE) -> Farhad Muhammad Khan | J12: =VLOOKUP($C12,Master!$F:$AU,J$4,FALSE) -> IT | K12: =VLOOKUP($C12,Master!$F:$AU,K$4,FALSE) -> Support Engineer | L12: =VLOOKUP($C12,Master!$F:$AU,L$4,FALSE) -> Wahaj Qureshi | M12: =VLOOKUP($C12,Master!$F:$AU,M$4,FALSE) -> ALL | N12: =VLOOKUP($C12,Master!$F:$AU,N$4,FALSE) -> ALL | ... AU12: =VLOOKUP($C12,Master!$F:$AU,AU$4,FALSE) -> 79532.2 | AX12: =+Master!$K$1 -> 276 | AY12: =+AD12/AX12 -> 289.85507
B13: 8 | C13: 204 | D13: =_xlfn.XLOOKUP(C13,Master[Emp Code],Master[date of last increment]) -> 0 | E13: =_xlfn.XLOOKUP(C13,Master[Emp Code],Master[[last incremnet ]]) -> 0 | F13: =_xlfn.XLOOKUP(C13,Master[Emp Code],Master['# Months Since Last Increment]) -> 0 | G13: =VLOOKUP($C13,Master!$F:$AU,G$4,FALSE) -> 43769 | H13: =VLOOKUP($C13,Master!$F:$AU,H$4,FALSE) -> NJ | I13: =VLOOKUP($C13,Master!$F:$AU,I$4,FALSE) -> Abdul Hadi Ravasia | J13: =VLOOKUP($C13,Master!$F:$AU,J$4,FALSE) -> Accounts | K13: =VLOOKUP($C13,Master!$F:$AU,K$4,FALSE) -> Accounts Executive | L13: =VLOOKUP($C13,Master!$F:$AU,L$4,FALSE) -> Farooq Khan | M13: =VLOOKUP($C13,Master!$F:$AU,M$4,FALSE) -> ALL | N13: =VLOOKUP($C13,Master!$F:$AU,N$4,FALSE) -> ALL | ... AU13: =VLOOKUP($C13,Master!$F:$AU,AU$4,FALSE) -> 35000 | AX13: =+Master!$K$1 -> 276 | AY13: =+AD13/AX13 -> 163.04348
B14: 9 | C14: 223 | D14: =_xlfn.XLOOKUP(C14,Master[Emp Code],Master[date of last increment]) -> 0 | E14: =_xlfn.XLOOKUP(C14,Master[Emp Code],Master[[last incremnet ]]) -> 0 | F14: =_xlfn.XLOOKUP(C14,Master[Emp Code],Master['# Months Since Last Increment]) -> 0 | G14: =VLOOKUP($C14,Master!$F:$AU,G$4,FALSE) -> 43866 | H14: =VLOOKUP($C14,Master!$F:$AU,H$4,FALSE) -> 0 | I14: =VLOOKUP($C14,Master!$F:$AU,I$4,FALSE) -> Arsalan Ahmed | J14: =VLOOKUP($C14,Master!$F:$AU,J$4,FALSE) -> HR | K14: =VLOOKUP($C14,Master!$F:$AU,K$4,FALSE) -> 0 | L14: =VLOOKUP($C14,Master!$F:$AU,L$4,FALSE) -> Wahaj Qureshi | M14: =VLOOKUP($C14,Master!$F:$AU,M$4,FALSE) -> ALL | N14: =VLOOKUP($C14,Master!$F:$AU,N$4,FALSE) -> ALL | ... AU14: =VLOOKUP($C14,Master!$F:$AU,AU$4,FALSE) -> 42368.421 | AX14: =+Master!$K$1 -> 276 | AY14: =+AD14/AX14 -> 171.62471
B15: 10 | C15: 164 | D15: =_xlfn.XLOOKUP(C15,Master[Emp Code],Master[date of last increment]) -> 0 | E15: =_xlfn.XLOOKUP(C15,Master[Emp Code],Master[[last incremnet ]]) -> 0 | F15: =_xlfn.XLOOKUP(C15,Master[Emp Code],Master['# Months Since Last Increment]) -> 0 | G15: =VLOOKUP($C15,Master!$F:$AU,G$4,FALSE) -> 0 | H15: =VLOOKUP($C15,Master!$F:$AU,H$4,FALSE) -> 0 | I15: =VLOOKUP($C15,Master!$F:$AU,I$4,FALSE) -> Hareem Fatima | J15: =VLOOKUP($C15,Master!$F:$AU,J$4,FALSE) -> HR | K15: =VLOOKUP($C15,Master!$F:$AU,K$4,FALSE) -> 0 | L15: =VLOOKUP($C15,Master!$F:$AU,L$4,FALSE) -> Wahaj Qureshi | M15: =VLOOKUP($C15,Master!$F:$AU,M$4,FALSE) -> ALL | N15: =VLOOKUP($C15,Master!$F:$AU,N$4,FALSE) -> ALL | ... AU15: =VLOOKUP($C15,Master!$F:$AU,AU$4,FALSE) -> 7644.7368 | AX15: =+Master!$K$1 -> 276 | AY15: =+AD15/AX15 -> 28.604119
P17: =SUM(P6:P16) -> 657000 | Q17: =SUM(Q6:Q16) -> 410625 | R17: =SUM(R6:R16) -> 164250 | S17: =SUM(S6:S16) -> 41062.5 | T17: =SUM(T6:T16) -> 41062.5 | U17: =SUM(U6:U16) -> 657000 | V17: =SUM(V6:V16) -> 0 | W17: =SUM(W6:W16) -> 0 | ... AI17: =SUM(AI6:AI16) -> 579238.96 | AN17: =SUM(AN6:AN16) -> 305338.74 | AO17: =SUM(AO6:AO16) -> 0 | AP17: =SUM(AP6:AP16) -> 0 | AQ17: =SUM(AQ6:AQ16) -> 221900.62 | AR17: =SUM(AR6:AR16) -> 52000 | AS17: =SUM(AS6:AS16) -> 579239.36 | AT17: =SUM(AT6:AT16) -> 0 | AU17: =SUM(AU6:AU16) -> 579239.36 | AY17: =SUM(AY6:AY16) -> 2218.3448

Sheet Summary Dept Wise
C1: Payroll April 2024 | H1: =Master!$K$1 -> 276 | Z1: 43960
B3: Department | D3: No. of Emp. | E3: MCS | F3: Brand | G3: Gross Salary Before Vehicle Allowance | H3: Gross Salary | I3: Bonus/ Incentive/Reimbursemet | J3: Amount Ex. Days | K3: Deduction Absent Days | L3: Ded Amt Hrs | M3: Net Gross | N3: Tax | O3: Eobi | P3: Advance / Car Rentals | Q3: Loan | R3: Net Pay | S3: HBL to HBL | T3: From Samba | U3: Cheque | V3: IBFT | W3: Cash | X3: To be Disbursed | Y3: Hold | Z3: Total | AA3: Already Paid | AB3: Balance | AC3: EOBI Contribution (Employer)
B5: SUPPORT
C6: Accounts | D6: =COUNTIFS(Master!$J$8:$J$55,'Summary Dept Wise'!$C6,Master!$M$8:$M$55,'Summary Dept Wise'!$E6,Master!$N$8:$N$55,'Summary Dept Wise'!$F6) -> 3 | E6: ALL | F6: ALL | G6: =SUMIFS(Master!$P$8:$P$55,Master!$J$8:$J$55,'Summary Dept Wise'!$C6,Master!$M$8:$M$55,'Summary Dept Wise'!$E6,Master!$N$8:$N$55,'Summary Dept Wise'!$F6) -> 377000 | H6: =SUMIFS(Master!$U$8:$U$55,Master!$J$8:$J$55,'Summary Dept Wise'!$C6,Master!$M$8:$M$55,'Summary Dept Wise'!$E6,Master!$N$8:$N$55,'Summary Dept Wise'!$F6) -> 377000 | I6: =SUMIFS(Master!$V$8:$V$55,Master!$J$8:$J$55,'Summary Dept Wise'!$C6,Master!$M$8:$M$55,'Summary Dept Wise'!$E6,Master!$N$8:$N$55,'Summary Dept Wise'!$F6) -> 0 | J6: =SUMIFS(Master!$X$8:$X$55,Master!$J$8:$J$55,'Summary Dept Wise'!$C6,Master!$M$8:$M$55,'Summary Dept Wise'!$E6,Master!$N$8:$N$55,'Summary Dept Wise'!$F6) -> 0 | K6: =SUMIFS(Master!$Z$8:$Z$55,Master!$J$8:$J$55,'Summary Dept Wise'!$C6,Master!$M$8:$M$55,'Summary Dept Wise'!$E6,Master!$N$8:$N$55,'Summary Dept Wise'!$F6) -> 0 | L6: =SUMIFS(Master!AC$8:AC$55,Master!$J$8:$J$55,'Summary Dept Wise'!$C6,Master!$M$8:$M$55,'Summary Dept Wise'!$E6,Master!$N$8:$N$55,'Summary Dept Wise'!$F6) -> 0 | M6: =SUMIFS(Master!AD$8:AD$55,Master!$J$8:$J$55,'Summary Dept Wise'!$C6,Master!$M$8:$M$55,'Summary Dept Wise'!$E6,Master!$N$8:$N$55,'Summary Dept Wise'!$F6) -> 377000 | N6: =SUMIFS(Master!AE$8:AE$55,Master!$J$8:$J$55,'Summary Dept Wise'!$C6,Master!$M$8:$M$55,'Summary Dept Wise'!$E6,Master!$N$8:$N$55,'Summary Dept Wise'!$F6) -> 4806.4 | O6: =SUMIFS(Master!AF$8:AF$55,Master!$J$8:$J$55,'Summary Dept Wise'!$C6,Master!$M$8:$M$55,'Summary Dept Wise'!$E6,Master!$N$8:$N$55,'Summary Dept Wise'!$F6) -> 500 | P6: =SUMIFS(Master!AG$8:AG$55,Master!$J$8:$J$55,'Summary Dept Wise'!$C6,Master!$M$8:$M$55,'Summary Dept Wise'!$E6,Master!$N$8:$N$55,'Summary Dept Wise'!$F6) -> 10000 | Q6: =SUMIFS(Master!AH$8:AH$55,Master!$J$8:$J$55,'Summary Dept Wise'!$C6,Master!$M$8:$M$55,'Summary Dept Wise'!$E6,Master!$N$8:$N$55,'Summary Dept Wise'!$F6) -> 0 | R6: =SUMIFS(Master!AI$8:AI$55,Master!$J$8:$J$55,'Summary Dept Wise'!$C6,Master!$M$8:$M$55,'Summary Dept Wise'!$E6,Master!$N$8:$N$55,'Summary Dept Wise'!$F6) -> 361693.6 | S6: =SUMIFS(Master!AN$8:AN$55,Master!$J$8:$J$55,'Summary Dept Wise'!$C6,Master!$M$8:$M$55,'Summary Dept Wise'!$E6,Master!$N$8:$N$55,'Summary Dept Wise'!$F6) -> 276694 | T6: =SUMIFS(Master!AO$8:AO$55,Master!$J$8:$J$55,'Summary Dept Wise'!$C6,Master!$M$8:$M$55,'Summary Dept Wise'!$E6,Master!$N$8:$N$55,'Summary Dept Wise'!$F6) -> 0 | U6: =SUMIFS(Master!AP$8:AP$55,Master!$J$8:$J$55,'Summary Dept Wise'!$C6,Master!$M$8:$M$55,'Summary Dept Wise'!$E6,Master!$N$8:$N$55,'Summary Dept Wise'!$F6) -> 0 | V6: =SUMIFS(Master!AQ$8:AQ$55,Master!$J$8:$J$55,'Summary Dept Wise'!$C6,Master!$M$8:$M$55,'Summary Dept Wise'!$E6,Master!$N$8:$N$55,'Summary Dept Wise'!$F6) -> 85000 | W6: =SUMIFS(Master!AR$8:AR$55,Master!$J$8:$J$55,'Summary Dept Wise'!$C6,Master!$M$8:$M$55,'Summary Dept Wise'!$E6,Master!$N$8:$N$55,'Summary Dept Wise'!$F6) -> 0 | X6: =SUM(S6:W6) -> 361694 | Y6: =SUMIFS(Master!AT$8:AT$55,Master!$J$8:$J$55,'Summary Dept Wise'!$C6,Master!$M$8:$M$55,'Summary Dept Wise'!$E6,Master!$N$8:$N$55,'Summary Dept Wise'!$F6) -> 0 | Z6: =SUM(X6:Y6) -> 361694 | AA6: =SUMIFS(Master!AI$8:AI$55,Master!$J$8:$J$55,'Summary Dept Wise'!$C6,Master!$M$8:$M$55,'Summary Dept Wise'!$E6,Master!$N$8:$N$55,'Summary Dept Wise'!$F6,Master!$AV$8:$AV$55,"Paid") -> 0 | AB6: =+Z6-AA6 -> 361694 | AC6: =SUMIFS(Master!BF$8:BF$55,Master!$J$8:$J$55,'Summary Dept Wise'!$C6,Master!$M$8:$M$55,'Summary Dept Wise'!$E6,Master!$N$8:$N$55,'Summary Dept Wise'!$F6) -> 0
C7: Administration | D7: =COUNTIFS(Master!$J$8:$J$55,'Summary Dept Wise'!$C7,Master!$M$8:$M$55,'Summary Dept Wise'!$E7,Master!$N$8:$N$55,'Summary Dept Wise'!$F7) -> 4 | E7: ALL | F7: ALL | G7: =SUMIFS(Master!$P$8:$P$55,Master!$J$8:$J$55,'Summary Dept Wise'!$C7,Master!$M$8:$M$55,'Summary Dept Wise'!$E7,Master!$N$8:$N$55,'Summary Dept Wise'!$F7) -> 100000 | H7: =SUMIFS(Master!$U$8:$U$55,Master!$J$8:$J$55,'Summary Dept Wise'!$C7,Master!$M$8:$M$55,'Summary Dept Wise'!$E7,Master!$N$8:$N$55,'Summary Dept Wise'!$F7) -> 100000 | I7: =SUMIFS(Master!$V$8:$V$55,Master!$J$8:$J$55,'Summary Dept Wise'!$C7,Master!$M$8:$M$55,'Summary Dept Wise'!$E7,Master!$N$8:$N$55,'Summary Dept Wise'!$F7) -> 0 | J7: =SUMIFS(Master!$X$8:$X$55,Master!$J$8:$J$55,'Summary Dept Wise'!$C7,Master!$M$8:$M$55,'Summary Dept Wise'!$E7,Master!$N$8:$N$55,'Summary Dept Wise'!$F7) -> 0 | K7: =SUMIFS(Master!$Z$8:$Z$55,Master!$J$8:$J$55,'Summary Dept Wise'!$C7,Master!$M$8:$M$55,'Summary Dept Wise'!$E7,Master!$N$8:$N$55,'Summary Dept Wise'!$F7) -> 0 | L7: =SUMIFS(Master!AC$8:AC$55,Master!$J$8:$J$55,'Summary Dept Wise'!$C7,Master!$M$8:$M$55,'Summary Dept Wise'!$E7,Master!$N$8:$N$55,'Summary Dept Wise'!$F7) -> 0 | M7: =SUMIFS(Master!AD$8:AD$55,Master!$J$8:$J$55,'Summary Dept Wise'!$C7,Master!$M$8:$M$55,'Summary Dept Wise'!$E7,Master!$N$8:$N$55,'Summary Dept Wise'!$F7) -> 100000 | N7: =SUMIFS(Master!AE$8:AE$55,Master!$J$8:$J$55,'Summary Dept Wise'!$C7,Master!$M$8:$M$55,'Summary Dept Wise'!$E7,Master!$N$8:$N$55,'Summary Dept Wise'!$F7) -> 0 | O7: =SUMIFS(Master!AF$8:AF$55,Master!$J$8:$J$55,'Summary Dept Wise'!$C7,Master!$M$8:$M$55,'Summary Dept Wise'!$E7,Master!$N$8:$N$55,'Summary Dept Wise'!$F7) -> 0 | P7: =SUMIFS(Master!AG$8:AG$55,Master!$J$8:$J$55,'Summary Dept Wise'!$C7,Master!$M$8:$M$55,'Summary Dept Wise'!$E7,Master!$N$8:$N$55,'Summary Dept Wise'!$F7) -> 7000 | Q7: =SUMIFS(Master!AH$8:AH$55,Master!$J$8:$J$55,'Summary Dept Wise'!$C7,Master!$M$8:$M$55,'Summary Dept Wise'!$E7,Master!$N$8:$N$55,'Summary Dept Wise'!$F7) -> 5000 | R7: =SUMIFS(Master!AI$8:AI$55,Master!$J$8:$J$55,'Summary Dept Wise'!$C7,Master!$M$8:$M$55,'Summary Dept Wise'!$E7,Master!$N$8:$N$55,'Summary Dept Wise'!$F7) -> 88000 | S7: =SUMIFS(Master!AN$8:AN$55,Master!$J$8:$J$55,'Summary Dept Wise'!$C7,Master!$M$8:$M$55,'Summary Dept Wise'!$E7,Master!$N$8:$N$55,'Summary Dept Wise'!$F7) -> 21000 | T7: =SUMIFS(Master!AO$8:AO$55,Master!$J$8:$J$55,'Summary Dept Wise'!$C7,Master!$M$8:$M$55,'Summary Dept Wise'!$E7,Master!$N$8:$N$55,'Summary Dept Wise'!$F7) -> 0 | U7: =SUMIFS(Master!AP$8:AP$55,Master!$J$8:$J$55,'Summary Dept Wise'!$C7,Master!$M$8:$M$55,'Summary Dept Wise'!$E7,Master!$N$8:$N$55,'Summary Dept Wise'!$F7) -> 0 | V7: =SUMIFS(Master!AQ$8:AQ$55,Master!$J$8:$J$55,'Summary Dept Wise'!$C7,Master!$M$8:$M$55,'Summary Dept Wise'!$E7,Master!$N$8:$N$55,'Summary Dept Wise'!$F7) -> 15000 | W7: =SUMIFS(Master!AR$8:AR$55,Master!$J$8:$J$55,'Summary Dept Wise'!$C7,Master!$M$8:$M$55,'Summary Dept Wise'!$E7,Master!$N$8:$N$55,'Summary Dept Wise'!$F7) -> 52000 | X7: =SUM(S7:W7) -> 88000 | Y7: =SUMIFS(Master!AT$8:AT$55,Master!$J$8:$J$55,'Summary Dept Wise'!$C7,Master!$M$8:$M$55,'Summary Dept Wise'!$E7,Master!$N$8:$N$55,'Summary Dept Wise'!$F7) -> 0 | Z7: =SUM(X7:Y7) -> 88000 | AA7: =SUMIFS(Master!AI$8:AI$55,Master!$J$8:$J$55,'Summary Dept Wise'!$C7,Master!$M$8:$M$55,'Summary Dept Wise'!$E7,Master!$N$8:$N$55,'Summary Dept Wise'!$F7,Master!$AV$8:$AV$55,"Paid") -> 73000 | AB7: =+Z7-AA7 -> 15000 | AC7: =SUMIFS(Master!BF$8:BF$55,Master!$J$8:$J$55,'Summary Dept Wise'!$C7,Master!$M$8:$M$55,'Summary Dept Wise'!$E7,Master!$N$8:$N$55,'Summary Dept Wise'!$F7) -> 0
C8: HR | D8: =COUNTIFS(Master!$J$8:$J$55,'Summary Dept Wise'!$C8,Master!$M$8:$M$55,'Summary Dept Wise'!$E8,Master!$N$8:$N$55,'Summary Dept Wise'!$F8) -> 2 | E8: ALL | F8: ALL | G8: =SUMIFS(Master!$P$8:$P$55,Master!$J$8:$J$55,'Summary Dept Wise'!$C8,Master!$M$8:$M$55,'Summary Dept Wise'!$E8,Master!$N$8:$N$55,'Summary Dept Wise'!$F8) -> 100000 | H8: =SUMIFS(Master!$U$8:$U$55,Master!$J$8:$J$55,'Summary Dept Wise'!$C8,Master!$M$8:$M$55,'Summary Dept Wise'!$E8,Master!$N$8:$N$55,'Summary Dept Wise'!$F8) -> 100000 | I8: =SUMIFS(Master!$V$8:$V$55,Master!$J$8:$J$55,'Summary Dept Wise'!$C8,Master!$M$8:$M$55,'Summary Dept Wise'!$E8,Master!$N$8:$N$55,'Summary Dept Wise'!$F8) -> 0 | J8: =SUMIFS(Master!$X$8:$X$55,Master!$J$8:$J$55,'Summary Dept Wise'!$C8,Master!$M$8:$M$55,'Summary Dept Wise'!$E8,Master!$N$8:$N$55,'Summary Dept Wise'!$F8) -> 0 | K8: =SUMIFS(Master!$Z$8:$Z$55,Master!$J$8:$J$55,'Summary Dept Wise'!$C8,Master!$M$8:$M$55,'Summary Dept Wise'!$E8,Master!$N$8:$N$55,'Summary Dept Wise'!$F8) -> 44736.842 | L8: =SUMIFS(Master!AC$8:AC$55,Master!$J$8:$J$55,'Summary Dept Wise'!$C8,Master!$M$8:$M$55,'Summary Dept Wise'!$E8,Master!$N$8:$N$55,'Summary Dept Wise'!$F8) -> 0 | M8: =SUMIFS(Master!AD$8:AD$55,Master!$J$8:$J$55,'Summary Dept Wise'!$C8,Master!$M$8:$M$55,'Summary Dept Wise'!$E8,Master!$N$8:$N$55,'Summary Dept Wise'!$F8) -> 55263.158 | N8: =SUMIFS(Master!AE$8:AE$55,Master!$J$8:$J$55,'Summary Dept Wise'!$C8,Master!$M$8:$M$55,'Summary Dept Wise'!$E8,Master!$N$8:$N$55,'Summary Dept Wise'!$F8) -> 0 | O8: =SUMIFS(Master!AF$8:AF$55,Master!$J$8:$J$55,'Summary Dept Wise'!$C8,Master!$M$8:$M$55,'Summary Dept Wise'!$E8,Master!$N$8:$N$55,'Summary Dept Wise'!$F8) -> 250 | P8: =SUMIFS(Master!AG$8:AG$55,Master!$J$8:$J$55,'Summary Dept Wise'!$C8,Master!$M$8:$M$55,'Summary Dept Wise'!$E8,Master!$N$8:$N$55,'Summary Dept Wise'!$F8) -> 0 | Q8: =SUMIFS(Master!AH$8:AH$55,Master!$J$8:$J$55,'Summary Dept Wise'!$C8,Master!$M$8:$M$55,'Summary Dept Wise'!$E8,Master!$N$8:$N$55,'Summary Dept Wise'!$F8) -> 5000 | R8: =SUMIFS(Master!AI$8:AI$55,Master!$J$8:$J$55,'Summary Dept Wise'!$C8,Master!$M$8:$M$55,'Summary Dept Wise'!$E8,Master!$N$8:$N$55,'Summary Dept Wise'!$F8) -> 50013.158 | S8: =SUMIFS(Master!AN$8:AN$55,Master!$J$8:$J$55,'Summary Dept Wise'!$C8,Master!$M$8:$M$55,'Summary Dept Wise'!$E8,Master!$N$8:$N$55,'Summary Dept Wise'!$F8) -> 7644.7368 | T8: =SUMIFS(Master!AO$8:AO$55,Master!$J$8:$J$55,'Summary Dept Wise'!$C8,Master!$M$8:$M$55,'Summary Dept Wise'!$E8,Master!$N$8:$N$55,'Summary Dept Wise'!$F8) -> 0 | U8: =SUMIFS(Master!AP$8:AP$55,Master!$J$8:$J$55,'Summary Dept Wise'!$C8,Master!$M$8:$M$55,'Summary Dept Wise'!$E8,Master!$N$8:$N$55,'Summary Dept Wise'!$F8) -> 0 | V8: =SUMIFS(Master!AQ$8:AQ$55,Master!$J$8:$J$55,'Summary Dept Wise'!$C8,Master!$M$8:$M$55,'Summary Dept Wise'!$E8,Master!$N$8:$N$55,'Summary Dept Wise'!$F8) -> 42368.421 | W8: =SUMIFS(Master!AR$8:AR$55,Master!$J$8:$J$55,'Summary Dept Wise'!$C8,Master!$M$8:$M$55,'Summary Dept Wise'!$E8,Master!$N$8:$N$55,'Summary Dept Wise'!$F8) -> 0 | X8: =SUM(S8:W8) -> 50013.158 | Y8: =SUMIFS(Master!AT$8:AT$55,Master!$J$8:$J$55,'Summary Dept Wise'!$C8,Master!$M$8:$M$55,'Summary Dept Wise'!$E8,Master!$N$8:$N$55,'Summary Dept Wise'!$F8) -> 0 | Z8: =SUM(X8:Y8) -> 50013.158 | AA8: =SUMIFS(Master!AI$8:AI$55,Master!$J$8:$J$55,'Summary Dept Wise'!$C8,Master!$M$8:$M$55,'Summary Dept Wise'!$E8,Master!$N$8:$N$55,'Summary Dept Wise'!$F8,Master!$AV$8:$AV$55,"Paid") -> 0 | AB8: =+Z8-AA8 -> 50013.158 | AC8: =SUMIFS(Master!BF$8:BF$55,Master!$J$8:$J$55,'Summary Dept Wise'!$C8,Master!$M$8:$M$55,'Summary Dept Wise'!$E8,Master!$N$8:$N$55,'Summary Dept Wise'!$F8) -> 0
C9: IT | D9: =COUNTIFS(Master!$J$8:$J$55,'Summary Dept Wise'!$C9,Master!$M$8:$M$55,'Summary Dept Wise'!$E9,Master!$N$8:$N$55,'Summary Dept Wise'!$F9) -> 1 | E9: ALL | F9: ALL | G9: =SUMIFS(Master!$P$8:$P$55,Master!$J$8:$J$55,'Summary Dept Wise'!$C9,Master!$M$8:$M$55,'Summary Dept Wise'!$E9,Master!$N$8:$N$55,'Summary Dept Wise'!$F9) -> 80000 | H9: =SUMIFS(Master!$U$8:$U$55,Master!$J$8:$J$55,'Summary Dept Wise'!$C9,Master!$M$8:$M$55,'Summary Dept Wise'!$E9,Master!$N$8:$N$55,'Summary Dept Wise'!$F9) -> 80000 | I9: =SUMIFS(Master!$V$8:$V$55,Master!$J$8:$J$55,'Summary Dept Wise'!$C9,Master!$M$8:$M$55,'Summary Dept Wise'!$E9,Master!$N$8:$N$55,'Summary Dept Wise'!$F9) -> 0 | J9: =SUMIFS(Master!$X$8:$X$55,Master!$J$8:$J$55,'Summary Dept Wise'!$C9,Master!$M$8:$M$55,'Summary Dept Wise'!$E9,Master!$N$8:$N$55,'Summary Dept Wise'!$F9) -> 0 | K9: =SUMIFS(Master!$Z$8:$Z$55,Master!$J$8:$J$55,'Summary Dept Wise'!$C9,Master!$M$8:$M$55,'Summary Dept Wise'!$E9,Master!$N$8:$N$55,'Summary Dept Wise'!$F9) -> 0 | L9: =SUMIFS(Master!AC$8:AC$55,Master!$J$8:$J$55,'Summary Dept Wise'!$C9,Master!$M$8:$M$55,'Summary Dept Wise'!$E9,Master!$N$8:$N$55,'Summary Dept Wise'!$F9) -> 0 | M9: =SUMIFS(Master!AD$8:AD$55,Master!$J$8:$J$55,'Summary Dept Wise'!$C9,Master!$M$8:$M$55,'Summary Dept Wise'!$E9,Master!$N$8:$N$55,'Summary Dept Wise'!$F9) -> 80000 | N9: =SUMIFS(Master!AE$8:AE$55,Master!$J$8:$J$55,'Summary Dept Wise'!$C9,Master!$M$8:$M$55,'Summary Dept Wise'!$E9,Master!$N$8:$N$55,'Summary Dept Wise'!$F9) -> 467.8 | O9: =SUMIFS(Master!AF$8:AF$55,Master!$J$8:$J$55,'Summary Dept Wise'!$C9,Master!$M$8:$M$55,'Summary Dept Wise'!$E9,Master!$N$8:$N$55,'Summary Dept Wise'!$F9) -> 0 | P9: =SUMIFS(Master!AG$8:AG$55,Master!$J$8:$J$55,'Summary Dept Wise'!$C9,Master!$M$8:$M$55,'Summary Dept Wise'!$E9,Master!$N$8:$N$55,'Summary Dept Wise'!$F9) -> 0 | Q9: =SUMIFS(Master!AH$8:AH$55,Master!$J$8:$J$55,'Summary Dept Wise'!$C9,Master!$M$8:$M$55,'Summary Dept Wise'!$E9,Master!$N$8:$N$55,'Summary Dept Wise'!$F9) -> 0 | R9: =SUMIFS(Master!AI$8:AI$55,Master!$J$8:$J$55,'Summary Dept Wise'!$C9,Master!$M$8:$M$55,'Summary Dept Wise'!$E9,Master!$N$8:$N$55,'Summary Dept Wise'!$F9) -> 79532.2 | S9: =SUMIFS(Master!AN$8:AN$55,Master!$J$8:$J$55,'Summary Dept Wise'!$C9,Master!$M$8:$M$55,'Summary Dept Wise'!$E9,Master!$N$8:$N$55,'Summary Dept Wise'!$F9) -> 0 | T9: =SUMIFS(Master!AO$8:AO$55,Master!$J$8:$J$55,'Summary Dept Wise'!$C9,Master!$M$8:$M$55,'Summary Dept Wise'!$E9,Master!$N$8:$N$55,'Summary Dept Wise'!$F9) -> 0 | U9: =SUMIFS(Master!AP$8:AP$55,Master!$J$8:$J$55,'Summary Dept Wise'!$C9,Master!$M$8:$M$55,'Summary Dept Wise'!$E9,Master!$N$8:$N$55,'Summary Dept Wise'!$F9) -> 0 | V9: =SUMIFS(Master!AQ$8:AQ$55,Master!$J$8:$J$55,'Summary Dept Wise'!$C9,Master!$M$8:$M$55,'Summary Dept Wise'!$E9,Master!$N$8:$N$55,'Summary Dept Wise'!$F9) -> 79532.2 | W9: =SUMIFS(Master!AR$8:AR$55,Master!$J$8:$J$55,'Summary Dept Wise'!$C9,Master!$M$8:$M$55,'Summary Dept Wise'!$E9,Master!$N$8:$N$55,'Summary Dept Wise'!$F9) -> 0 | X9: =SUM(S9:W9) -> 79532.2 | Y9: =SUMIFS(Master!AT$8:AT$55,Master!$J$8:$J$55,'Summary Dept Wise'!$C9,Master!$M$8:$M$55,'Summary Dept Wise'!$E9,Master!$N$8:$N$55,'Summary Dept Wise'!$F9) -> 0 | Z9: =SUM(X9:Y9) -> 79532.2 | AA9: =SUMIFS(Master!AI$8:AI$55,Master!$J$8:$J$55,'Summary Dept Wise'!$C9,Master!$M$8:$M$55,'Summary Dept Wise'!$E9,Master!$N$8:$N$55,'Summary Dept Wise'!$F9,Master!$AV$8:$AV$55,"Paid") -> 0 | AB9: =+Z9-AA9 -> 79532.2 | AC9: =SUMIFS(Master!BF$8:BF$55,Master!$J$8:$J$55,'Summary Dept Wise'!$C9,Master!$M$8:$M$55,'Summary Dept Wise'!$E9,Master!$N$8:$N$55,'Summary Dept Wise'!$F9) -> 0
C10: (PKR) | D10: =SUBTOTAL(9,D6:D9) -> 10 | F10: =G10/$G$69 -> 0.20454545 | G10: =SUBTOTAL(9,G6:G9) -> 657000 | H10: =SUBTOTAL(9,H6:H9) -> 657000 | I10: =SUBTOTAL(9,I6:I9) -> 0 | J10: =SUBTOTAL(9,J6:J9) -> 0 | K10: =SUBTOTAL(9,K6:K9) -> 44736.842 | L10: =SUBTOTAL(9,L6:L9) -> 0 | M10: =SUBTOTAL(9,M6:M9) -> 612263.16 | N10: =SUBTOTAL(9,N6:N9) -> 5274.2 | ... AC10: =SUBTOTAL(9,AC6:AC9) -> 0
C11: (USD) | G11: =+G10/$H$1 -> 2380.4348 | H11: =+H10/$H$1 -> 2380.4348 | I11: =+I10/$H$1 -> 0 | J11: =+J10/$H$1 -> 0 | K11: =+K10/$H$1 -> 162.09001 | L11: =+L10/$H$1 -> 0 | M11: =+M10/$H$1 -> 2218.3448 | N11: =+N10/$H$1 -> 19.10942 | ... AC11: =+AC10/$H$1 -> 0
B13: DESGIN
B14: Design - Portal
C15: Production - Design | D15: =COUNTIFS('Payroll DES Apr24'!$M$6:$M$35,'Summary Dept Wise'!$E15,'Payroll DES Apr24'!$N$6:$N$35,'Summary Dept Wise'!$F15,'Payroll DES Apr24'!$J$6:$J$35,'Summary Dept Wise'!$C15) -> 1 | E15: PORTAL | F15: PORTAL | G15: =SUMIFS(Master!$P$8:$P$55,Master!$J$8:$J$55,'Summary Dept Wise'!$C15,Master!$M$8:$M$55,'Summary Dept Wise'!$E15,Master!$N$8:$N$55,'Summary Dept Wise'!$F15) -> 100000 | H15: =SUMIFS('Payroll DES Apr24'!U$6:U$35,'Payroll DES Apr24'!$M$6:$M$35,'Summary Dept Wise'!$E15,'Payroll DES Apr24'!$N$6:$N$35,'Summary Dept Wise'!$F15,'Payroll DES Apr24'!$J$6:$J$35,'Summary Dept Wise'!$C15) -> 100000 | I15: =SUMIFS('Payroll DES Apr24'!V$6:V$35,'Payroll DES Apr24'!$M$6:$M$35,'Summary Dept Wise'!$E15,'Payroll DES Apr24'!$N$6:$N$35,'Summary Dept Wise'!$F15,'Payroll DES Apr24'!$J$6:$J$35,'Summary Dept Wise'!$C15) -> 0 | J15: =SUMIFS('Payroll DES Apr24'!X$6:X$35,'Payroll DES Apr24'!$M$6:$M$35,'Summary Dept Wise'!$E15,'Payroll DES Apr24'!$N$6:$N$35,'Summary Dept Wise'!$F15,'Payroll DES Apr24'!$J$6:$J$35,'Summary Dept Wise'!$C15) -> 0 | K15: =SUMIFS('Payroll DES Apr24'!Z$6:Z$35,'Payroll DES Apr24'!$M$6:$M$35,'Summary Dept Wise'!$E15,'Payroll DES Apr24'!$N$6:$N$35,'Summary Dept Wise'!$F15,'Payroll DES Apr24'!$J$6:$J$35,'Summary Dept Wise'!$C15) -> 28571.429 | L15: =SUMIFS('Payroll DES Apr24'!AC$6:AC$35,'Payroll DES Apr24'!$M$6:$M$35,'Summary Dept Wise'!$E15,'Payroll DES Apr24'!$N$6:$N$35,'Summary Dept Wise'!$F15,'Payroll DES Apr24'!$J$6:$J$35,'Summary Dept Wise'!$C15) -> 0 | M15: =SUMIFS('Payroll DES Apr24'!AD$6:AD$35,'Payroll DES Apr24'!$M$6:$M$35,'Summary Dept Wise'!$E15,'Payroll DES Apr24'!$N$6:$N$35,'Summary Dept Wise'!$F15,'Payroll DES Apr24'!$J$6:$J$35,'Summary Dept Wise'!$C15) -> 71428.571 | N15: =SUMIFS('Payroll DES Apr24'!AE$6:AE$35,'Payroll DES Apr24'!$M$6:$M$35,'Summary Dept Wise'!$E15,'Payroll DES Apr24'!$N$6:$N$35,'Summary Dept Wise'!$F15,'Payroll DES Apr24'!$J$6:$J$35,'Summary Dept Wise'!$C15) -> 0 | O15: =SUMIFS('Payroll DES Apr24'!AF$6:AF$35,'Payroll DES Apr24'!$M$6:$M$35,'Summary Dept Wise'!$E15,'Payroll DES Apr24'!$N$6:$N$35,'Summary Dept Wise'!$F15,'Payroll DES Apr24'!$J$6:$J$35,'Summary Dept Wise'!$C15) -> 0 | P15: =SUMIFS('Payroll DES Apr24'!AG$6:AG$35,'Payroll DES Apr24'!$M$6:$M$35,'Summary Dept Wise'!$E15,'Payroll DES Apr24'!$N$6:$N$35,'Summary Dept Wise'!$F15,'Payroll DES Apr24'!$J$6:$J$35,'Summary Dept Wise'!$C15) -> 0 | Q15: =SUMIFS('Payroll DES Apr24'!AH$6:AH$35,'Payroll DES Apr24'!$M$6:$M$35,'Summary Dept Wise'!$E15,'Payroll DES Apr24'!$N$6:$N$35,'Summary Dept Wise'!$F15,'Payroll DES Apr24'!$J$6:$J$35,'Summary Dept Wise'!$C15) -> 0 | R15: =SUMIFS('Payroll DES Apr24'!AI$6:AI$35,'Payroll DES Apr24'!$M$6:$M$35,'Summary Dept Wise'!$E15,'Payroll DES Apr24'!$N$6:$N$35,'Summary Dept Wise'!$F15,'Payroll DES Apr24'!$J$6:$J$35,'Summary Dept Wise'!$C15) -> 71428.571 | S15: =SUMIFS('Payroll DES Apr24'!AN$6:AN$35,'Payroll DES Apr24'!$M$6:$M$35,'Summary Dept Wise'!$E15,'Payroll DES Apr24'!$N$6:$N$35,'Summary Dept Wise'!$F15,'Payroll DES Apr24'!$J$6:$J$35,'Summary Dept Wise'!$C15) -> 71428.571 | T15: =SUMIFS('Payroll DES Apr24'!AO$6:AO$35,'Payroll DES Apr24'!$M$6:$M$35,'Summary Dept Wise'!$E15,'Payroll DES Apr24'!$N$6:$N$35,'Summary Dept Wise'!$F15,'Payroll DES Apr24'!$J$6:$J$35,'Summary Dept Wise'!$C15) -> 0 | U15: =SUMIFS('Payroll DES Apr24'!AP$6:AP$35,'Payroll DES Apr24'!$M$6:$M$35,'Summary Dept Wise'!$E15,'Payroll DES Apr24'!$N$6:$N$35,'Summary Dept Wise'!$F15,'Payroll DES Apr24'!$J$6:$J$35,'Summary Dept Wise'!$C15) -> 0 | V15: =SUMIFS('Payroll DES Apr24'!AQ$6:AQ$35,'Payroll DES Apr24'!$M$6:$M$35,'Summary Dept Wise'!$E15,'Payroll DES Apr24'!$N$6:$N$35,'Summary Dept Wise'!$F15,'Payroll DES Apr24'!$J$6:$J$35,'Summary Dept Wise'!$C15) -> 0 | W15: =SUMIFS('Payroll DES Apr24'!AR$6:AR$35,'Payroll DES Apr24'!$M$6:$M$35,'Summary Dept Wise'!$E15,'Payroll DES Apr24'!$N$6:$N$35,'Summary Dept Wise'!$F15,'Payroll DES Apr24'!$J$6:$J$35,'Summary Dept Wise'!$C15) -> 0 | X15: =SUM(S15:W15) -> 71428.571 | Y15: =SUMIFS('Payroll DES Apr24'!AT$6:AT$35,'Payroll DES Apr24'!$M$6:$M$35,'Summary Dept Wise'!$E15,'Payroll DES Apr24'!$N$6:$N$35,'Summary Dept Wise'!$F15,'Payroll DES Apr24'!$J$6:$J$35,'Summary Dept Wise'!$C15) -> 0 | Z15: =SUM(X15:Y15) -> 71428.571 | AA15: =SUMIFS(Master!AI$8:AI$55,Master!$J$8:$J$55,'Summary Dept Wise'!$C15,Master!$M$8:$M$55,'Summary Dept Wise'!$E15,Master!$N$8:$N$55,'Summary Dept Wise'!$F15,Master!$AV$8:$AV$55,"Paid") -> 0 | AB15: =+Z15-AA15 -> 71428.571 | AC15: =SUMIFS(Master!BF$8:BF$55,Master!$J$8:$J$55,'Summary Dept Wise'!$C15,Master!$M$8:$M$55,'Summary Dept Wise'!$E15,Master!$N$8:$N$55,'Summary Dept Wise'!$F15) -> 0
C16: Marketing | D16: =COUNTIFS('Payroll DES Apr24'!$M$6:$M$35,'Summary Dept Wise'!$E16,'Payroll DES Apr24'!$N$6:$N$35,'Summary Dept Wise'!$F16,'Payroll DES Apr24'!$J$6:$J$35,'Summary Dept Wise'!$C16) -> 0 | E16: PORTAL | F16: PORTAL | G16: =SUMIFS('Payroll DES Apr24'!T$6:T$35,'Payroll DES Apr24'!$M$6:$M$35,'Summary Dept Wise'!$E16,'Payroll DES Apr24'!$N$6:$N$35,'Summary Dept Wise'!$F16,'Payroll DES Apr24'!$J$6:$J$35,'Summary Dept Wise'!$C16) -> 0 | H16: =SUMIFS('Payroll DES Apr24'!U$6:U$35,'Payroll DES Apr24'!$M$6:$M$35,'Summary Dept Wise'!$E16,'Payroll DES Apr24'!$N$6:$N$35,'Summary Dept Wise'!$F16,'Payroll DES Apr24'!$J$6:$J$35,'Summary Dept Wise'!$C16) -> 0 | I16: =SUMIFS('Payroll DES Apr24'!V$6:V$35,'Payroll DES Apr24'!$M$6:$M$35,'Summary Dept Wise'!$E16,'Payroll DES Apr24'!$N$6:$N$35,'Summary Dept Wise'!$F16,'Payroll DES Apr24'!$J$6:$J$35,'Summary Dept Wise'!$C16) -> 0 | J16: =SUMIFS('Payroll DES Apr24'!X$6:X$35,'Payroll DES Apr24'!$M$6:$M$35,'Summary Dept Wise'!$E16,'Payroll DES Apr24'!$N$6:$N$35,'Summary Dept Wise'!$F16,'Payroll DES Apr24'!$J$6:$J$35,'Summary Dept Wise'!$C16) -> 0 | K16: =SUMIFS('Payroll DES Apr24'!Z$6:Z$35,'Payroll DES Apr24'!$M$6:$M$35,'Summary Dept Wise'!$E16,'Payroll DES Apr24'!$N$6:$N$35,'Summary Dept Wise'!$F16,'Payroll DES Apr24'!$J$6:$J$35,'Summary Dept Wise'!$C16) -> 0 | L16: =SUMIFS('Payroll DES Apr24'!AC$6:AC$35,'Payroll DES Apr24'!$M$6:$M$35,'Summary Dept Wise'!$E16,'Payroll DES Apr24'!$N$6:$N$35,'Summary Dept Wise'!$F16,'Payroll DES Apr24'!$J$6:$J$35,'Summary Dept Wise'!$C16) -> 0 | M16: =SUMIFS('Payroll DES Apr24'!AD$6:AD$35,'Payroll DES Apr24'!$M$6:$M$35,'Summary Dept Wise'!$E16,'Payroll DES Apr24'!$N$6:$N$35,'Summary Dept Wise'!$F16,'Payroll DES Apr24'!$J$6:$J$35,'Summary Dept Wise'!$C16) -> 0 | N16: =SUMIFS('Payroll DES Apr24'!AE$6:AE$35,'Payroll DES Apr24'!$M$6:$M$35,'Summary Dept Wise'!$E16,'Payroll DES Apr24'!$N$6:$N$35,'Summary Dept Wise'!$F16,'Payroll DES Apr24'!$J$6:$J$35,'Summary Dept Wise'!$C16) -> 0 | O16: =SUMIFS('Payroll DES Apr24'!AF$6:AF$35,'Payroll DES Apr24'!$M$6:$M$35,'Summary Dept Wise'!$E16,'Payroll DES Apr24'!$N$6:$N$35,'Summary Dept Wise'!$F16,'Payroll DES Apr24'!$J$6:$J$35,'Summary Dept Wise'!$C16) -> 0 | P16: =SUMIFS('Payroll DES Apr24'!AG$6:AG$35,'Payroll DES Apr24'!$M$6:$M$35,'Summary Dept Wise'!$E16,'Payroll DES Apr24'!$N$6:$N$35,'Summary Dept Wise'!$F16,'Payroll DES Apr24'!$J$6:$J$35,'Summary Dept Wise'!$C16) -> 0 | Q16: =SUMIFS('Payroll DES Apr24'!AH$6:AH$35,'Payroll DES Apr24'!$M$6:$M$35,'Summary Dept Wise'!$E16,'Payroll DES Apr24'!$N$6:$N$35,'Summary Dept Wise'!$F16,'Payroll DES Apr24'!$J$6:$J$35,'Summary Dept Wise'!$C16) -> 0 | R16: =SUMIFS('Payroll DES Apr24'!AI$6:AI$35,'Payroll DES Apr24'!$M$6:$M$35,'Summary Dept Wise'!$E16,'Payroll DES Apr24'!$N$6:$N$35,'Summary Dept Wise'!$F16,'Payroll DES Apr24'!$J$6:$J$35,'Summary Dept Wise'!$C16) -> 0 | S16: =SUMIFS('Payroll DES Apr24'!AN$6:AN$35,'Payroll DES Apr24'!$M$6:$M$35,'Summary Dept Wise'!$E16,'Payroll DES Apr24'!$N$6:$N$35,'Summary Dept Wise'!$F16,'Payroll DES Apr24'!$J$6:$J$35,'Summary Dept Wise'!$C16) -> 0 | T16: =SUMIFS('Payroll DES Apr24'!AO$6:AO$35,'Payroll DES Apr24'!$M$6:$M$35,'Summary Dept Wise'!$E16,'Payroll DES Apr24'!$N$6:$N$35,'Summary Dept Wise'!$F16,'Payroll DES Apr24'!$J$6:$J$35,'Summary Dept Wise'!$C16) -> 0 | U16: =SUMIFS('Payroll DES Apr24'!AP$6:AP$35,'Payroll DES Apr24'!$M$6:$M$35,'Summary Dept Wise'!$E16,'Payroll DES Apr24'!$N$6:$N$35,'Summary Dept Wise'!$F16,'Payroll DES Apr24'!$J$6:$J$35,'Summary Dept Wise'!$C16) -> 0 | V16: =SUMIFS('Payroll DES Apr24'!AQ$6:AQ$35,'Payroll DES Apr24'!$M$6:$M$35,'Summary Dept Wise'!$E16,'Payroll DES Apr24'!$N$6:$N$35,'Summary Dept Wise'!$F16,'Payroll DES Apr24'!$J$6:$J$35,'Summary Dept Wise'!$C16) -> 0 | W16: =SUMIFS('Payroll DES Apr24'!AR$6:AR$35,'Payroll DES Apr24'!$M$6:$M$35,'Summary Dept Wise'!$E16,'Payroll DES Apr24'!$N$6:$N$35,'Summary Dept Wise'!$F16,'Payroll DES Apr24'!$J$6:$J$35,'Summary Dept Wise'!$C16) -> 0 | X16: =SUM(S16:W16) -> 0 | Y16: =SUMIFS('Payroll DES Apr24'!AT$6:AT$35,'Payroll DES Apr24'!$M$6:$M$35,'Summary Dept Wise'!$E16,'Payroll DES Apr24'!$N$6:$N$35,'Summary Dept Wise'!$F16,'Payroll DES Apr24'!$J$6:$J$35,'Summary Dept Wise'!$C16) -> 0 | Z16: =SUM(X16:Y16) -> 0 | AA16: =SUMIFS(Master!AI$8:AI$55,Master!$J$8:$J$55,'Summary Dept Wise'!$C16,Master!$M$8:$M$55,'Summary Dept Wise'!$E16,Master!$N$8:$N$55,'Summary Dept Wise'!$F16,Master!$AV$8:$AV$55,"Paid") -> 0 | AB16: =+Z16-AA16 -> 0 | AC16: =SUMIFS(Master!BF$8:BF$55,Master!$J$8:$J$55,'Summary Dept Wise'!$C16,Master!$M$8:$M$55,'Summary Dept Wise'!$E16,Master!$N$8:$N$55,'Summary Dept Wise'!$F16) -> 0
C17: Sales | D17: =COUNTIFS(Master!$J$8:$J$55,'Summary Dept Wise'!$C17,Master!$M$8:$M$55,'Summary Dept Wise'!$E17,Master!$N$8:$N$55,'Summary Dept Wise'!$F17) -> 1 | E17: PORTAL | F17: PORTAL | G17: =SUMIFS(Master!$P$8:$P$55,Master!$J$8:$J$55,'Summary Dept Wise'!$C17,Master!$M$8:$M$55,'Summary Dept Wise'!$E17,Master!$N$8:$N$55,'Summary Dept Wise'!$F17) -> 175000 | H17: =SUMIFS(Master!$U$8:$U$55,Master!$J$8:$J$55,'Summary Dept Wise'!$C17,Master!$M$8:$M$55,'Summary Dept Wise'!$E17,Master!$N$8:$N$55,'Summary Dept Wise'!$F17) -> 175000 | I17: =SUMIFS(Master!$V$8:$V$55,Master!$J$8:$J$55,'Summary Dept Wise'!$C17,Master!$M$8:$M$55,'Summary Dept Wise'!$E17,Master!$N$8:$N$55,'Summary Dept Wise'!$F17) -> 0 | J17: =SUMIFS(Master!$X$8:$X$55,Master!$J$8:$J$55,'Summary Dept Wise'!$C17,Master!$M$8:$M$55,'Summary Dept Wise'!$E17,Master!$N$8:$N$55,'Summary Dept Wise'!$F17) -> 0 | K17: =SUMIFS(Master!$Z$8:$Z$55,Master!$J$8:$J$55,'Summary Dept Wise'!$C17,Master!$M$8:$M$55,'Summary Dept Wise'!$E17,Master!$N$8:$N$55,'Summary Dept Wise'!$F17) -> 0 | L17: =SUMIFS(Master!AC$8:AC$55,Master!$J$8:$J$55,'Summary Dept Wise'!$C17,Master!$M$8:$M$55,'Summary Dept Wise'!$E17,Master!$N$8:$N$55,'Summary Dept Wise'!$F17) -> 0 | M17: =SUMIFS(Master!AD$8:AD$55,Master!$J$8:$J$55,'Summary Dept Wise'!$C17,Master!$M$8:$M$55,'Summary Dept Wise'!$E17,Master!$N$8:$N$55,'Summary Dept Wise'!$F17) -> 175000 | N17: =SUMIFS(Master!AE$8:AE$55,Master!$J$8:$J$55,'Summary Dept Wise'!$C17,Master!$M$8:$M$55,'Summary Dept Wise'!$E17,Master!$N$8:$N$55,'Summary Dept Wise'!$F17) -> 0 | O17: =SUMIFS(Master!AF$8:AF$55,Master!$J$8:$J$55,'Summary Dept Wise'!$C17,Master!$M$8:$M$55,'Summary Dept Wise'!$E17,Master!$N$8:$N$55,'Summary Dept Wise'!$F17) -> 0 | P17: =SUMIFS(Master!AG$8:AG$55,Master!$J$8:$J$55,'Summary Dept Wise'!$C17,Master!$M$8:$M$55,'Summary Dept Wise'!$E17,Master!$N$8:$N$55,'Summary Dept Wise'!$F17) -> 0 | Q17: =SUMIFS(Master!AH$8:AH$55,Master!$J$8:$J$55,'Summary Dept Wise'!$C17,Master!$M$8:$M$55,'Summary Dept Wise'!$E17,Master!$N$8:$N$55,'Summary Dept Wise'!$F17) -> 0 | R17: =SUMIFS(Master!AI$8:AI$55,Master!$J$8:$J$55,'Summary Dept Wise'!$C17,Master!$M$8:$M$55,'Summary Dept Wise'!$E17,Master!$N$8:$N$55,'Summary Dept Wise'!$F17) -> 175000 | S17: =SUMIFS(Master!AN$8:AN$55,Master!$J$8:$J$55,'Summary Dept Wise'!$C17,Master!$M$8:$M$55,'Summary Dept Wise'!$E17,Master!$N$8:$N$55,'Summary Dept Wise'!$F17) -> 175000 | T17: =SUMIFS(Master!AO$8:AO$55,Master!$J$8:$J$55,'Summary Dept Wise'!$C17,Master!$M$8:$M$55,'Summary Dept Wise'!$E17,Master!$N$8:$N$55,'Summary Dept Wise'!$F17) -> 0 | U17: =SUMIFS(Master!AP$8:AP$55,Master!$J$8:$J$55,'Summary Dept Wise'!$C17,Master!$M$8:$M$55,'Summary Dept Wise'!$E17,Master!$N$8:$N$55,'Summary Dept Wise'!$F17) -> 0 | V17: =SUMIFS(Master!AQ$8:AQ$55,Master!$J$8:$J$55,'Summary Dept Wise'!$C17,Master!$M$8:$M$55,'Summary Dept Wise'!$E17,Master!$N$8:$N$55,'Summary Dept Wise'!$F17) -> 0 | W17: =SUMIFS(Master!AR$8:AR$55,Master!$J$8:$J$55,'Summary Dept Wise'!$C17,Master!$M$8:$M$55,'Summary Dept Wise'!$E17,Master!$N$8:$N$55,'Summary Dept Wise'!$F17) -> 0 | X17: =SUM(S17:W17) -> 175000 | Y17: =SUMIFS(Master!AT$8:AT$55,Master!$J$8:$J$55,'Summary Dept Wise'!$C17,Master!$M$8:$M$55,'Summary Dept Wise'!$E17,Master!$N$8:$N$55,'Summary Dept Wise'!$F17) -> 0 | Z17: =SUM(X17:Y17) -> 175000 | AA17: =SUMIFS(Master!AI$8:AI$55,Master!$J$8:$J$55,'Summary Dept Wise'!$C17,Master!$M$8:$M$55,'Summary Dept Wise'!$E17,Master!$N$8:$N$55,'Summary Dept Wise'!$F17,Master!$AV$8:$AV$55,"Paid") -> 0 | AB17: =+Z17-AA17 -> 175000 | AC17: =SUMIFS(Master!BF$8:BF$55,Master!$J$8:$J$55,'Summary Dept Wise'!$C17,Master!$M$8:$M$55,'Summary Dept Wise'!$E17,Master!$N$8:$N$55,'Summary Dept Wise'!$F17) -> 0
D18: =SUBTOTAL(9,D15:D17) -> 2 | F18: =G18/$G$69 -> 0.085616438 | G18: =SUBTOTAL(9,G15:G17) -> 275000 | H18: =SUBTOTAL(9,H15:H17) -> 275000 | I18: =SUBTOTAL(9,I15:I17) -> 0 | J18: =SUBTOTAL(9,J15:J17) -> 0 | K18: =SUBTOTAL(9,K15:K17) -> 28571.429 | L18: =SUBTOTAL(9,L15:L17) -> 0 | M18: =SUBTOTAL(9,M15:M17) -> 246428.57 | N18: =SUBTOTAL(9,N15:N17) -> 0 | ... AC18: =SUBTOTAL(9,AC15:AC17) -> 0
B21: Design - Production
C22: Production - Web | D22: =COUNTIFS(Master!$J$8:$J$55,'Summary Dept Wise'!$C22,Master!$M$8:$M$55,'Summary Dept Wise'!$E22,Master!$N$8:$N$55,'Summary Dept Wise'!$F22) -> 0 | E22: DD | F22: ALL | G22: =SUMIFS(Master!$P$8:$P$55,Master!$J$8:$J$55,'Summary Dept Wise'!$C22,Master!$M$8:$M$55,'Summary Dept Wise'!$E22,Master!$N$8:$N$55,'Summary Dept Wise'!$F22) -> 0 | H22: =SUMIFS(Master!$U$8:$U$55,Master!$J$8:$J$55,'Summary Dept Wise'!$C22,Master!$M$8:$M$55,'Summary Dept Wise'!$E22,Master!$N$8:$N$55,'Summary Dept Wise'!$F22) -> 0 | I22: =SUMIFS(Master!$V$8:$V$55,Master!$J$8:$J$55,'Summary Dept Wise'!$C22,Master!$M$8:$M$55,'Summary Dept Wise'!$E22,Master!$N$8:$N$55,'Summary Dept Wise'!$F22) -> 0 | J22: =SUMIFS(Master!$X$8:$X$55,Master!$J$8:$J$55,'Summary Dept Wise'!$C22,Master!$M$8:$M$55,'Summary Dept Wise'!$E22,Master!$N$8:$N$55,'Summary Dept Wise'!$F22) -> 0 | K22: =SUMIFS(Master!$Z$8:$Z$55,Master!$J$8:$J$55,'Summary Dept Wise'!$C22,Master!$M$8:$M$55,'Summary Dept Wise'!$E22,Master!$N$8:$N$55,'Summary Dept Wise'!$F22) -> 0 | L22: =SUMIFS(Master!AC$8:AC$55,Master!$J$8:$J$55,'Summary Dept Wise'!$C22,Master!$M$8:$M$55,'Summary Dept Wise'!$E22,Master!$N$8:$N$55,'Summary Dept Wise'!$F22) -> 0 | M22: =SUMIFS(Master!AD$8:AD$55,Master!$J$8:$J$55,'Summary Dept Wise'!$C22,Master!$M$8:$M$55,'Summary Dept Wise'!$E22,Master!$N$8:$N$55,'Summary Dept Wise'!$F22) -> 0 | N22: =SUMIFS(Master!AE$8:AE$55,Master!$J$8:$J$55,'Summary Dept Wise'!$C22,Master!$M$8:$M$55,'Summary Dept Wise'!$E22,Master!$N$8:$N$55,'Summary Dept Wise'!$F22) -> 0 | O22: =SUMIFS(Master!AF$8:AF$55,Master!$J$8:$J$55,'Summary Dept Wise'!$C22,Master!$M$8:$M$55,'Summary Dept Wise'!$E22,Master!$N$8:$N$55,'Summary Dept Wise'!$F22) -> 0 | P22: =SUMIFS(Master!AG$8:AG$55,Master!$J$8:$J$55,'Summary Dept Wise'!$C22,Master!$M$8:$M$55,'Summary Dept Wise'!$E22,Master!$N$8:$N$55,'Summary Dept Wise'!$F22) -> 0 | Q22: =SUMIFS(Master!AH$8:AH$55,Master!$J$8:$J$55,'Summary Dept Wise'!$C22,Master!$M$8:$M$55,'Summary Dept Wise'!$E22,Master!$N$8:$N$55,'Summary Dept Wise'!$F22) -> 0 | R22: =SUMIFS(Master!AI$8:AI$55,Master!$J$8:$J$55,'Summary Dept Wise'!$C22,Master!$M$8:$M$55,'Summary Dept Wise'!$E22,Master!$N$8:$N$55,'Summary Dept Wise'!$F22) -> 0 | S22: =SUMIFS(Master!AN$8:AN$55,Master!$J$8:$J$55,'Summary Dept Wise'!$C22,Master!$M$8:$M$55,'Summary Dept Wise'!$E22,Master!$N$8:$N$55,'Summary Dept Wise'!$F22) -> 0 | T22: =SUMIFS(Master!AO$8:AO$55,Master!$J$8:$J$55,'Summary Dept Wise'!$C22,Master!$M$8:$M$55,'Summary Dept Wise'!$E22,Master!$N$8:$N$55,'Summary Dept Wise'!$F22) -> 0 | U22: =SUMIFS(Master!AP$8:AP$55,Master!$J$8:$J$55,'Summary Dept Wise'!$C22,Master!$M$8:$M$55,'Summary Dept Wise'!$E22,Master!$N$8:$N$55,'Summary Dept Wise'!$F22) -> 0 | V22: =SUMIFS(Master!AQ$8:AQ$55,Master!$J$8:$J$55,'Summary Dept Wise'!$C22,Master!$M$8:$M$55,'Summary Dept Wise'!$E22,Master!$N$8:$N$55,'Summary Dept Wise'!$F22) -> 0 | W22: =SUMIFS(Master!AR$8:AR$55,Master!$J$8:$J$55,'Summary Dept Wise'!$C22,Master!$M$8:$M$55,'Summary Dept Wise'!$E22,Master!$N$8:$N$55,'Summary Dept Wise'!$F22) -> 0 | Y22: =SUMIFS(Master!AT$8:AT$55,Master!$J$8:$J$55,'Summary Dept Wise'!$C22,Master!$M$8:$M$55,'Summary Dept Wise'!$E22,Master!$N$8:$N$55,'Summary Dept Wise'!$F22) -> 0 | Z22: =SUM(X22:Y22) -> 0 | AA22: =SUMIFS(Master!AI$8:AI$55,Master!$J$8:$J$55,'Summary Dept Wise'!$C22,Master!$M$8:$M$55,'Summary Dept Wise'!$E22,Master!$N$8:$N$55,'Summary Dept Wise'!$F22,Master!$AV$8:$AV$55,"Paid") -> 0 | AB22: =+Z22-AA22 -> 0 | AC22: =SUMIFS(Master!BF$8:BF$55,Master!$J$8:$J$55,'Summary Dept Wise'!$C22,Master!$M$8:$M$55,'Summary Dept Wise'!$E22,Master!$N$8:$N$55,'Summary Dept Wise'!$F22) -> 0
C23: Production - Video | D23: =COUNTIFS(Master!$J$8:$J$55,'Summary Dept Wise'!$C23,Master!$M$8:$M$55,'Summary Dept Wise'!$E23,Master!$N$8:$N$55,'Summary Dept Wise'!$F23) -> 0 | E23: DD | F23: ALL | G23: =SUMIFS(Master!$P$8:$P$55,Master!$J$8:$J$55,'Summary Dept Wise'!$C23,Master!$M$8:$M$55,'Summary Dept Wise'!$E23,Master!$N$8:$N$55,'Summary Dept Wise'!$F23) -> 0 | H23: =SUMIFS(Master!$U$8:$U$55,Master!$J$8:$J$55,'Summary Dept Wise'!$C23,Master!$M$8:$M$55,'Summary Dept Wise'!$E23,Master!$N$8:$N$55,'Summary Dept Wise'!$F23) -> 0 | I23: =SUMIFS(Master!$V$8:$V$55,Master!$J$8:$J$55,'Summary Dept Wise'!$C23,Master!$M$8:$M$55,'Summary Dept Wise'!$E23,Master!$N$8:$N$55,'Summary Dept Wise'!$F23) -> 0 | J23: =SUMIFS(Master!$X$8:$X$55,Master!$J$8:$J$55,'Summary Dept Wise'!$C23,Master!$M$8:$M$55,'Summary Dept Wise'!$E23,Master!$N$8:$N$55,'Summary Dept Wise'!$F23) -> 0 | K23: =SUMIFS(Master!$Z$8:$Z$55,Master!$J$8:$J$55,'Summary Dept Wise'!$C23,Master!$M$8:$M$55,'Summary Dept Wise'!$E23,Master!$N$8:$N$55,'Summary Dept Wise'!$F23) -> 0 | L23: =SUMIFS(Master!AC$8:AC$55,Master!$J$8:$J$55,'Summary Dept Wise'!$C23,Master!$M$8:$M$55,'Summary Dept Wise'!$E23,Master!$N$8:$N$55,'Summary Dept Wise'!$F23) -> 0 | M23: =SUMIFS(Master!AD$8:AD$55,Master!$J$8:$J$55,'Summary Dept Wise'!$C23,Master!$M$8:$M$55,'Summary Dept Wise'!$E23,Master!$N$8:$N$55,'Summary Dept Wise'!$F23) -> 0 | N23: =SUMIFS(Master!AE$8:AE$55,Master!$J$8:$J$55,'Summary Dept Wise'!$C23,Master!$M$8:$M$55,'Summary Dept Wise'!$E23,Master!$N$8:$N$55,'Summary Dept Wise'!$F23) -> 0 | O23: =SUMIFS(Master!AF$8:AF$55,Master!$J$8:$J$55,'Summary Dept Wise'!$C23,Master!$M$8:$M$55,'Summary Dept Wise'!$E23,Master!$N$8:$N$55,'Summary Dept Wise'!$F23) -> 0 | P23: =SUMIFS(Master!AG$8:AG$55,Master!$J$8:$J$55,'Summary Dept Wise'!$C23,Master!$M$8:$M$55,'Summary Dept Wise'!$E23,Master!$N$8:$N$55,'Summary Dept Wise'!$F23) -> 0 | Q23: =SUMIFS(Master!AH$8:AH$55,Master!$J$8:$J$55,'Summary Dept Wise'!$C23,Master!$M$8:$M$55,'Summary Dept Wise'!$E23,Master!$N$8:$N$55,'Summary Dept Wise'!$F23) -> 0 | R23: =SUMIFS(Master!AI$8:AI$55,Master!$J$8:$J$55,'Summary Dept Wise'!$C23,Master!$M$8:$M$55,'Summary Dept Wise'!$E23,Master!$N$8:$N$55,'Summary Dept Wise'!$F23) -> 0 | S23: =SUMIFS(Master!AN$8:AN$55,Master!$J$8:$J$55,'Summary Dept Wise'!$C23,Master!$M$8:$M$55,'Summary Dept Wise'!$E23,Master!$N$8:$N$55,'Summary Dept Wise'!$F23) -> 0 | T23: =SUMIFS(Master!AO$8:AO$55,Master!$J$8:$J$55,'Summary Dept Wise'!$C23,Master!$M$8:$M$55,'Summary Dept Wise'!$E23,Master!$N$8:$N$55,'Summary Dept Wise'!$F23) -> 0 | U23: =SUMIFS(Master!AP$8:AP$55,Master!$J$8:$J$55,'Summary Dept Wise'!$C23,Master!$M$8:$M$55,'Summary Dept Wise'!$E23,Master!$N$8:$N$55,'Summary Dept Wise'!$F23) -> 0 | V23: =SUMIFS(Master!AQ$8:AQ$55,Master!$J$8:$J$55,'Summary Dept Wise'!$C23,Master!$M$8:$M$55,'Summary Dept Wise'!$E23,Master!$N$8:$N$55,'Summary Dept Wise'!$F23) -> 0 | W23: =SUMIFS(Master!AR$8:AR$55,Master!$J$8:$J$55,'Summary Dept Wise'!$C23,Master!$M$8:$M$55,'Summary Dept Wise'!$E23,Master!$N$8:$N$55,'Summary Dept Wise'!$F23) -> 0 | Y23: =SUMIFS(Master!AT$8:AT$55,Master!$J$8:$J$55,'Summary Dept Wise'!$C23,Master!$M$8:$M$55,'Summary Dept Wise'!$E23,Master!$N$8:$N$55,'Summary Dept Wise'!$F23) -> 0 | Z23: =SUM(X23:Y23) -> 0 | AA23: =SUMIFS(Master!AI$8:AI$55,Master!$J$8:$J$55,'Summary Dept Wise'!$C23,Master!$M$8:$M$55,'Summary Dept Wise'!$E23,Master!$N$8:$N$55,'Summary Dept Wise'!$F23,Master!$AV$8:$AV$55,"Paid") -> 0 | AB23: =+Z23-AA23 -> 0 | AC23: =SUMIFS(Master!BF$8:BF$55,Master!$J$8:$J$55,'Summary Dept Wise'!$C23,Master!$M$8:$M$55,'Summary Dept Wise'!$E23,Master!$N$8:$N$55,'Summary Dept Wise'!$F23) -> 0
C24: Production - Design | D24: =COUNTIFS(Master!$J$8:$J$55,'Summary Dept Wise'!$C24,Master!$M$8:$M$55,'Summary Dept Wise'!$E24,Master!$N$8:$N$55,'Summary Dept Wise'!$F24) -> 0 | E24: DD | F24: ALL | G24: =SUMIFS(Master!$P$8:$P$55,Master!$J$8:$J$55,'Summary Dept Wise'!$C24,Master!$M$8:$M$55,'Summary Dept Wise'!$E24,Master!$N$8:$N$55,'Summary Dept Wise'!$F24) -> 0 | H24: =SUMIFS(Master!$U$8:$U$55,Master!$J$8:$J$55,'Summary Dept Wise'!$C24,Master!$M$8:$M$55,'Summary Dept Wise'!$E24,Master!$N$8:$N$55,'Summary Dept Wise'!$F24) -> 0 | I24: =SUMIFS(Master!$V$8:$V$55,Master!$J$8:$J$55,'Summary Dept Wise'!$C24,Master!$M$8:$M$55,'Summary Dept Wise'!$E24,Master!$N$8:$N$55,'Summary Dept Wise'!$F24) -> 0 | J24: =SUMIFS(Master!$X$8:$X$55,Master!$J$8:$J$55,'Summary Dept Wise'!$C24,Master!$M$8:$M$55,'Summary Dept Wise'!$E24,Master!$N$8:$N$55,'Summary Dept Wise'!$F24) -> 0 | K24: =SUMIFS(Master!$Z$8:$Z$55,Master!$J$8:$J$55,'Summary Dept Wise'!$C24,Master!$M$8:$M$55,'Summary Dept Wise'!$E24,Master!$N$8:$N$55,'Summary Dept Wise'!$F24) -> 0 | L24: =SUMIFS(Master!AC$8:AC$55,Master!$J$8:$J$55,'Summary Dept Wise'!$C24,Master!$M$8:$M$55,'Summary Dept Wise'!$E24,Master!$N$8:$N$55,'Summary Dept Wise'!$F24) -> 0 | M24: =SUMIFS(Master!AD$8:AD$55,Master!$J$8:$J$55,'Summary Dept Wise'!$C24,Master!$M$8:$M$55,'Summary Dept Wise'!$E24,Master!$N$8:$N$55,'Summary Dept Wise'!$F24) -> 0 | N24: =SUMIFS(Master!AE$8:AE$55,Master!$J$8:$J$55,'Summary Dept Wise'!$C24,Master!$M$8:$M$55,'Summary Dept Wise'!$E24,Master!$N$8:$N$55,'Summary Dept Wise'!$F24) -> 0 | O24: =SUMIFS(Master!AF$8:AF$55,Master!$J$8:$J$55,'Summary Dept Wise'!$C24,Master!$M$8:$M$55,'Summary Dept Wise'!$E24,Master!$N$8:$N$55,'Summary Dept Wise'!$F24) -> 0 | P24: =SUMIFS(Master!AG$8:AG$55,Master!$J$8:$J$55,'Summary Dept Wise'!$C24,Master!$M$8:$M$55,'Summary Dept Wise'!$E24,Master!$N$8:$N$55,'Summary Dept Wise'!$F24) -> 0 | Q24: =SUMIFS(Master!AH$8:AH$55,Master!$J$8:$J$55,'Summary Dept Wise'!$C24,Master!$M$8:$M$55,'Summary Dept Wise'!$E24,Master!$N$8:$N$55,'Summary Dept Wise'!$F24) -> 0 | R24: =SUMIFS(Master!AI$8:AI$55,Master!$J$8:$J$55,'Summary Dept Wise'!$C24,Master!$M$8:$M$55,'Summary Dept Wise'!$E24,Master!$N$8:$N$55,'Summary Dept Wise'!$F24) -> 0 | S24: =SUMIFS(Master!AN$8:AN$55,Master!$J$8:$J$55,'Summary Dept Wise'!$C24,Master!$M$8:$M$55,'Summary Dept Wise'!$E24,Master!$N$8:$N$55,'Summary Dept Wise'!$F24) -> 0 | T24: =SUMIFS(Master!AO$8:AO$55,Master!$J$8:$J$55,'Summary Dept Wise'!$C24,Master!$M$8:$M$55,'Summary Dept Wise'!$E24,Master!$N$8:$N$55,'Summary Dept Wise'!$F24) -> 0 | U24: =SUMIFS(Master!AP$8:AP$55,Master!$J$8:$J$55,'Summary Dept Wise'!$C24,Master!$M$8:$M$55,'Summary Dept Wise'!$E24,Master!$N$8:$N$55,'Summary Dept Wise'!$F24) -> 0 | V24: =SUMIFS(Master!AQ$8:AQ$55,Master!$J$8:$J$55,'Summary Dept Wise'!$C24,Master!$M$8:$M$55,'Summary Dept Wise'!$E24,Master!$N$8:$N$55,'Summary Dept Wise'!$F24) -> 0 | W24: =SUMIFS(Master!AR$8:AR$55,Master!$J$8:$J$55,'Summary Dept Wise'!$C24,Master!$M$8:$M$55,'Summary Dept Wise'!$E24,Master!$N$8:$N$55,'Summary Dept Wise'!$F24) -> 0 | X24: =SUM(S24:W24) -> 0 | Y24: =SUMIFS(Master!AT$8:AT$55,Master!$J$8:$J$55,'Summary Dept Wise'!$C24,Master!$M$8:$M$55,'Summary Dept Wise'!$E24,Master!$N$8:$N$55,'Summary Dept Wise'!$F24) -> 0 | Z24: =SUM(X24:Y24) -> 0 | AA24: =SUMIFS(Master!AI$8:AI$55,Master!$J$8:$J$55,'Summary Dept Wise'!$C24,Master!$M$8:$M$55,'Summary Dept Wise'!$E24,Master!$N$8:$N$55,'Summary Dept Wise'!$F24,Master!$AV$8:$AV$55,"Paid") -> 0 | AB24: =+Z24-AA24 -> 0 | AC24: =SUMIFS(Master!BF$8:BF$55,Master!$J$8:$J$55,'Summary Dept Wise'!$C24,Master!$M$8:$M$55,'Summary Dept Wise'!$E24,Master!$N$8:$N$55,'Summary Dept Wise'!$F24) -> 0
C25: Marketing | D25: =COUNTIFS(Master!$J$8:$J$55,'Summary Dept Wise'!$C25,Master!$M$8:$M$55,'Summary Dept Wise'!$E25,Master!$N$8:$N$55,'Summary Dept Wise'!$F25) -> 0 | E25: DD | F25: ALL | G25: =SUMIFS(Master!$P$8:$P$55,Master!$J$8:$J$55,'Summary Dept Wise'!$C25,Master!$M$8:$M$55,'Summary Dept Wise'!$E25,Master!$N$8:$N$55,'Summary Dept Wise'!$F25) -> 0 | H25: =SUMIFS(Master!$U$8:$U$55,Master!$J$8:$J$55,'Summary Dept Wise'!$C25,Master!$M$8:$M$55,'Summary Dept Wise'!$E25,Master!$N$8:$N$55,'Summary Dept Wise'!$F25) -> 0 | I25: =SUMIFS(Master!$V$8:$V$55,Master!$J$8:$J$55,'Summary Dept Wise'!$C25,Master!$M$8:$M$55,'Summary Dept Wise'!$E25,Master!$N$8:$N$55,'Summary Dept Wise'!$F25) -> 0 | J25: =SUMIFS(Master!$X$8:$X$55,Master!$J$8:$J$55,'Summary Dept Wise'!$C25,Master!$M$8:$M$55,'Summary Dept Wise'!$E25,Master!$N$8:$N$55,'Summary Dept Wise'!$F25) -> 0 | K25: =SUMIFS(Master!$Z$8:$Z$55,Master!$J$8:$J$55,'Summary Dept Wise'!$C25,Master!$M$8:$M$55,'Summary Dept Wise'!$E25,Master!$N$8:$N$55,'Summary Dept Wise'!$F25) -> 0 | L25: =SUMIFS(Master!AC$8:AC$55,Master!$J$8:$J$55,'Summary Dept Wise'!$C25,Master!$M$8:$M$55,'Summary Dept Wise'!$E25,Master!$N$8:$N$55,'Summary Dept Wise'!$F25) -> 0 | M25: =SUMIFS(Master!AD$8:AD$55,Master!$J$8:$J$55,'Summary Dept Wise'!$C25,Master!$M$8:$M$55,'Summary Dept Wise'!$E25,Master!$N$8:$N$55,'Summary Dept Wise'!$F25) -> 0 | N25: =SUMIFS(Master!AE$8:AE$55,Master!$J$8:$J$55,'Summary Dept Wise'!$C25,Master!$M$8:$M$55,'Summary Dept Wise'!$E25,Master!$N$8:$N$55,'Summary Dept Wise'!$F25) -> 0 | O25: =SUMIFS(Master!AF$8:AF$55,Master!$J$8:$J$55,'Summary Dept Wise'!$C25,Master!$M$8:$M$55,'Summary Dept Wise'!$E25,Master!$N$8:$N$55,'Summary Dept Wise'!$F25) -> 0 | P25: =SUMIFS(Master!AG$8:AG$55,Master!$J$8:$J$55,'Summary Dept Wise'!$C25,Master!$M$8:$M$55,'Summary Dept Wise'!$E25,Master!$N$8:$N$55,'Summary Dept Wise'!$F25) -> 0 | Q25: =SUMIFS(Master!AH$8:AH$55,Master!$J$8:$J$55,'Summary Dept Wise'!$C25,Master!$M$8:$M$55,'Summary Dept Wise'!$E25,Master!$N$8:$N$55,'Summary Dept Wise'!$F25) -> 0 | R25: =SUMIFS(Master!AI$8:AI$55,Master!$J$8:$J$55,'Summary Dept Wise'!$C25,Master!$M$8:$M$55,'Summary Dept Wise'!$E25,Master!$N$8:$N$55,'Summary Dept Wise'!$F25) -> 0 | S25: =SUMIFS(Master!AN$8:AN$55,Master!$J$8:$J$55,'Summary Dept Wise'!$C25,Master!$M$8:$M$55,'Summary Dept Wise'!$E25,Master!$N$8:$N$55,'Summary Dept Wise'!$F25) -> 0 | T25: =SUMIFS(Master!AO$8:AO$55,Master!$J$8:$J$55,'Summary Dept Wise'!$C25,Master!$M$8:$M$55,'Summary Dept Wise'!$E25,Master!$N$8:$N$55,'Summary Dept Wise'!$F25) -> 0 | U25: =SUMIFS(Master!AP$8:AP$55,Master!$J$8:$J$55,'Summary Dept Wise'!$C25,Master!$M$8:$M$55,'Summary Dept Wise'!$E25,Master!$N$8:$N$55,'Summary Dept Wise'!$F25) -> 0 | V25: =SUMIFS(Master!AQ$8:AQ$55,Master!$J$8:$J$55,'Summary Dept Wise'!$C25,Master!$M$8:$M$55,'Summary Dept Wise'!$E25,Master!$N$8:$N$55,'Summary Dept Wise'!$F25) -> 0 | W25: =SUMIFS(Master!AR$8:AR$55,Master!$J$8:$J$55,'Summary Dept Wise'!$C25,Master!$M$8:$M$55,'Summary Dept Wise'!$E25,Master!$N$8:$N$55,'Summary Dept Wise'!$F25) -> 0 | Y25: =SUMIFS(Master!AT$8:AT$55,Master!$J$8:$J$55,'Summary Dept Wise'!$C25,Master!$M$8:$M$55,'Summary Dept Wise'!$E25,Master!$N$8:$N$55,'Summary Dept Wise'!$F25) -> 0 | Z25: =SUM(X25:Y25) -> 0 | AA25: =SUMIFS(Master!AI$8:AI$55,Master!$J$8:$J$55,'Summary Dept Wise'!$C25,Master!$M$8:$M$55,'Summary Dept Wise'!$E25,Master!$N$8:$N$55,'Summary Dept Wise'!$F25,Master!$AV$8:$AV$55,"Paid") -> 0 | AB25: =+Z25-AA25 -> 0 | AC25: =SUMIFS(Master!BF$8:BF$55,Master!$J$8:$J$55,'Summary Dept Wise'!$C25,Master!$M$8:$M$55,'Summary Dept Wise'!$E25,Master!$N$8:$N$55,'Summary Dept Wise'!$F25) -> 0
D26: =SUBTOTAL(9,D22:D25) -> 0 | F26: =G26/$G$69 -> 0 | G26: =SUBTOTAL(9,G22:G25) -> 0 | H26: =SUBTOTAL(9,H22:H25) -> 0 | I26: =SUBTOTAL(9,I22:I25) -> 0 | J26: =SUBTOTAL(9,J22:J25) -> 0 | K26: =SUBTOTAL(9,K22:K25) -> 0 | L26: =SUBTOTAL(9,L22:L25) -> 0 | M26: =SUBTOTAL(9,M22:M25) -> 0 | N26: =SUBTOTAL(9,N22:N25) -> 0 | ... AC26: =SUBTOTAL(9,AC22:AC25) -> 0
C28: (PKR) | D28: =SUBTOTAL(9,D14:D27) -> 2 | F28: =G28/$G$69 -> 0.085616438 | G28: =SUBTOTAL(9,G14:G27) -> 275000 | H28: =SUBTOTAL(9,H14:H27) -> 275000 | I28: =SUBTOTAL(9,I14:I27) -> 0 | J28: =SUBTOTAL(9,J14:J27) -> 0 | K28: =SUBTOTAL(9,K14:K27) -> 28571.429 | L28: =SUBTOTAL(9,L14:L27) -> 0 | M28: =SUBTOTAL(9,M14:M27) -> 246428.57 | N28: =SUBTOTAL(9,N14:N27) -> 0 | ... W28: =SUBTOTAL(9,W14:W27) -> 0 | Y28: =SUBTOTAL(9,Y14:Y27) -> 0 | Z28: =SUBTOTAL(9,Z14:Z27) -> 246428.57 | AA28: =SUBTOTAL(9,AA14:AA27) -> 0 | AB28: =SUBTOTAL(9,AB14:AB27) -> 246428.57 | AC28: =SUBTOTAL(9,AC14:AC27) -> 0
C29: (USD) | G29: =+G28/$H$1 -> 996.37681 | H29: =+H28/$H$1 -> 996.37681 | I29: =+I28/$H$1 -> 0 | J29: =+J28/$H$1 -> 0 | K29: =+K28/$H$1 -> 103.51967 | L29: =+L28/$H$1 -> 0 | M29: =+M28/$H$1 -> 892.85714 | N29: =+N28/$H$1 -> 0 | ... W29: =+W28/$H$1 -> 0 | Y29: =+Y28/$H$1 -> 0 | Z29: =+Z28/$H$1 -> 892.85714 | AA29: =+AA28/$H$1 -> 0 | AB29: =+AB28/$H$1 -> 892.85714 | AC29: =+AC28/$H$1 -> 0
B31: HARDWARE
B32: Support
C33: Data Analysis | D33: =COUNTIFS(Master!$J$8:$J$55,'Summary Dept Wise'!$C33,Master!$M$8:$M$55,'Summary Dept Wise'!$E33,Master!$N$8:$N$55,'Summary Dept Wise'!$F33) -> 8 | E33: HW | F33: ALL | G33: =SUMIFS(Master!$P$8:$P$55,Master!$J$8:$J$55,'Summary Dept Wise'!$C33,Master!$M$8:$M$55,'Summary Dept Wise'!$E33,Master!$N$8:$N$55,'Summary Dept Wise'!$F33) -> 240000 | H33: =SUMIFS(Master!$U$8:$U$55,Master!$J$8:$J$55,'Summary Dept Wise'!$C33,Master!$M$8:$M$55,'Summary Dept Wise'!$E33,Master!$N$8:$N$55,'Summary Dept Wise'!$F33) -> 240000 | I33: =SUMIFS(Master!$V$8:$V$55,Master!$J$8:$J$55,'Summary Dept Wise'!$C33,Master!$M$8:$M$55,'Summary Dept Wise'!$E33,Master!$N$8:$N$55,'Summary Dept Wise'!$F33) -> 0 | J33: =SUMIFS(Master!$X$8:$X$55,Master!$J$8:$J$55,'Summary Dept Wise'!$C33,Master!$M$8:$M$55,'Summary Dept Wise'!$E33,Master!$N$8:$N$55,'Summary Dept Wise'!$F33) -> 0 | K33: =SUMIFS(Master!$Z$8:$Z$55,Master!$J$8:$J$55,'Summary Dept Wise'!$C33,Master!$M$8:$M$55,'Summary Dept Wise'!$E33,Master!$N$8:$N$55,'Summary Dept Wise'!$F33) -> 18421.053 | L33: =SUMIFS(Master!AC$8:AC$55,Master!$J$8:$J$55,'Summary Dept Wise'!$C33,Master!$M$8:$M$55,'Summary Dept Wise'!$E33,Master!$N$8:$N$55,'Summary Dept Wise'!$F33) -> 0 | M33: =SUMIFS(Master!AD$8:AD$55,Master!$J$8:$J$55,'Summary Dept Wise'!$C33,Master!$M$8:$M$55,'Summary Dept Wise'!$E33,Master!$N$8:$N$55,'Summary Dept Wise'!$F33) -> 221578.95 | N33: =SUMIFS(Master!AE$8:AE$55,Master!$J$8:$J$55,'Summary Dept Wise'!$C33,Master!$M$8:$M$55,'Summary Dept Wise'!$E33,Master!$N$8:$N$55,'Summary Dept Wise'!$F33) -> 0 | O33: =SUMIFS(Master!AF$8:AF$55,Master!$J$8:$J$55,'Summary Dept Wise'!$C33,Master!$M$8:$M$55,'Summary Dept Wise'!$E33,Master!$N$8:$N$55,'Summary Dept Wise'!$F33) -> 0 | P33: =SUMIFS(Master!AG$8:AG$55,Master!$J$8:$J$55,'Summary Dept Wise'!$C33,Master!$M$8:$M$55,'Summary Dept Wise'!$E33,Master!$N$8:$N$55,'Summary Dept Wise'!$F33) -> 0 | Q33: =SUMIFS(Master!AH$8:AH$55,Master!$J$8:$J$55,'Summary Dept Wise'!$C33,Master!$M$8:$M$55,'Summary Dept Wise'!$E33,Master!$N$8:$N$55,'Summary Dept Wise'!$F33) -> 5000 | R33: =SUMIFS(Master!AI$8:AI$55,Master!$J$8:$J$55,'Summary Dept Wise'!$C33,Master!$M$8:$M$55,'Summary Dept Wise'!$E33,Master!$N$8:$N$55,'Summary Dept Wise'!$F33) -> 216578.95 | S33: =SUMIFS(Master!AN$8:AN$55,Master!$J$8:$J$55,'Summary Dept Wise'!$C33,Master!$M$8:$M$55,'Summary Dept Wise'!$E33,Master!$N$8:$N$55,'Summary Dept Wise'!$F33) -> 145000 | T33: =SUMIFS(Master!AO$8:AO$55,Master!$J$8:$J$55,'Summary Dept Wise'!$C33,Master!$M$8:$M$55,'Summary Dept Wise'!$E33,Master!$N$8:$N$55,'Summary Dept Wise'!$F33) -> 0 | U33: =SUMIFS(Master!AP$8:AP$55,Master!$J$8:$J$55,'Summary Dept Wise'!$C33,Master!$M$8:$M$55,'Summary Dept Wise'!$E33,Master!$N$8:$N$55,'Summary Dept Wise'!$F33) -> 0 | V33: =SUMIFS(Master!AQ$8:AQ$55,Master!$J$8:$J$55,'Summary Dept Wise'!$C33,Master!$M$8:$M$55,'Summary Dept Wise'!$E33,Master!$N$8:$N$55,'Summary Dept Wise'!$F33) -> 40000 | W33: =SUMIFS(Master!AR$8:AR$55,Master!$J$8:$J$55,'Summary Dept Wise'!$C33,Master!$M$8:$M$55,'Summary Dept Wise'!$E33,Master!$N$8:$N$55,'Summary Dept Wise'!$F33) -> 31578.947 | X33: =SUM(S33:W33) -> 216578.95 | Y33: =SUMIFS(Master!AT$8:AT$55,Master!$J$8:$J$55,'Summary Dept Wise'!$C33,Master!$M$8:$M$55,'Summary Dept Wise'!$E33,Master!$N$8:$N$55,'Summary Dept Wise'!$F33) -> 0 | Z33: =SUM(X33:Y33) -> 216578.95 | AA33: =SUMIFS(Master!AI$8:AI$55,Master!$J$8:$J$55,'Summary Dept Wise'!$C33,Master!$M$8:$M$55,'Summary Dept Wise'!$E33,Master!$N$8:$N$55,'Summary Dept Wise'!$F33,Master!$AV$8:$AV$55,"Paid") -> 161578.95 | AB33: =+Z33-AA33 -> 55000 | AC33: =SUMIFS(Master!BF$8:BF$55,Master!$J$8:$J$55,'Summary Dept Wise'!$C33,Master!$M$8:$M$55,'Summary Dept Wise'!$E33,Master!$N$8:$N$55,'Summary Dept Wise'!$F33) -> 0
C34: Marketing - SEO | D34: =COUNTIFS(Master!$J$8:$J$55,'Summary Dept Wise'!$C34,Master!$M$8:$M$55,'Summary Dept Wise'!$E34,Master!$N$8:$N$55,'Summary Dept Wise'!$F34) -> 4 | E34: HW | F34: ALL | G34: =SUMIFS(Master!$P$8:$P$55,Master!$J$8:$J$55,'Summary Dept Wise'!$C34,Master!$M$8:$M$55,'Summary Dept Wise'!$E34,Master!$N$8:$N$55,'Summary Dept Wise'!$F34) -> 130000 | H34: =SUMIFS(Master!$U$8:$U$55,Master!$J$8:$J$55,'Summary Dept Wise'!$C34,Master!$M$8:$M$55,'Summary Dept Wise'!$E34,Master!$N$8:$N$55,'Summary Dept Wise'!$F34) -> 130000 | I34: =SUMIFS(Master!$V$8:$V$55,Master!$J$8:$J$55,'Summary Dept Wise'!$C34,Master!$M$8:$M$55,'Summary Dept Wise'!$E34,Master!$N$8:$N$55,'Summary Dept Wise'!$F34) -> 0 | J34: =SUMIFS(Master!$X$8:$X$55,Master!$J$8:$J$55,'Summary Dept Wise'!$C34,Master!$M$8:$M$55,'Summary Dept Wise'!$E34,Master!$N$8:$N$55,'Summary Dept Wise'!$F34) -> 0 | K34: =SUMIFS(Master!$Z$8:$Z$55,Master!$J$8:$J$55,'Summary Dept Wise'!$C34,Master!$M$8:$M$55,'Summary Dept Wise'!$E34,Master!$N$8:$N$55,'Summary Dept Wise'!$F34) -> 32368.421 | L34: =SUMIFS(Master!AC$8:AC$55,Master!$J$8:$J$55,'Summary Dept Wise'!$C34,Master!$M$8:$M$55,'Summary Dept Wise'!$E34,Master!$N$8:$N$55,'Summary Dept Wise'!$F34) -> 2192.9825 | M34: =SUMIFS(Master!AD$8:AD$55,Master!$J$8:$J$55,'Summary Dept Wise'!$C34,Master!$M$8:$M$55,'Summary Dept Wise'!$E34,Master!$N$8:$N$55,'Summary Dept Wise'!$F34) -> 95438.596 | N34: =SUMIFS(Master!AE$8:AE$55,Master!$J$8:$J$55,'Summary Dept Wise'!$C34,Master!$M$8:$M$55,'Summary Dept Wise'!$E34,Master!$N$8:$N$55,'Summary Dept Wise'!$F34) -> 0 | O34: =SUMIFS(Master!AF$8:AF$55,Master!$J$8:$J$55,'Summary Dept Wise'!$C34,Master!$M$8:$M$55,'Summary Dept Wise'!$E34,Master!$N$8:$N$55,'Summary Dept Wise'!$F34) -> 0 | P34: =SUMIFS(Master!AG$8:AG$55,Master!$J$8:$J$55,'Summary Dept Wise'!$C34,Master!$M$8:$M$55,'Summary Dept Wise'!$E34,Master!$N$8:$N$55,'Summary Dept Wise'!$F34) -> 0 | Q34: =SUMIFS(Master!AH$8:AH$55,Master!$J$8:$J$55,'Summary Dept Wise'!$C34,Master!$M$8:$M$55,'Summary Dept Wise'!$E34,Master!$N$8:$N$55,'Summary Dept Wise'!$F34) -> 0 | R34: =SUMIFS(Master!AI$8:AI$55,Master!$J$8:$J$55,'Summary Dept Wise'!$C34,Master!$M$8:$M$55,'Summary Dept Wise'!$E34,Master!$N$8:$N$55,'Summary Dept Wise'!$F34) -> 95438.596 | S34: =SUMIFS(Master!AN$8:AN$55,Master!$J$8:$J$55,'Summary Dept Wise'!$C34,Master!$M$8:$M$55,'Summary Dept Wise'!$E34,Master!$N$8:$N$55,'Summary Dept Wise'!$F34) -> 50000 | T34: =SUMIFS(Master!AO$8:AO$55,Master!$J$8:$J$55,'Summary Dept Wise'!$C34,Master!$M$8:$M$55,'Summary Dept Wise'!$E34,Master!$N$8:$N$55,'Summary Dept Wise'!$F34) -> 0 | U34: =SUMIFS(Master!AP$8:AP$55,Master!$J$8:$J$55,'Summary Dept Wise'!$C34,Master!$M$8:$M$55,'Summary Dept Wise'!$E34,Master!$N$8:$N$55,'Summary Dept Wise'!$F34) -> 0 | V34: =SUMIFS(Master!AQ$8:AQ$55,Master!$J$8:$J$55,'Summary Dept Wise'!$C34,Master!$M$8:$M$55,'Summary Dept Wise'!$E34,Master!$N$8:$N$55,'Summary Dept Wise'!$F34) -> 20000 | W34: =SUMIFS(Master!AR$8:AR$55,Master!$J$8:$J$55,'Summary Dept Wise'!$C34,Master!$M$8:$M$55,'Summary Dept Wise'!$E34,Master!$N$8:$N$55,'Summary Dept Wise'!$F34) -> 0 | X34: =SUM(S34:W34) -> 70000 | Y34: =SUMIFS(Master!AT$8:AT$55,Master!$J$8:$J$55,'Summary Dept Wise'!$C34,Master!$M$8:$M$55,'Summary Dept Wise'!$E34,Master!$N$8:$N$55,'Summary Dept Wise'!$F34) -> 25438.596 | Z34: =SUM(X34:Y34) -> 95438.596 | AA34: =SUMIFS(Master!AI$8:AI$55,Master!$J$8:$J$55,'Summary Dept Wise'!$C34,Master!$M$8:$M$55,'Summary Dept Wise'!$E34,Master!$N$8:$N$55,'Summary Dept Wise'!$F34,Master!$AV$8:$AV$55,"Paid") -> 0 | AB34: =+Z34-AA34 -> 95438.596 | AC34: =SUMIFS(Master!BF$8:BF$55,Master!$J$8:$J$55,'Summary Dept Wise'!$C34,Master!$M$8:$M$55,'Summary Dept Wise'!$E34,Master!$N$8:$N$55,'Summary Dept Wise'!$F34) -> 0
C35: Marketing | D35: =COUNTIFS(Master!$J$8:$J$55,'Summary Dept Wise'!$C35,Master!$M$8:$M$55,'Summary Dept Wise'!$E35,Master!$N$8:$N$55,'Summary Dept Wise'!$F35) -> 1 | E35: HW | F35: ALL | G35: =SUMIFS(Master!$P$8:$P$55,Master!$J$8:$J$55,'Summary Dept Wise'!$C35,Master!$M$8:$M$55,'Summary Dept Wise'!$E35,Master!$N$8:$N$55,'Summary Dept Wise'!$F35) -> 200000 | H35: =SUMIFS(Master!$U$8:$U$55,Master!$J$8:$J$55,'Summary Dept Wise'!$C35,Master!$M$8:$M$55,'Summary Dept Wise'!$E35,Master!$N$8:$N$55,'Summary Dept Wise'!$F35) -> 275000 | I35: =SUMIFS(Master!$V$8:$V$55,Master!$J$8:$J$55,'Summary Dept Wise'!$C35,Master!$M$8:$M$55,'Summary Dept Wise'!$E35,Master!$N$8:$N$55,'Summary Dept Wise'!$F35) -> 0 | J35: =SUMIFS(Master!$X$8:$X$55,Master!$J$8:$J$55,'Summary Dept Wise'!$C35,Master!$M$8:$M$55,'Summary Dept Wise'!$E35,Master!$N$8:$N$55,'Summary Dept Wise'!$F35) -> 0 | K35: =SUMIFS(Master!$Z$8:$Z$55,Master!$J$8:$J$55,'Summary Dept Wise'!$C35,Master!$M$8:$M$55,'Summary Dept Wise'!$E35,Master!$N$8:$N$55,'Summary Dept Wise'!$F35) -> 0 | L35: =SUMIFS(Master!AC$8:AC$55,Master!$J$8:$J$55,'Summary Dept Wise'!$C35,Master!$M$8:$M$55,'Summary Dept Wise'!$E35,Master!$N$8:$N$55,'Summary Dept Wise'!$F35) -> 0 | M35: =SUMIFS(Master!AD$8:AD$55,Master!$J$8:$J$55,'Summary Dept Wise'!$C35,Master!$M$8:$M$55,'Summary Dept Wise'!$E35,Master!$N$8:$N$55,'Summary Dept Wise'!$F35) -> 275000 | N35: =SUMIFS(Master!AE$8:AE$55,Master!$J$8:$J$55,'Summary Dept Wise'!$C35,Master!$M$8:$M$55,'Summary Dept Wise'!$E35,Master!$N$8:$N$55,'Summary Dept Wise'!$F35) -> 9790 | O35: =SUMIFS(Master!AF$8:AF$55,Master!$J$8:$J$55,'Summary Dept Wise'!$C35,Master!$M$8:$M$55,'Summary Dept Wise'!$E35,Master!$N$8:$N$55,'Summary Dept Wise'!$F35) -> 250 | P35: =SUMIFS(Master!AG$8:AG$55,Master!$J$8:$J$55,'Summary Dept Wise'!$C35,Master!$M$8:$M$55,'Summary Dept Wise'!$E35,Master!$N$8:$N$55,'Summary Dept Wise'!$F35) -> 75000 | Q35: =SUMIFS(Master!AH$8:AH$55,Master!$J$8:$J$55,'Summary Dept Wise'!$C35,Master!$M$8:$M$55,'Summary Dept Wise'!$E35,Master!$N$8:$N$55,'Summary Dept Wise'!$F35) -> 0 | R35: =SUMIFS(Master!AI$8:AI$55,Master!$J$8:$J$55,'Summary Dept Wise'!$C35,Master!$M$8:$M$55,'Summary Dept Wise'!$E35,Master!$N$8:$N$55,'Summary Dept Wise'!$F35) -> 189960 | S35: =SUMIFS(Master!AN$8:AN$55,Master!$J$8:$J$55,'Summary Dept Wise'!$C35,Master!$M$8:$M$55,'Summary Dept Wise'!$E35,Master!$N$8:$N$55,'Summary Dept Wise'!$F35) -> 189960 | T35: =SUMIFS(Master!AO$8:AO$55,Master!$J$8:$J$55,'Summary Dept Wise'!$C35,Master!$M$8:$M$55,'Summary Dept Wise'!$E35,Master!$N$8:$N$55,'Summary Dept Wise'!$F35) -> 0 | U35: =SUMIFS(Master!AP$8:AP$55,Master!$J$8:$J$55,'Summary Dept Wise'!$C35,Master!$M$8:$M$55,'Summary Dept Wise'!$E35,Master!$N$8:$N$55,'Summary Dept Wise'!$F35) -> 0 | V35: =SUMIFS(Master!AQ$8:AQ$55,Master!$J$8:$J$55,'Summary Dept Wise'!$C35,Master!$M$8:$M$55,'Summary Dept Wise'!$E35,Master!$N$8:$N$55,'Summary Dept Wise'!$F35) -> 0 | W35: =SUMIFS(Master!AR$8:AR$55,Master!$J$8:$J$55,'Summary Dept Wise'!$C35,Master!$M$8:$M$55,'Summary Dept Wise'!$E35,Master!$N$8:$N$55,'Summary Dept Wise'!$F35) -> 0 | X35: =SUM(S35:W35) -> 189960 | Y35: =SUMIFS(Master!AT$8:AT$55,Master!$J$8:$J$55,'Summary Dept Wise'!$C35,Master!$M$8:$M$55,'Summary Dept Wise'!$E35,Master!$N$8:$N$55,'Summary Dept Wise'!$F35) -> 0 | Z35: =SUM(X35:Y35) -> 189960 | AA35: =SUMIFS(Master!AI$8:AI$55,Master!$J$8:$J$55,'Summary Dept Wise'!$C35,Master!$M$8:$M$55,'Summary Dept Wise'!$E35,Master!$N$8:$N$55,'Summary Dept Wise'!$F35,Master!$AV$8:$AV$55,"Paid") -> 0 | AB35: =+Z35-AA35 -> 189960 | AC35: =SUMIFS(Master!BF$8:BF$55,Master!$J$8:$J$55,'Summary Dept Wise'!$C35,Master!$M$8:$M$55,'Summary Dept Wise'!$E35,Master!$N$8:$N$55,'Summary Dept Wise'!$F35) -> 0
C36: Production | D36: =COUNTIFS(Master!$J$8:$J$55,'Summary Dept Wise'!$C36,Master!$M$8:$M$55,'Summary Dept Wise'!$E36,Master!$N$8:$N$55,'Summary Dept Wise'!$F36) -> 0 | E36: HW | F36: ALL | G36: =SUMIFS(Master!$P$8:$P$55,Master!$J$8:$J$55,'Summary Dept Wise'!$C36,Master!$M$8:$M$55,'Summary Dept Wise'!$E36,Master!$N$8:$N$55,'Summary Dept Wise'!$F36) -> 0 | H36: =SUMIFS(Master!$U$8:$U$55,Master!$J$8:$J$55,'Summary Dept Wise'!$C36,Master!$M$8:$M$55,'Summary Dept Wise'!$E36,Master!$N$8:$N$55,'Summary Dept Wise'!$F36) -> 0 | I36: =SUMIFS(Master!$V$8:$V$55,Master!$J$8:$J$55,'Summary Dept Wise'!$C36,Master!$M$8:$M$55,'Summary Dept Wise'!$E36,Master!$N$8:$N$55,'Summary Dept Wise'!$F36) -> 0 | J36: =SUMIFS(Master!$X$8:$X$55,Master!$J$8:$J$55,'Summary Dept Wise'!$C36,Master!$M$8:$M$55,'Summary Dept Wise'!$E36,Master!$N$8:$N$55,'Summary Dept Wise'!$F36) -> 0 | K36: =SUMIFS(Master!$Z$8:$Z$55,Master!$J$8:$J$55,'Summary Dept Wise'!$C36,Master!$M$8:$M$55,'Summary Dept Wise'!$E36,Master!$N$8:$N$55,'Summary Dept Wise'!$F36) -> 0 | L36: =SUMIFS(Master!AC$8:AC$55,Master!$J$8:$J$55,'Summary Dept Wise'!$C36,Master!$M$8:$M$55,'Summary Dept Wise'!$E36,Master!$N$8:$N$55,'Summary Dept Wise'!$F36) -> 0 | M36: =SUMIFS(Master!AD$8:AD$55,Master!$J$8:$J$55,'Summary Dept Wise'!$C36,Master!$M$8:$M$55,'Summary Dept Wise'!$E36,Master!$N$8:$N$55,'Summary Dept Wise'!$F36) -> 0 | N36: =SUMIFS(Master!AE$8:AE$55,Master!$J$8:$J$55,'Summary Dept Wise'!$C36,Master!$M$8:$M$55,'Summary Dept Wise'!$E36,Master!$N$8:$N$55,'Summary Dept Wise'!$F36) -> 0 | O36: =SUMIFS(Master!AF$8:AF$55,Master!$J$8:$J$55,'Summary Dept Wise'!$C36,Master!$M$8:$M$55,'Summary Dept Wise'!$E36,Master!$N$8:$N$55,'Summary Dept Wise'!$F36) -> 0 | P36: =SUMIFS(Master!AG$8:AG$55,Master!$J$8:$J$55,'Summary Dept Wise'!$C36,Master!$M$8:$M$55,'Summary Dept Wise'!$E36,Master!$N$8:$N$55,'Summary Dept Wise'!$F36) -> 0 | Q36: =SUMIFS(Master!AH$8:AH$55,Master!$J$8:$J$55,'Summary Dept Wise'!$C36,Master!$M$8:$M$55,'Summary Dept Wise'!$E36,Master!$N$8:$N$55,'Summary Dept Wise'!$F36) -> 0 | R36: =SUMIFS(Master!AI$8:AI$55,Master!$J$8:$J$55,'Summary Dept Wise'!$C36,Master!$M$8:$M$55,'Summary Dept Wise'!$E36,Master!$N$8:$N$55,'Summary Dept Wise'!$F36) -> 0 | S36: =SUMIFS(Master!AN$8:AN$55,Master!$J$8:$J$55,'Summary Dept Wise'!$C36,Master!$M$8:$M$55,'Summary Dept Wise'!$E36,Master!$N$8:$N$55,'Summary Dept Wise'!$F36) -> 0 | T36: =SUMIFS(Master!AO$8:AO$55,Master!$J$8:$J$55,'Summary Dept Wise'!$C36,Master!$M$8:$M$55,'Summary Dept Wise'!$E36,Master!$N$8:$N$55,'Summary Dept Wise'!$F36) -> 0 | U36: =SUMIFS(Master!AP$8:AP$55,Master!$J$8:$J$55,'Summary Dept Wise'!$C36,Master!$M$8:$M$55,'Summary Dept Wise'!$E36,Master!$N$8:$N$55,'Summary Dept Wise'!$F36) -> 0 | V36: =SUMIFS(Master!AQ$8:AQ$55,Master!$J$8:$J$55,'Summary Dept Wise'!$C36,Master!$M$8:$M$55,'Summary Dept Wise'!$E36,Master!$N$8:$N$55,'Summary Dept Wise'!$F36) -> 0 | W36: =SUMIFS(Master!AR$8:AR$55,Master!$J$8:$J$55,'Summary Dept Wise'!$C36,Master!$M$8:$M$55,'Summary Dept Wise'!$E36,Master!$N$8:$N$55,'Summary Dept Wise'!$F36) -> 0 | Y36: =SUMIFS(Master!AT$8:AT$55,Master!$J$8:$J$55,'Summary Dept Wise'!$C36,Master!$M$8:$M$55,'Summary Dept Wise'!$E36,Master!$N$8:$N$55,'Summary Dept Wise'!$F36) -> 0 | Z36: =SUM(X36:Y36) -> 0 | AA36: =SUMIFS(Master!AI$8:AI$55,Master!$J$8:$J$55,'Summary Dept Wise'!$C36,Master!$M$8:$M$55,'Summary Dept Wise'!$E36,Master!$N$8:$N$55,'Summary Dept Wise'!$F36,Master!$AV$8:$AV$55,"Paid") -> 0 | AB36: =+Z36-AA36 -> 0 | AC36: =SUMIFS(Master!BF$8:BF$55,Master!$J$8:$J$55,'Summary Dept Wise'!$C36,Master!$M$8:$M$55,'Summary Dept Wise'!$E36,Master!$N$8:$N$55,'Summary Dept Wise'!$F36) -> 0
